Workbook

Sheet Легенда
A1: Дорожная карта брокерского бизнеса — модель метрик (этап 1)
A3: Документ | B3: Модель метрик брокерского бизнеса — этап 1 дорожной карты проектов
A4: Версия | B4: v0.2 — в работе, метрики на согласовании
A5: Назначение | B5: Единая система метрик, связывающая управляемые драйверы с маржинальным доходом (МД). На этапе 2 каждая гипотеза ссылается на код драйвера, а её эффект переводится в деньги через лист «Чувствительность».
A6: Статус данных | B6: Значения вводных иллюстративные: условный брокер среднего размера, ориентиры — публичные брокеры (см. колонку «Источник / ориентир» на листе «Вводные» и отчёт с бенчмарками в репозитории). Перед выводами замените жёлтые ячейки фактом.
A7: Надёжность ориентиров | B7: Цифры бенчмарков получены из поисковых выдержек первоисточников: прямой доступ к отчётам компаний был закрыт. Перед внешним использованием сверить с документами.
A8: Единицы | B8: у.е. — условные денежные единицы; все суммы — за период (год).
A10: Этапы
A11: 1. Метрики | B11: Этот файл: дерево, паспорта, модель, чувствительность — в работе, метрики на согласовании
A12: 2. Гипотезы | B12: Шаблон карты гипотез, привязка к драйверам — следующий шаг
A13: 3. Трудозатраты | B13: Оценка гипотез — после этапа 2
A14: 4. Дорожная карта | B14: Приоритизация и раскладка по времени — после этапа 3
A16: Листы
A17: Сводка | B17: P&L по сегментам, ключевые KPI, топ-10 драйверов по ценности улучшения
A18: Дерево | B18: Иерархия метрик от МД до драйверов с текущими значениями
A19: Вводные | B19: Все допущения модели по сегментам — редактировать здесь
A20: Чувствительность | B20: Ценность улучшения каждого драйвера на 1% и на практический шаг (1 п.п., 1 б.п.) — в горизонтах «год 1» и «долгосрочно»
A21: Модель | B21: Расчёт по сегментам; справа сгруппированы технические сценарии для чувствительности
A22: Паспорта | B22: Определения, формулы, источники данных, владельцы; опережающие индикаторы, ограничители, внешние факторы
A24: Цвета
A25: Вводная | B25: Синий шрифт на жёлтом фоне — допущения, которые нужно заменить фактом
A26: Формула | B26: Чёрный шрифт — расчёт
A27: Ссылка | B27: Зелёный шрифт — значение с другого листа
A29: Принятые решения
A30: Рынок | B30: Универсальная модель без привязки к юрисдикции; бенчмарки — публичные брокеры
A31: Сегменты | B31: Масс-розница, состоятельные, институционалы и корпоративные; B2B вне периметра
A32: Верх дерева | B32: Маржинальный доход; регуляторные задачи — отдельный обязательный трек без денежной оценки
A33: Формат | B33: Excel-модель + описание в markdown в репозитории
A34: Горизонт оценки | B34: Оба горизонта; гипотезы ранжируются по долгосрочному эффекту, бюджет проверяется по году 1
A35: Клиент | B35: Фондированный — активы от ≈$100 в эквиваленте; активный — любая операция за месяц
A36: Продукты | B36: «Выделение сервисов в продукты» — внутренние сервисы со своим P&L; учитывается только эффект брокера, без эффектов для группы
A37: Ставки | B37: План строится на сценарии снижения ставок (RATE_SHIFT, по умолчанию −1 п.п.)
A38: Данные | B38: Работаем на ориентирах публичных брокеров; факт подставим позже
A39: Апгрейд МР → СК | B39: Отдельным драйвером не моделируется, считается внутри гипотез
A40: Срок карты | B40: 3 года по полугодиям
A42: Как пользоваться
A43: Шаг 1 | B43: Замените значения на листе «Вводные» фактическими данными по сегментам
A44: Шаг 2 | B44: Сверьте «Сводку» с управленческой отчётностью: ЧВ и МД по сегментам должны совпасть (±5%)
A45: Шаг 3 | B45: На листе «Чувствительность» — сколько МД даёт улучшение каждого драйвера
A46: Шаг 4 | B46: HORIZON на листе «Вводные» переключает «Сводку» и «Дерево»: 1 — год 1 (P&L плана), 2 — run-rate на конец года, 3 — долгосрочно (база = NEW ÷ CHURN). «Чувствительность» всегда показывает горизонты 1 и 3 рядом
A47: Шаг 5 | B47: RATE_SHIFT на листе «Вводные» задаёт сценарий ставок; PT_MRG и PT_FLOAT — какая доля сдвига переходит в ставки клиентам
A49: Ограничения
A50: Сегменты | B50: Независимы: переход клиентов между сегментами (апгрейд) пока не моделируется
A51: Эластичность | B51: Не учитывается: ценовые рычаги показаны при неизменных объёмах
A52: Линейность | B52: Модель линейна по каждому драйверу (кроме нагрузки на менеджера): эффект +5% = 5 × эффект +1%; совместные изменения дают небольшой перекрёстный эффект
A53: Периметр | B53: Постоянные расходы (ИТ-платформа, центральные функции, аренда) в МД не входят
A54: Горизонт | B54: Долгосрочный режим — упрощение: без дисконтирования и при неизменных драйверах; это ориентир для сравнения гипотез, а не прогноз

Sheet Сводка
A1: Сводка: экономика брокерского бизнеса по сегментам
A2: Значения иллюстративные до замены вводных фактическими данными. P&L и KPI — в режиме HORIZON (лист «Вводные»).
D3: Сдвиг ставок: | E3: =Вводные!$D$7 -> -0.01 | F3: Режим HORIZON: | G3: =Вводные!$D$6 -> 1
A4: Код | B4: P&L, у.е. за период | C4: Масс-розница | D4: Состоятельные | E4: Институционалы и корп. | F4: Итого | G4: Доля в ЧВ
A5: R1 | B5: Торговые комиссии (нетто) | C5: =INDEX(Модель!$E$8:$E$101,MATCH($A5,Модель!$A$8:$A$101,0)) -> 12268368 | D5: =INDEX(Модель!$F$8:$F$101,MATCH($A5,Модель!$A$8:$A$101,0)) -> 4188492 | E5: =INDEX(Модель!$G$8:$G$101,MATCH($A5,Модель!$A$8:$A$101,0)) -> 6020352 | F5: =INDEX(Модель!$H$8:$H$101,MATCH($A5,Модель!$A$8:$A$101,0)) -> 22477212 | G5: =IF($F$12<>0,F5/$F$12,0) -> 0.20602506
A6: R2 | B6: Маржинальное кредитование (нетто) | C6: =INDEX(Модель!$E$8:$E$101,MATCH($A6,Модель!$A$8:$A$101,0)) -> 10142500 | D6: =INDEX(Модель!$F$8:$F$101,MATCH($A6,Модель!$A$8:$A$101,0)) -> 6799500 | E6: =INDEX(Модель!$G$8:$G$101,MATCH($A6,Модель!$A$8:$A$101,0)) -> 6030000 | F6: =INDEX(Модель!$H$8:$H$101,MATCH($A6,Модель!$A$8:$A$101,0)) -> 22972000 | G6: =IF($F$12<>0,F6/$F$12,0) -> 0.21056026
A7: R3 | B7: Доход на свободные остатки (нетто) | C7: =INDEX(Модель!$E$8:$E$101,MATCH($A7,Модель!$A$8:$A$101,0)) -> 12171000 | D7: =INDEX(Модель!$F$8:$F$101,MATCH($A7,Модель!$A$8:$A$101,0)) -> 4835200 | E7: =INDEX(Модель!$G$8:$G$101,MATCH($A7,Модель!$A$8:$A$101,0)) -> 5025000 | F7: =INDEX(Модель!$H$8:$H$101,MATCH($A7,Модель!$A$8:$A$101,0)) -> 22031200 | G7: =IF($F$12<>0,F7/$F$12,0) -> 0.20193693
A8: R4 | B8: Конвертация валют | C8: =INDEX(Модель!$E$8:$E$101,MATCH($A8,Модель!$A$8:$A$101,0)) -> 3803437.5 | D8: =INDEX(Модель!$F$8:$F$101,MATCH($A8,Модель!$A$8:$A$101,0)) -> 2266500 | E8: =INDEX(Модель!$G$8:$G$101,MATCH($A8,Модель!$A$8:$A$101,0)) -> 804000 | F8: =INDEX(Модель!$H$8:$H$101,MATCH($A8,Модель!$A$8:$A$101,0)) -> 6873937.5 | G8: =IF($F$12<>0,F8/$F$12,0) -> 0.063006184
A9: R5 | B9: Размещения и продукты | C9: =INDEX(Модель!$E$8:$E$101,MATCH($A9,Модель!$A$8:$A$101,0)) -> 1217100 | D9: =INDEX(Модель!$F$8:$F$101,MATCH($A9,Модель!$A$8:$A$101,0)) -> 5076960 | E9: =INDEX(Модель!$G$8:$G$101,MATCH($A9,Модель!$A$8:$A$101,0)) -> 10050000 | F9: =INDEX(Модель!$H$8:$H$101,MATCH($A9,Модель!$A$8:$A$101,0)) -> 16344060 | G9: =IF($F$12<>0,F9/$F$12,0) -> 0.14980888
A10: R6 | B10: ДУ и консультирование | C10: =INDEX(Модель!$E$8:$E$101,MATCH($A10,Модель!$A$8:$A$101,0)) -> 811400 | D10: =INDEX(Модель!$F$8:$F$101,MATCH($A10,Модель!$A$8:$A$101,0)) -> 6044000 | E10: =INDEX(Модель!$G$8:$G$101,MATCH($A10,Модель!$A$8:$A$101,0)) -> 1507500 | F10: =INDEX(Модель!$H$8:$H$101,MATCH($A10,Модель!$A$8:$A$101,0)) -> 8362900 | G10: =IF($F$12<>0,F10/$F$12,0) -> 0.076653944
A11: R7 | B11: Подписки и сервисные комиссии | C11: =INDEX(Модель!$E$8:$E$101,MATCH($A11,Модель!$A$8:$A$101,0)) -> 3245600 | D11: =INDEX(Модель!$F$8:$F$101,MATCH($A11,Модель!$A$8:$A$101,0)) -> 3777500 | E11: =INDEX(Модель!$G$8:$G$101,MATCH($A11,Модель!$A$8:$A$101,0)) -> 3015000 | F11: =INDEX(Модель!$H$8:$H$101,MATCH($A11,Модель!$A$8:$A$101,0)) -> 10038100 | G11: =IF($F$12<>0,F11/$F$12,0) -> 0.092008747
A12: NR | B12: ЧВ — чистая выручка | C12: =INDEX(Модель!$E$8:$E$101,MATCH($A12,Модель!$A$8:$A$101,0)) -> 43659406 | D12: =INDEX(Модель!$F$8:$F$101,MATCH($A12,Модель!$A$8:$A$101,0)) -> 32988152 | E12: =INDEX(Модель!$G$8:$G$101,MATCH($A12,Модель!$A$8:$A$101,0)) -> 32451852 | F12: =INDEX(Модель!$H$8:$H$101,MATCH($A12,Модель!$A$8:$A$101,0)) -> 1.0909941e+08 | G12: =IF($F$12<>0,F12/$F$12,0) -> 1
A13: C1 | B13: Поддержка клиентов | C13: =INDEX(Модель!$E$8:$E$101,MATCH($A13,Модель!$A$8:$A$101,0)) -> 2535625 | D13: =INDEX(Модель!$F$8:$F$101,MATCH($A13,Модель!$A$8:$A$101,0)) -> 679950 | E13: =INDEX(Модель!$G$8:$G$101,MATCH($A13,Модель!$A$8:$A$101,0)) -> 144720 | F13: =INDEX(Модель!$H$8:$H$101,MATCH($A13,Модель!$A$8:$A$101,0)) -> 3360295 | G13: =IF($F$12<>0,F13/$F$12,0) -> 0.030800304
A14: C2 | B14: Онбординг и KYC | C14: =INDEX(Модель!$E$8:$E$101,MATCH($A14,Модель!$A$8:$A$101,0)) -> 1170000 | D14: =INDEX(Модель!$F$8:$F$101,MATCH($A14,Модель!$A$8:$A$101,0)) -> 54000 | E14: =INDEX(Модель!$G$8:$G$101,MATCH($A14,Модель!$A$8:$A$101,0)) -> 186000 | F14: =INDEX(Модель!$H$8:$H$101,MATCH($A14,Модель!$A$8:$A$101,0)) -> 1410000 | G14: =IF($F$12<>0,F14/$F$12,0) -> 0.012923993
A15: C3 | B15: Бэк-офис: ручные операции | C15: =INDEX(Модель!$E$8:$E$101,MATCH($A15,Модель!$A$8:$A$101,0)) -> 912825 | D15: =INDEX(Модель!$F$8:$F$101,MATCH($A15,Модель!$A$8:$A$101,0)) -> 566625 | E15: =INDEX(Модель!$G$8:$G$101,MATCH($A15,Модель!$A$8:$A$101,0)) -> 603000 | F15: =INDEX(Модель!$H$8:$H$101,MATCH($A15,Модель!$A$8:$A$101,0)) -> 2082450 | G15: =IF($F$12<>0,F15/$F$12,0) -> 0.019087638
A16: C4 | B16: Персональные менеджеры и покрытие | C16: =INDEX(Модель!$E$8:$E$101,MATCH($A16,Модель!$A$8:$A$101,0)) -> 0 | D16: =INDEX(Модель!$F$8:$F$101,MATCH($A16,Модель!$A$8:$A$101,0)) -> 6044000 | E16: =INDEX(Модель!$G$8:$G$101,MATCH($A16,Модель!$A$8:$A$101,0)) -> 4020000 | F16: =INDEX(Модель!$H$8:$H$101,MATCH($A16,Модель!$A$8:$A$101,0)) -> 10064000 | G16: =IF($F$12<>0,F16/$F$12,0) -> 0.092246145
... A22: CM | B22: МД — маржинальный доход | C22: =INDEX(Модель!$E$8:$E$101,MATCH($A22,Модель!$A$8:$A$101,0)) -> 31786706 | D22: =INDEX(Модель!$F$8:$F$101,MATCH($A22,Модель!$A$8:$A$101,0)) -> 23410277 | E22: =INDEX(Модель!$G$8:$G$101,MATCH($A22,Модель!$A$8:$A$101,0)) -> 26356132 | F22: =INDEX(Модель!$H$8:$H$101,MATCH($A22,Модель!$A$8:$A$101,0)) -> 81553114 | G22: =IF($F$12<>0,F22/$F$12,0) -> 0.74751197
A24: Код | B24: Ключевые показатели | C24: Масс-розница | D24: Состоятельные | E24: Институционалы и корп. | F24: Итого
A25: N_AVG | B25: Фондированные клиенты, среднее за период | C25: =INDEX(Модель!$E$8:$E$101,MATCH($A25,Модель!$A$8:$A$101,0)) -> 507125 | D25: =INDEX(Модель!$F$8:$F$101,MATCH($A25,Модель!$A$8:$A$101,0)) -> 15110 | E25: =INDEX(Модель!$G$8:$G$101,MATCH($A25,Модель!$A$8:$A$101,0)) -> 402 | F25: =INDEX(Модель!$H$8:$H$101,MATCH($A25,Модель!$A$8:$A$101,0)) -> 522637
A26: NEW | B26: Новые фондированные клиенты | C26: =INDEX(Модель!$E$8:$E$101,MATCH($A26,Модель!$A$8:$A$101,0)) -> 74250 | D26: =INDEX(Модель!$F$8:$F$101,MATCH($A26,Модель!$A$8:$A$101,0)) -> 1120 | E26: =INDEX(Модель!$G$8:$G$101,MATCH($A26,Модель!$A$8:$A$101,0)) -> 36 | F26: =INDEX(Модель!$H$8:$H$101,MATCH($A26,Модель!$A$8:$A$101,0)) -> 75406
A27: ACTIVE | B27: Активные клиенты (среднемесячно) | C27: =INDEX(Модель!$E$8:$E$101,MATCH($A27,Модель!$A$8:$A$101,0)) -> 177493.75 | D27: =INDEX(Модель!$F$8:$F$101,MATCH($A27,Модель!$A$8:$A$101,0)) -> 8310.5 | E27: =INDEX(Модель!$G$8:$G$101,MATCH($A27,Модель!$A$8:$A$101,0)) -> 321.6 | F27: =INDEX(Модель!$H$8:$H$101,MATCH($A27,Модель!$A$8:$A$101,0)) -> 186125.85
A28: AUC | B28: Активы клиентов, среднее за период | C28: =INDEX(Модель!$E$8:$E$101,MATCH($A28,Модель!$A$8:$A$101,0)) -> 4057000000 | D28: =INDEX(Модель!$F$8:$F$101,MATCH($A28,Модель!$A$8:$A$101,0)) -> 3022000000 | E28: =INDEX(Модель!$G$8:$G$101,MATCH($A28,Модель!$A$8:$A$101,0)) -> 10050000000 | F28: =INDEX(Модель!$H$8:$H$101,MATCH($A28,Модель!$A$8:$A$101,0)) -> 17129000000
A29: TURN | B29: Оборот клиентов за период | C29: =INDEX(Модель!$E$8:$E$101,MATCH($A29,Модель!$A$8:$A$101,0)) -> 10223640000 | D29: =INDEX(Модель!$F$8:$F$101,MATCH($A29,Модель!$A$8:$A$101,0)) -> 5235615000 | E29: =INDEX(Модель!$G$8:$G$101,MATCH($A29,Модель!$A$8:$A$101,0)) -> 50169600000 | F29: =INDEX(Модель!$H$8:$H$101,MATCH($A29,Модель!$A$8:$A$101,0)) -> 65628855000
A30: MPORT | B30: Маржинальный портфель, среднее за период | C30: =INDEX(Модель!$E$8:$E$101,MATCH($A30,Модель!$A$8:$A$101,0)) -> 202850000 | D30: =INDEX(Модель!$F$8:$F$101,MATCH($A30,Модель!$A$8:$A$101,0)) -> 226650000 | E30: =INDEX(Модель!$G$8:$G$101,MATCH($A30,Модель!$A$8:$A$101,0)) -> 402000000 | F30: =INDEX(Модель!$H$8:$H$101,MATCH($A30,Модель!$A$8:$A$101,0)) -> 831500000
A31: ARPU | B31: Чистая выручка на фондированного клиента | C31: =INDEX(Модель!$E$8:$E$101,MATCH($A31,Модель!$A$8:$A$101,0)) -> 86.092 | D31: =INDEX(Модель!$F$8:$F$101,MATCH($A31,Модель!$A$8:$A$101,0)) -> 2183.2 | E31: =INDEX(Модель!$G$8:$G$101,MATCH($A31,Модель!$A$8:$A$101,0)) -> 80726 | F31: =INDEX(Модель!$H$8:$H$101,MATCH($A31,Модель!$A$8:$A$101,0)) -> 208.74796
A32: YIELD | B32: Доходность активов клиентов | C32: =INDEX(Модель!$E$8:$E$101,MATCH($A32,Модель!$A$8:$A$101,0)) -> 107.615 | D32: =INDEX(Модель!$F$8:$F$101,MATCH($A32,Модель!$A$8:$A$101,0)) -> 109.16 | E32: =INDEX(Модель!$G$8:$G$101,MATCH($A32,Модель!$A$8:$A$101,0)) -> 32.2904 | F32: =INDEX(Модель!$H$8:$H$101,MATCH($A32,Модель!$A$8:$A$101,0)) -> 63.692807
A33: CM_MARGIN | B33: Маржинальность (МД ÷ ЧВ) | C33: =INDEX(Модель!$E$8:$E$101,MATCH($A33,Модель!$A$8:$A$101,0)) -> 0.72806089 | D33: =INDEX(Модель!$F$8:$F$101,MATCH($A33,Модель!$A$8:$A$101,0)) -> 0.70965712 | E33: =INDEX(Модель!$G$8:$G$101,MATCH($A33,Модель!$A$8:$A$101,0)) -> 0.81216111 | F33: =INDEX(Модель!$H$8:$H$101,MATCH($A33,Модель!$A$8:$A$101,0)) -> 0.74751197
A34: CM_PC | B34: МД на фондированного клиента | C34: =INDEX(Модель!$E$8:$E$101,MATCH($A34,Модель!$A$8:$A$101,0)) -> 62.680218 | D34: =INDEX(Модель!$F$8:$F$101,MATCH($A34,Модель!$A$8:$A$101,0)) -> 1549.3234 | E34: =INDEX(Модель!$G$8:$G$101,MATCH($A34,Модель!$A$8:$A$101,0)) -> 65562.517 | F34: =INDEX(Модель!$H$8:$H$101,MATCH($A34,Модель!$A$8:$A$101,0)) -> 156.0416
A35: LTV | B35: LTV — вклад клиента за срок жизни | C35: =INDEX(Модель!$E$8:$E$101,MATCH($A35,Модель!$A$8:$A$101,0)) -> 619.94422 | D35: =INDEX(Модель!$F$8:$F$101,MATCH($A35,Модель!$A$8:$A$101,0)) -> 27675.135 | E35: =INDEX(Модель!$G$8:$G$101,MATCH($A35,Модель!$A$8:$A$101,0)) -> 836322.51 | F35: =INDEX(Модель!$H$8:$H$101,MATCH($A35,Модель!$A$8:$A$101,0)) -> 1451.9604
A36: LTV_CAC | B36: LTV ÷ CAC | C36: =INDEX(Модель!$E$8:$E$101,MATCH($A36,Модель!$A$8:$A$101,0)) -> 7.7493027 | D36: =INDEX(Модель!$F$8:$F$101,MATCH($A36,Модель!$A$8:$A$101,0)) -> 18.45009 | E36: =INDEX(Модель!$G$8:$G$101,MATCH($A36,Модель!$A$8:$A$101,0)) -> 55.754834 | F36: =INDEX(Модель!$H$8:$H$101,MATCH($A36,Модель!$A$8:$A$101,0)) -> 13.417466
... A38: RATE_SHARE | B38: Доля ЧВ, зависящая от процентных ставок | C38: =INDEX(Модель!$E$8:$E$101,MATCH($A38,Модель!$A$8:$A$101,0)) -> 0.51108117 | D38: =INDEX(Модель!$F$8:$F$101,MATCH($A38,Модель!$A$8:$A$101,0)) -> 0.35269329 | E38: =INDEX(Модель!$G$8:$G$101,MATCH($A38,Модель!$A$8:$A$101,0)) -> 0.34065852 | F38: =INDEX(Модель!$H$8:$H$101,MATCH($A38,Модель!$A$8:$A$101,0)) -> 0.41249719
A40: Код | B40: Долгосрочный ориентир (горизонт 3: база = NEW ÷ CHURN) | C40: Масс-розница | D40: Состоятельные | E40: Институционалы и корп. | F40: Итого
A41: N_AVG | B41: Фондированные клиенты, среднее за период | C41: =INDEX(Модель!$J$16:$JA$16,MATCH("MR|BASE|3",Модель!$J$6:$JA$6,0)) -> 618750 | D41: =INDEX(Модель!$J$16:$JA$16,MATCH("AF|BASE|3",Модель!$J$6:$JA$6,0)) -> 18666.667 | E41: =INDEX(Модель!$J$16:$JA$16,MATCH("IC|BASE|3",Модель!$J$6:$JA$6,0)) -> 450 | F41: =SUM(C41:E41) -> 637866.67
A42: NR | B42: ЧВ — чистая выручка | C42: =INDEX(Модель!$J$65:$JA$65,MATCH("MR|BASE|3",Модель!$J$6:$JA$6,0)) -> 53269425 | D42: =INDEX(Модель!$J$65:$JA$65,MATCH("AF|BASE|3",Модель!$J$6:$JA$6,0)) -> 40753067 | E42: =INDEX(Модель!$J$65:$JA$65,MATCH("IC|BASE|3",Модель!$J$6:$JA$6,0)) -> 36326700 | F42: =SUM(C42:E42) -> 1.3034919e+08
A43: CM | B43: МД — маржинальный доход | C43: =INDEX(Модель!$J$91:$JA$91,MATCH("MR|BASE|3",Модель!$J$6:$JA$6,0)) -> 40414425 | D43: =INDEX(Модель!$J$91:$JA$91,MATCH("AF|BASE|3",Модель!$J$6:$JA$6,0)) -> 29352400 | E43: =INDEX(Модель!$J$91:$JA$91,MATCH("IC|BASE|3",Модель!$J$6:$JA$6,0)) -> 29613700 | F43: =SUM(C43:E43) -> 99380525
A45: Ранг | B45: Топ-10 объёмных и затратных драйверов: ценность улучшения на 1% | C45: Код | D45: ΔМД в год, долгосрочно | E45: ΔМД, год 1 | F45: Тип рычага | G45: Управляемость
A46: 1 | B46: =INDEX(Чувствительность!$B$5:$B$45,MATCH(LARGE(Чувствительность!$X$5:$X$45,1),Чувствительность!$X$5:$X$45,0)) -> Годовой отток фондированных клиентов (вывели активы ниже порога или закрыли счёт) | C46: =INDEX(Чувствительность!$A$5:$A$45,MATCH(LARGE(Чувствительность!$X$5:$X$45,1),Чувствительность!$X$5:$X$45,0)) -> CHURN | D46: =INDEX(Чувствительность!$Q$5:$Q$45,MATCH(LARGE(Чувствительность!$X$5:$X$45,1),Чувствительность!$X$5:$X$45,0)) -> 1106571 | E46: =INDEX(Чувствительность!$M$5:$M$45,MATCH(LARGE(Чувствительность!$X$5:$X$45,1),Чувствительность!$X$5:$X$45,0)) -> 41564.31 | F46: =INDEX(Чувствительность!$F$5:$F$45,MATCH(LARGE(Чувствительность!$X$5:$X$45,1),Чувствительность!$X$5:$X$45,0)) -> Объёмный | G46: =INDEX(Чувствительность!$E$5:$E$45,MATCH(LARGE(Чувствительность!$X$5:$X$45,1),Чувствительность!$X$5:$X$45,0)) -> Управляемый
A47: 2 | B47: =INDEX(Чувствительность!$B$5:$B$45,MATCH(LARGE(Чувствительность!$X$5:$X$45,2),Чувствительность!$X$5:$X$45,0)) -> Конверсия: открытый счёт → фондированный (первое пополнение) | C47: =INDEX(Чувствительность!$A$5:$A$45,MATCH(LARGE(Чувствительность!$X$5:$X$45,2),Чувствительность!$X$5:$X$45,0)) -> CR_FUND | D47: =INDEX(Чувствительность!$Q$5:$Q$45,MATCH(LARGE(Чувствительность!$X$5:$X$45,2),Чувствительность!$X$5:$X$45,0)) -> 1013905.3 | E47: =INDEX(Чувствительность!$M$5:$M$45,MATCH(LARGE(Чувствительность!$X$5:$X$45,2),Чувствительность!$X$5:$X$45,0)) -> -31333.545 | F47: =INDEX(Чувствительность!$F$5:$F$45,MATCH(LARGE(Чувствительность!$X$5:$X$45,2),Чувствительность!$X$5:$X$45,0)) -> Объёмный | G47: =INDEX(Чувствительность!$E$5:$E$45,MATCH(LARGE(Чувствительность!$X$5:$X$45,2),Чувствительность!$X$5:$X$45,0)) -> Управляемый
A48: 3 | B48: =INDEX(Чувствительность!$B$5:$B$45,MATCH(LARGE(Чувствительность!$X$5:$X$45,3),Чувствительность!$X$5:$X$45,0)) -> Конверсия: заявка → открытый счёт (KYC пройден; ИК — договор подписан) | C48: =INDEX(Чувствительность!$A$5:$A$45,MATCH(LARGE(Чувствительность!$X$5:$X$45,3),Чувствительность!$X$5:$X$45,0)) -> CR_OPEN | D48: =INDEX(Чувствительность!$Q$5:$Q$45,MATCH(LARGE(Чувствительность!$X$5:$X$45,3),Чувствительность!$X$5:$X$45,0)) -> 1013905.3 | E48: =INDEX(Чувствительность!$M$5:$M$45,MATCH(LARGE(Чувствительность!$X$5:$X$45,3),Чувствительность!$X$5:$X$45,0)) -> -31333.545 | F48: =INDEX(Чувствительность!$F$5:$F$45,MATCH(LARGE(Чувствительность!$X$5:$X$45,3),Чувствительность!$X$5:$X$45,0)) -> Объёмный | G48: =INDEX(Чувствительность!$E$5:$E$45,MATCH(LARGE(Чувствительность!$X$5:$X$45,3),Чувствительность!$X$5:$X$45,0)) -> Управляемый
A49: 4 | B49: =INDEX(Чувствительность!$B$5:$B$45,MATCH(LARGE(Чувствительность!$X$5:$X$45,4),Чувствительность!$X$5:$X$45,0)) -> Заявки на открытие счёта за период (ИК — потенциальные клиенты в воронке продаж) | C49: =INDEX(Чувствительность!$A$5:$A$45,MATCH(LARGE(Чувствительность!$X$5:$X$45,4),Чувствительность!$X$5:$X$45,0)) -> LEADS | D49: =INDEX(Чувствительность!$Q$5:$Q$45,MATCH(LARGE(Чувствительность!$X$5:$X$45,4),Чувствительность!$X$5:$X$45,0)) -> 999805.25 | E49: =INDEX(Чувствительность!$M$5:$M$45,MATCH(LARGE(Чувствительность!$X$5:$X$45,4),Чувствительность!$X$5:$X$45,0)) -> -45433.545 | F49: =INDEX(Чувствительность!$F$5:$F$45,MATCH(LARGE(Чувствительность!$X$5:$X$45,4),Чувствительность!$X$5:$X$45,0)) -> Объёмный | G49: =INDEX(Чувствительность!$E$5:$E$45,MATCH(LARGE(Чувствительность!$X$5:$X$45,4),Чувствительность!$X$5:$X$45,0)) -> Управляемый
A50: 5 | B50: =INDEX(Чувствительность!$B$5:$B$45,MATCH(LARGE(Чувствительность!$X$5:$X$45,5),Чувствительность!$X$5:$X$45,0)) -> Средние активы на фондированного клиента | C50: =INDEX(Чувствительность!$A$5:$A$45,MATCH(LARGE(Чувствительность!$X$5:$X$45,5),Чувствительность!$X$5:$X$45,0)) -> AUC_PC | D50: =INDEX(Чувствительность!$Q$5:$Q$45,MATCH(LARGE(Чувствительность!$X$5:$X$45,5),Чувствительность!$X$5:$X$45,0)) -> 428241.67 | E50: =INDEX(Чувствительность!$M$5:$M$45,MATCH(LARGE(Чувствительность!$X$5:$X$45,5),Чувствительность!$X$5:$X$45,0)) -> 357315 | F50: =INDEX(Чувствительность!$F$5:$F$45,MATCH(LARGE(Чувствительность!$X$5:$X$45,5),Чувствительность!$X$5:$X$45,0)) -> Объёмный | G50: =INDEX(Чувствительность!$E$5:$E$45,MATCH(LARGE(Чувствительность!$X$5:$X$45,5),Чувствительность!$X$5:$X$45,0)) -> Частично
A51: 6 | B51: =INDEX(Чувствительность!$B$5:$B$45,MATCH(LARGE(Чувствительность!$X$5:$X$45,6),Чувствительность!$X$5:$X$45,0)) -> Средний объём сделки | C51: =INDEX(Чувствительность!$A$5:$A$45,MATCH(LARGE(Чувствительность!$X$5:$X$45,6),Чувствительность!$X$5:$X$45,0)) -> TICKET | D51: =INDEX(Чувствительность!$Q$5:$Q$45,MATCH(LARGE(Чувствительность!$X$5:$X$45,6),Чувствительность!$X$5:$X$45,0)) -> 268824 | E51: =INDEX(Чувствительность!$M$5:$M$45,MATCH(LARGE(Чувствительность!$X$5:$X$45,6),Чувствительность!$X$5:$X$45,0)) -> 224772.12 | F51: =INDEX(Чувствительность!$F$5:$F$45,MATCH(LARGE(Чувствительность!$X$5:$X$45,6),Чувствительность!$X$5:$X$45,0)) -> Объёмный | G51: =INDEX(Чувствительность!$E$5:$E$45,MATCH(LARGE(Чувствительность!$X$5:$X$45,6),Чувствительность!$X$5:$X$45,0)) -> Частично
A52: 7 | B52: =INDEX(Чувствительность!$B$5:$B$45,MATCH(LARGE(Чувствительность!$X$5:$X$45,7),Чувствительность!$X$5:$X$45,0)) -> Сделок в месяц на активного клиента | C52: =INDEX(Чувствительность!$A$5:$A$45,MATCH(LARGE(Чувствительность!$X$5:$X$45,7),Чувствительность!$X$5:$X$45,0)) -> TPA | D52: =INDEX(Чувствительность!$Q$5:$Q$45,MATCH(LARGE(Чувствительность!$X$5:$X$45,7),Чувствительность!$X$5:$X$45,0)) -> 268824 | E52: =INDEX(Чувствительность!$M$5:$M$45,MATCH(LARGE(Чувствительность!$X$5:$X$45,7),Чувствительность!$X$5:$X$45,0)) -> 224772.12 | F52: =INDEX(Чувствительность!$F$5:$F$45,MATCH(LARGE(Чувствительность!$X$5:$X$45,7),Чувствительность!$X$5:$X$45,0)) -> Объёмный | G52: =INDEX(Чувствительность!$E$5:$E$45,MATCH(LARGE(Чувствительность!$X$5:$X$45,7),Чувствительность!$X$5:$X$45,0)) -> Частично
A53: 8 | B53: =INDEX(Чувствительность!$B$5:$B$45,MATCH(LARGE(Чувствительность!$X$5:$X$45,8),Чувствительность!$X$5:$X$45,0)) -> Доля активных: среднемесячная доля фондированных клиентов с ≥1 операцией (сделка, пополнение, покупка продукта или подписки) | C53: =INDEX(Чувствительность!$A$5:$A$45,MATCH(LARGE(Чувствительность!$X$5:$X$45,8),Чувствительность!$X$5:$X$45,0)) -> ACT | D53: =INDEX(Чувствительность!$Q$5:$Q$45,MATCH(LARGE(Чувствительность!$X$5:$X$45,8),Чувствительность!$X$5:$X$45,0)) -> 268824 | E53: =INDEX(Чувствительность!$M$5:$M$45,MATCH(LARGE(Чувствительность!$X$5:$X$45,8),Чувствительность!$X$5:$X$45,0)) -> 224772.12 | F53: =INDEX(Чувствительность!$F$5:$F$45,MATCH(LARGE(Чувствительность!$X$5:$X$45,8),Чувствительность!$X$5:$X$45,0)) -> Объёмный | G53: =INDEX(Чувствительность!$E$5:$E$45,MATCH(LARGE(Чувствительность!$X$5:$X$45,8),Чувствительность!$X$5:$X$45,0)) -> Управляемый
A54: 9 | B54: =INDEX(Чувствительность!$B$5:$B$45,MATCH(LARGE(Чувствительность!$X$5:$X$45,9),Чувствительность!$X$5:$X$45,0)) -> Доля свободных денежных средств в активах клиентов | C54: =INDEX(Чувствительность!$A$5:$A$45,MATCH(LARGE(Чувствительность!$X$5:$X$45,9),Чувствительность!$X$5:$X$45,0)) -> CASH | D54: =INDEX(Чувствительность!$Q$5:$Q$45,MATCH(LARGE(Чувствительность!$X$5:$X$45,9),Чувствительность!$X$5:$X$45,0)) -> 264483.33 | E54: =INDEX(Чувствительность!$M$5:$M$45,MATCH(LARGE(Чувствительность!$X$5:$X$45,9),Чувствительность!$X$5:$X$45,0)) -> 220312 | F54: =INDEX(Чувствительность!$F$5:$F$45,MATCH(LARGE(Чувствительность!$X$5:$X$45,9),Чувствительность!$X$5:$X$45,0)) -> Объёмный | G54: =INDEX(Чувствительность!$E$5:$E$45,MATCH(LARGE(Чувствительность!$X$5:$X$45,9),Чувствительность!$X$5:$X$45,0)) -> Частично
A55: 10 | B55: =INDEX(Чувствительность!$B$5:$B$45,MATCH(LARGE(Чувствительность!$X$5:$X$45,10),Чувствительность!$X$5:$X$45,0)) -> Средняя задолженность маржинального клиента | C55: =INDEX(Чувствительность!$A$5:$A$45,MATCH(LARGE(Чувствительность!$X$5:$X$45,10),Чувствительность!$X$5:$X$45,0)) -> MRG_DEBT | D55: =INDEX(Чувствительность!$Q$5:$Q$45,MATCH(LARGE(Чувствительность!$X$5:$X$45,10),Чувствительность!$X$5:$X$45,0)) -> 252775 | E55: =INDEX(Чувствительность!$M$5:$M$45,MATCH(LARGE(Чувствительность!$X$5:$X$45,10),Чувствительность!$X$5:$X$45,0)) -> 211024.5 | F55: =INDEX(Чувствительность!$F$5:$F$45,MATCH(LARGE(Чувствительность!$X$5:$X$45,10),Чувствительность!$X$5:$X$45,0)) -> Объёмный | G55: =INDEX(Чувствительность!$E$5:$E$45,MATCH(LARGE(Чувствительность!$X$5:$X$45,10),Чувствительность!$X$5:$X$45,0)) -> Частично
A57: Ранг | B57: Ценовые рычаги: ценность +1% при неизменных объёмах (без эластичности) | C57: Код | D57: ΔМД в год, долгосрочно | E57: ΔМД, год 1 | F57: Тип рычага | G57: Управляемость
A58: 1 | B58: =INDEX(Чувствительность!$B$5:$B$45,MATCH(LARGE(Чувствительность!$Y$5:$Y$45,1),Чувствительность!$Y$5:$Y$45,0)) -> Ставка для клиента по маржинальному кредиту (деньги и ценные бумаги) | C58: =INDEX(Чувствительность!$A$5:$A$45,MATCH(LARGE(Чувствительность!$Y$5:$Y$45,1),Чувствительность!$Y$5:$Y$45,0)) -> MRG_RATE | D58: =INDEX(Чувствительность!$Q$5:$Q$45,MATCH(LARGE(Чувствительность!$Y$5:$Y$45,1),Чувствительность!$Y$5:$Y$45,0)) -> 937000 | E58: =INDEX(Чувствительность!$M$5:$M$45,MATCH(LARGE(Чувствительность!$Y$5:$Y$45,1),Чувствительность!$Y$5:$Y$45,0)) -> 791670 | F58: =INDEX(Чувствительность!$F$5:$F$45,MATCH(LARGE(Чувствительность!$Y$5:$Y$45,1),Чувствительность!$Y$5:$Y$45,0)) -> Ценовой | G58: =INDEX(Чувствительность!$E$5:$E$45,MATCH(LARGE(Чувствительность!$Y$5:$Y$45,1),Чувствительность!$Y$5:$Y$45,0)) -> Управляемый
A59: 2 | B59: =INDEX(Чувствительность!$B$5:$B$45,MATCH(LARGE(Чувствительность!$Y$5:$Y$45,2),Чувствительность!$Y$5:$Y$45,0)) -> Ставка, выплачиваемая клиентам на свободные остатки | C59: =INDEX(Чувствительность!$A$5:$A$45,MATCH(LARGE(Чувствительность!$Y$5:$Y$45,2),Чувствительность!$Y$5:$Y$45,0)) -> FLOAT_P | D59: =INDEX(Чувствительность!$Q$5:$Q$45,MATCH(LARGE(Чувствительность!$Y$5:$Y$45,2),Чувствительность!$Y$5:$Y$45,0)) -> 390341.67 | E59: =INDEX(Чувствительность!$M$5:$M$45,MATCH(LARGE(Чувствительность!$Y$5:$Y$45,2),Чувствительность!$Y$5:$Y$45,0)) -> 333683 | F59: =INDEX(Чувствительность!$F$5:$F$45,MATCH(LARGE(Чувствительность!$Y$5:$Y$45,2),Чувствительность!$Y$5:$Y$45,0)) -> Ценовой | G59: =INDEX(Чувствительность!$E$5:$E$45,MATCH(LARGE(Чувствительность!$Y$5:$Y$45,2),Чувствительность!$Y$5:$Y$45,0)) -> Управляемый
A60: 3 | B60: =INDEX(Чувствительность!$B$5:$B$45,MATCH(LARGE(Чувствительность!$Y$5:$Y$45,3),Чувствительность!$Y$5:$Y$45,0)) -> Комиссия брокера, % от оборота (эффективная, с учётом тарифов и скидок) | C60: =INDEX(Чувствительность!$A$5:$A$45,MATCH(LARGE(Чувствительность!$Y$5:$Y$45,3),Чувствительность!$Y$5:$Y$45,0)) -> TAKE | D60: =INDEX(Чувствительность!$Q$5:$Q$45,MATCH(LARGE(Чувствительность!$Y$5:$Y$45,3),Чувствительность!$Y$5:$Y$45,0)) -> 364110 | E60: =INDEX(Чувствительность!$M$5:$M$45,MATCH(LARGE(Чувствительность!$Y$5:$Y$45,3),Чувствительность!$Y$5:$Y$45,0)) -> 306049.95 | F60: =INDEX(Чувствительность!$F$5:$F$45,MATCH(LARGE(Чувствительность!$Y$5:$Y$45,3),Чувствительность!$Y$5:$Y$45,0)) -> Ценовой | G60: =INDEX(Чувствительность!$E$5:$E$45,MATCH(LARGE(Чувствительность!$Y$5:$Y$45,3),Чувствительность!$Y$5:$Y$45,0)) -> Управляемый
A61: 4 | B61: =INDEX(Чувствительность!$B$5:$B$45,MATCH(LARGE(Чувствительность!$Y$5:$Y$45,4),Чувствительность!$Y$5:$Y$45,0)) -> Средняя комиссия или маржа по продуктам и размещениям, % от объёма | C61: =INDEX(Чувствительность!$A$5:$A$45,MATCH(LARGE(Чувствительность!$Y$5:$Y$45,4),Чувствительность!$Y$5:$Y$45,0)) -> PRD_FEE | D61: =INDEX(Чувствительность!$Q$5:$Q$45,MATCH(LARGE(Чувствительность!$Y$5:$Y$45,4),Чувствительность!$Y$5:$Y$45,0)) -> 190070 | E61: =INDEX(Чувствительность!$M$5:$M$45,MATCH(LARGE(Чувствительность!$Y$5:$Y$45,4),Чувствительность!$Y$5:$Y$45,0)) -> 163440.6 | F61: =INDEX(Чувствительность!$F$5:$F$45,MATCH(LARGE(Чувствительность!$Y$5:$Y$45,4),Чувствительность!$Y$5:$Y$45,0)) -> Ценовой | G61: =INDEX(Чувствительность!$E$5:$E$45,MATCH(LARGE(Чувствительность!$Y$5:$Y$45,4),Чувствительность!$Y$5:$Y$45,0)) -> Управляемый
A62: 5 | B62: =INDEX(Чувствительность!$B$5:$B$45,MATCH(LARGE(Чувствительность!$Y$5:$Y$45,5),Чувствительность!$Y$5:$Y$45,0)) -> Комиссия за управление и консультирование, % годовых (вкл. success fee) | C62: =INDEX(Чувствительность!$A$5:$A$45,MATCH(LARGE(Чувствительность!$Y$5:$Y$45,5),Чувствительность!$Y$5:$Y$45,0)) -> AM_FEE | D62: =INDEX(Чувствительность!$Q$5:$Q$45,MATCH(LARGE(Чувствительность!$Y$5:$Y$45,5),Чувствительность!$Y$5:$Y$45,0)) -> 101441.67 | E62: =INDEX(Чувствительность!$M$5:$M$45,MATCH(LARGE(Чувствительность!$Y$5:$Y$45,5),Чувствительность!$Y$5:$Y$45,0)) -> 83629 | F62: =INDEX(Чувствительность!$F$5:$F$45,MATCH(LARGE(Чувствительность!$Y$5:$Y$45,5),Чувствительность!$Y$5:$Y$45,0)) -> Ценовой | G62: =INDEX(Чувствительность!$E$5:$E$45,MATCH(LARGE(Чувствительность!$Y$5:$Y$45,5),Чувствительность!$Y$5:$Y$45,0)) -> Управляемый
A63: 6 | B63: =INDEX(Чувствительность!$B$5:$B$45,MATCH(LARGE(Чувствительность!$Y$5:$Y$45,6),Чувствительность!$Y$5:$Y$45,0)) -> Комиссия и спред за конвертацию, % от объёма | C63: =INDEX(Чувствительность!$A$5:$A$45,MATCH(LARGE(Чувствительность!$Y$5:$Y$45,6),Чувствительность!$Y$5:$Y$45,0)) -> FX_SPREAD | D63: =INDEX(Чувствительность!$Q$5:$Q$45,MATCH(LARGE(Чувствительность!$Y$5:$Y$45,6),Чувствительность!$Y$5:$Y$45,0)) -> 83406.25 | E63: =INDEX(Чувствительность!$M$5:$M$45,MATCH(LARGE(Чувствительность!$Y$5:$Y$45,6),Чувствительность!$Y$5:$Y$45,0)) -> 68739.375 | F63: =INDEX(Чувствительность!$F$5:$F$45,MATCH(LARGE(Чувствительность!$Y$5:$Y$45,6),Чувствительность!$Y$5:$Y$45,0)) -> Ценовой | G63: =INDEX(Чувствительность!$E$5:$E$45,MATCH(LARGE(Чувствительность!$Y$5:$Y$45,6),Чувствительность!$Y$5:$Y$45,0)) -> Управляемый
A64: 7 | B64: =INDEX(Чувствительность!$B$5:$B$45,MATCH(LARGE(Чувствительность!$Y$5:$Y$45,7),Чувствительность!$Y$5:$Y$45,0)) -> Депозитарная и кастодиальная комиссия, % от активов в год | C64: =INDEX(Чувствительность!$A$5:$A$45,MATCH(LARGE(Чувствительность!$Y$5:$Y$45,7),Чувствительность!$Y$5:$Y$45,0)) -> CUST_FEE | D64: =INDEX(Чувствительность!$Q$5:$Q$45,MATCH(LARGE(Чувствительность!$Y$5:$Y$45,7),Чувствительность!$Y$5:$Y$45,0)) -> 62316.667 | E64: =INDEX(Чувствительность!$M$5:$M$45,MATCH(LARGE(Чувствительность!$Y$5:$Y$45,7),Чувствительность!$Y$5:$Y$45,0)) -> 53374 | F64: =INDEX(Чувствительность!$F$5:$F$45,MATCH(LARGE(Чувствительность!$Y$5:$Y$45,7),Чувствительность!$Y$5:$Y$45,0)) -> Ценовой | G64: =INDEX(Чувствительность!$E$5:$E$45,MATCH(LARGE(Чувствительность!$Y$5:$Y$45,7),Чувствительность!$Y$5:$Y$45,0)) -> Управляемый
A65: 8 | B65: =INDEX(Чувствительность!$B$5:$B$45,MATCH(LARGE(Чувствительность!$Y$5:$Y$45,8),Чувствительность!$Y$5:$Y$45,0)) -> Стоимость подписки или премиального обслуживания в год | C65: =INDEX(Чувствительность!$A$5:$A$45,MATCH(LARGE(Чувствительность!$Y$5:$Y$45,8),Чувствительность!$Y$5:$Y$45,0)) -> SUB_PRICE | D65: =INDEX(Чувствительность!$Q$5:$Q$45,MATCH(LARGE(Чувствительность!$Y$5:$Y$45,8),Чувствительность!$Y$5:$Y$45,0)) -> 57700 | E65: =INDEX(Чувствительность!$M$5:$M$45,MATCH(LARGE(Чувствительность!$Y$5:$Y$45,8),Чувствительность!$Y$5:$Y$45,0)) -> 47007 | F65: =INDEX(Чувствительность!$F$5:$F$45,MATCH(LARGE(Чувствительность!$Y$5:$Y$45,8),Чувствительность!$Y$5:$Y$45,0)) -> Ценовой | G65: =INDEX(Чувствительность!$E$5:$E$45,MATCH(LARGE(Чувствительность!$Y$5:$Y$45,8),Чувствительность!$Y$5:$Y$45,0)) -> Управляемый
A67: Рейтинг — по долгосрочному эффекту. Внешние факторы (ставки рынка) исключены; ценовые рычаги — отдельный тип решений, их эффект показан без реакции клиентов.
A68: Отрицательный эффект года 1 у драйверов привлечения — не ошибка: CAC платится сразу, доход приходит позже. На иллюстративных данных рейтинг показывает механику, а не приоритеты.

Sheet Дерево
A1: Дерево метрик: от маржинального дохода к драйверам
A2: Каждый узел — формула от дочерних. Значения — базовый расчёт с листа «Модель».
A4: Уровень | B4: Код | C4: Метрика | D4: Формула | E4: Ед. | F4: Масс-розница | G4: Состоятельные | H4: Институционалы и корп. | I4: Итого | J4: Тип
A5: 0 | B5: CM | C5: МД — маржинальный доход | D5: ЧВ − ЗО − ЗП − ПТ | E5: у.е. | F5: =INDEX(Модель!$E$8:$E$101,MATCH($B5,Модель!$A$8:$A$101,0)) -> 31786706 | G5: =INDEX(Модель!$F$8:$F$101,MATCH($B5,Модель!$A$8:$A$101,0)) -> 23410277 | H5: =INDEX(Модель!$G$8:$G$101,MATCH($B5,Модель!$A$8:$A$101,0)) -> 26356132 | I5: =INDEX(Модель!$H$8:$H$101,MATCH($B5,Модель!$A$8:$A$101,0)) -> 81553114 | J5: Расчёт
A6: 1 | B6: NR | C6: ЧВ — чистая выручка | D6: R1 + R2 + R3 + R4 + R5 + R6 + R7 | E6: у.е. | F6: =INDEX(Модель!$E$8:$E$101,MATCH($B6,Модель!$A$8:$A$101,0)) -> 43659406 | G6: =INDEX(Модель!$F$8:$F$101,MATCH($B6,Модель!$A$8:$A$101,0)) -> 32988152 | H6: =INDEX(Модель!$G$8:$G$101,MATCH($B6,Модель!$A$8:$A$101,0)) -> 32451852 | I6: =INDEX(Модель!$H$8:$H$101,MATCH($B6,Модель!$A$8:$A$101,0)) -> 1.0909941e+08 | J6: Расчёт
A7: 2 | B7: R1 | C7: Торговые комиссии (нетто) | D7: TURN × (TAKE − EXEC) | E7: у.е. | F7: =INDEX(Модель!$E$8:$E$101,MATCH($B7,Модель!$A$8:$A$101,0)) -> 12268368 | G7: =INDEX(Модель!$F$8:$F$101,MATCH($B7,Модель!$A$8:$A$101,0)) -> 4188492 | H7: =INDEX(Модель!$G$8:$G$101,MATCH($B7,Модель!$A$8:$A$101,0)) -> 6020352 | I7: =INDEX(Модель!$H$8:$H$101,MATCH($B7,Модель!$A$8:$A$101,0)) -> 22477212 | J7: Расчёт
A8: 3 | B8: TURN | C8: Оборот клиентов за период | D8: ACTIVE × TPA × 12 × TICKET | E8: у.е. | F8: =INDEX(Модель!$E$8:$E$101,MATCH($B8,Модель!$A$8:$A$101,0)) -> 10223640000 | G8: =INDEX(Модель!$F$8:$F$101,MATCH($B8,Модель!$A$8:$A$101,0)) -> 5235615000 | H8: =INDEX(Модель!$G$8:$G$101,MATCH($B8,Модель!$A$8:$A$101,0)) -> 50169600000 | I8: =INDEX(Модель!$H$8:$H$101,MATCH($B8,Модель!$A$8:$A$101,0)) -> 65628855000 | J8: Расчёт
A9: 4 | B9: ACTIVE | C9: Активные клиенты (среднемесячно) | D9: N_AVG × ACT | E9: чел. | F9: =INDEX(Модель!$E$8:$E$101,MATCH($B9,Модель!$A$8:$A$101,0)) -> 177493.75 | G9: =INDEX(Модель!$F$8:$F$101,MATCH($B9,Модель!$A$8:$A$101,0)) -> 8310.5 | H9: =INDEX(Модель!$G$8:$G$101,MATCH($B9,Модель!$A$8:$A$101,0)) -> 321.6 | I9: =INDEX(Модель!$H$8:$H$101,MATCH($B9,Модель!$A$8:$A$101,0)) -> 186125.85 | J9: Расчёт
A10: 4 | B10: TPA | C10: Сделок в месяц на активного клиента | D10: Вводная | E10: шт./клиент | F10: =INDEX(Модель!$E$8:$E$101,MATCH($B10,Модель!$A$8:$A$101,0)) -> 6 | G10: =INDEX(Модель!$F$8:$F$101,MATCH($B10,Модель!$A$8:$A$101,0)) -> 3.5 | H10: =INDEX(Модель!$G$8:$G$101,MATCH($B10,Модель!$A$8:$A$101,0)) -> 130 | J10: Вводная: объёмный
A11: 4 | B11: TICKET | C11: Средний объём сделки | D11: Вводная | E11: у.е. | F11: =INDEX(Модель!$E$8:$E$101,MATCH($B11,Модель!$A$8:$A$101,0)) -> 800 | G11: =INDEX(Модель!$F$8:$F$101,MATCH($B11,Модель!$A$8:$A$101,0)) -> 15000 | H11: =INDEX(Модель!$G$8:$G$101,MATCH($B11,Модель!$A$8:$A$101,0)) -> 100000 | J11: Вводная: объёмный
A12: 3 | B12: TAKE | C12: Комиссия брокера, % от оборота (эффективная, с учётом тарифов и скидок) | D12: Вводная | E12: % | F12: =INDEX(Модель!$E$8:$E$101,MATCH($B12,Модель!$A$8:$A$101,0)) -> 0.0015 | G12: =INDEX(Модель!$F$8:$F$101,MATCH($B12,Модель!$A$8:$A$101,0)) -> 0.001 | H12: =INDEX(Модель!$G$8:$G$101,MATCH($B12,Модель!$A$8:$A$101,0)) -> 0.0002 | J12: Вводная: ценовой
A13: 3 | B13: EXEC | C13: Затраты на исполнение (биржевые, клиринговые, депозитарные сборы, вышестоящий брокер), % от оборота | D13: Вводная | E13: % | F13: =INDEX(Модель!$E$8:$E$101,MATCH($B13,Модель!$A$8:$A$101,0)) -> 0.0003 | G13: =INDEX(Модель!$F$8:$F$101,MATCH($B13,Модель!$A$8:$A$101,0)) -> 0.0002 | H13: =INDEX(Модель!$G$8:$G$101,MATCH($B13,Модель!$A$8:$A$101,0)) -> 8e-05 | J13: Вводная: затратный
A14: 2 | B14: R2 | C14: Маржинальное кредитование (нетто) | D14: MPORT × ((MRG_RATE + RATE_SHIFT × PT_MRG) − (FUND_RATE + RATE_SHIFT)) | E14: у.е. | F14: =INDEX(Модель!$E$8:$E$101,MATCH($B14,Модель!$A$8:$A$101,0)) -> 10142500 | G14: =INDEX(Модель!$F$8:$F$101,MATCH($B14,Модель!$A$8:$A$101,0)) -> 6799500 | H14: =INDEX(Модель!$G$8:$G$101,MATCH($B14,Модель!$A$8:$A$101,0)) -> 6030000 | I14: =INDEX(Модель!$H$8:$H$101,MATCH($B14,Модель!$A$8:$A$101,0)) -> 22972000 | J14: Расчёт
A15: 3 | B15: MPORT | C15: Маржинальный портфель, среднее за период | D15: N_AVG × MRG_PEN × MRG_DEBT | E15: у.е. | F15: =INDEX(Модель!$E$8:$E$101,MATCH($B15,Модель!$A$8:$A$101,0)) -> 202850000 | G15: =INDEX(Модель!$F$8:$F$101,MATCH($B15,Модель!$A$8:$A$101,0)) -> 226650000 | H15: =INDEX(Модель!$G$8:$G$101,MATCH($B15,Модель!$A$8:$A$101,0)) -> 402000000 | I15: =INDEX(Модель!$H$8:$H$101,MATCH($B15,Модель!$A$8:$A$101,0)) -> 831500000 | J15: Расчёт
A16: 4 | B16: MRG_PEN | C16: Проникновение маржинальной торговли: доля фондированных клиентов с задолженностью | D16: Вводная | E16: % | F16: =INDEX(Модель!$E$8:$E$101,MATCH($B16,Модель!$A$8:$A$101,0)) -> 0.05 | G16: =INDEX(Модель!$F$8:$F$101,MATCH($B16,Модель!$A$8:$A$101,0)) -> 0.1 | H16: =INDEX(Модель!$G$8:$G$101,MATCH($B16,Модель!$A$8:$A$101,0)) -> 0.2 | J16: Вводная: объёмный
A17: 4 | B17: MRG_DEBT | C17: Средняя задолженность маржинального клиента | D17: Вводная | E17: у.е. | F17: =INDEX(Модель!$E$8:$E$101,MATCH($B17,Модель!$A$8:$A$101,0)) -> 8000 | G17: =INDEX(Модель!$F$8:$F$101,MATCH($B17,Модель!$A$8:$A$101,0)) -> 150000 | H17: =INDEX(Модель!$G$8:$G$101,MATCH($B17,Модель!$A$8:$A$101,0)) -> 5000000 | J17: Вводная: объёмный
A18: 3 | B18: MRG_RATE | C18: Ставка для клиента по маржинальному кредиту (деньги и ценные бумаги) | D18: Вводная | E18: % | F18: =INDEX(Модель!$E$8:$E$101,MATCH($B18,Модель!$A$8:$A$101,0)) -> 0.12 | G18: =INDEX(Модель!$F$8:$F$101,MATCH($B18,Модель!$A$8:$A$101,0)) -> 0.1 | H18: =INDEX(Модель!$G$8:$G$101,MATCH($B18,Модель!$A$8:$A$101,0)) -> 0.08 | J18: Вводная: ценовой
A19: 3 | B19: FUND_RATE | C19: Стоимость фондирования маржинального портфеля | D19: Вводная | E19: % | F19: =INDEX(Модель!$E$8:$E$101,MATCH($B19,Модель!$A$8:$A$101,0)) -> 0.07 | G19: =INDEX(Модель!$F$8:$F$101,MATCH($B19,Модель!$A$8:$A$101,0)) -> 0.07 | H19: =INDEX(Модель!$G$8:$G$101,MATCH($B19,Модель!$A$8:$A$101,0)) -> 0.065 | J19: Вводная: внешний
A20: 2 | B20: R3 | C20: Доход на свободные остатки (нетто) | D20: CASHBAL × ((FLOAT_Y + RATE_SHIFT) − max(0; FLOAT_P + RATE_SHIFT × PT_FLOAT)) | E20: у.е. | F20: =INDEX(Модель!$E$8:$E$101,MATCH($B20,Модель!$A$8:$A$101,0)) -> 12171000 | G20: =INDEX(Модель!$F$8:$F$101,MATCH($B20,Модель!$A$8:$A$101,0)) -> 4835200 | H20: =INDEX(Модель!$G$8:$G$101,MATCH($B20,Модель!$A$8:$A$101,0)) -> 5025000 | I20: =INDEX(Модель!$H$8:$H$101,MATCH($B20,Модель!$A$8:$A$101,0)) -> 22031200 | J20: Расчёт
A21: 3 | B21: CASHBAL | C21: Свободные денежные остатки клиентов | D21: AUC × CASH | E21: у.е. | F21: =INDEX(Модель!$E$8:$E$101,MATCH($B21,Модель!$A$8:$A$101,0)) -> 486840000 | G21: =INDEX(Модель!$F$8:$F$101,MATCH($B21,Модель!$A$8:$A$101,0)) -> 241760000 | H21: =INDEX(Модель!$G$8:$G$101,MATCH($B21,Модель!$A$8:$A$101,0)) -> 502500000 | I21: =INDEX(Модель!$H$8:$H$101,MATCH($B21,Модель!$A$8:$A$101,0)) -> 1231100000 | J21: Расчёт
A22: 4 | B22: AUC | C22: Активы клиентов, среднее за период | D22: N_AVG × AUC_PC | E22: у.е. | F22: =INDEX(Модель!$E$8:$E$101,MATCH($B22,Модель!$A$8:$A$101,0)) -> 4057000000 | G22: =INDEX(Модель!$F$8:$F$101,MATCH($B22,Модель!$A$8:$A$101,0)) -> 3022000000 | H22: =INDEX(Модель!$G$8:$G$101,MATCH($B22,Модель!$A$8:$A$101,0)) -> 10050000000 | I22: =INDEX(Модель!$H$8:$H$101,MATCH($B22,Модель!$A$8:$A$101,0)) -> 17129000000 | J22: Расчёт
A23: 5 | B23: AUC_PC | C23: Средние активы на фондированного клиента | D23: Вводная | E23: у.е. | F23: =INDEX(Модель!$E$8:$E$101,MATCH($B23,Модель!$A$8:$A$101,0)) -> 8000 | G23: =INDEX(Модель!$F$8:$F$101,MATCH($B23,Модель!$A$8:$A$101,0)) -> 200000 | H23: =INDEX(Модель!$G$8:$G$101,MATCH($B23,Модель!$A$8:$A$101,0)) -> 25000000 | J23: Вводная: объёмный
A24: 4 | B24: CASH | C24: Доля свободных денежных средств в активах клиентов | D24: Вводная | E24: % | F24: =INDEX(Модель!$E$8:$E$101,MATCH($B24,Модель!$A$8:$A$101,0)) -> 0.12 | G24: =INDEX(Модель!$F$8:$F$101,MATCH($B24,Модель!$A$8:$A$101,0)) -> 0.08 | H24: =INDEX(Модель!$G$8:$G$101,MATCH($B24,Модель!$A$8:$A$101,0)) -> 0.05 | J24: Вводная: объёмный
A25: 3 | B25: FLOAT_Y | C25: Доходность размещения свободных остатков клиентов | D25: Вводная | E25: % | F25: =INDEX(Модель!$E$8:$E$101,MATCH($B25,Модель!$A$8:$A$101,0)) -> 0.05 | G25: =INDEX(Модель!$F$8:$F$101,MATCH($B25,Модель!$A$8:$A$101,0)) -> 0.05 | H25: =INDEX(Модель!$G$8:$G$101,MATCH($B25,Модель!$A$8:$A$101,0)) -> 0.05 | J25: Вводная: внешний
A26: 3 | B26: FLOAT_P | C26: Ставка, выплачиваемая клиентам на свободные остатки | D26: Вводная | E26: % | F26: =INDEX(Модель!$E$8:$E$101,MATCH($B26,Модель!$A$8:$A$101,0)) -> 0.02 | G26: =INDEX(Модель!$F$8:$F$101,MATCH($B26,Модель!$A$8:$A$101,0)) -> 0.025 | H26: =INDEX(Модель!$G$8:$G$101,MATCH($B26,Модель!$A$8:$A$101,0)) -> 0.035 | J26: Вводная: ценовой
A27: 2 | B27: R4 | C27: Конвертация валют | D27: FXVOLUME × FX_SPREAD | E27: у.е. | F27: =INDEX(Модель!$E$8:$E$101,MATCH($B27,Модель!$A$8:$A$101,0)) -> 3803437.5 | G27: =INDEX(Модель!$F$8:$F$101,MATCH($B27,Модель!$A$8:$A$101,0)) -> 2266500 | H27: =INDEX(Модель!$G$8:$G$101,MATCH($B27,Модель!$A$8:$A$101,0)) -> 804000 | I27: =INDEX(Модель!$H$8:$H$101,MATCH($B27,Модель!$A$8:$A$101,0)) -> 6873937.5 | J27: Расчёт
A28: 3 | B28: FXVOLUME | C28: Объём конвертаций за период | D28: N_AVG × FX_PEN × FX_VOL | E28: у.е. | F28: =INDEX(Модель!$E$8:$E$101,MATCH($B28,Модель!$A$8:$A$101,0)) -> 760687500 | G28: =INDEX(Модель!$F$8:$F$101,MATCH($B28,Модель!$A$8:$A$101,0)) -> 755500000 | H28: =INDEX(Модель!$G$8:$G$101,MATCH($B28,Модель!$A$8:$A$101,0)) -> 1608000000 | I28: =INDEX(Модель!$H$8:$H$101,MATCH($B28,Модель!$A$8:$A$101,0)) -> 3124187500 | J28: Расчёт
A29: 4 | B29: FX_PEN | C29: Доля фондированных клиентов, совершающих конвертации | D29: Вводная | E29: % | F29: =INDEX(Модель!$E$8:$E$101,MATCH($B29,Модель!$A$8:$A$101,0)) -> 0.3 | G29: =INDEX(Модель!$F$8:$F$101,MATCH($B29,Модель!$A$8:$A$101,0)) -> 0.5 | H29: =INDEX(Модель!$G$8:$G$101,MATCH($B29,Модель!$A$8:$A$101,0)) -> 0.4 | J29: Вводная: объёмный
A30: 4 | B30: FX_VOL | C30: Объём конвертаций на конвертирующего клиента в год | D30: Вводная | E30: у.е. | F30: =INDEX(Модель!$E$8:$E$101,MATCH($B30,Модель!$A$8:$A$101,0)) -> 5000 | G30: =INDEX(Модель!$F$8:$F$101,MATCH($B30,Модель!$A$8:$A$101,0)) -> 100000 | H30: =INDEX(Модель!$G$8:$G$101,MATCH($B30,Модель!$A$8:$A$101,0)) -> 10000000 | J30: Вводная: объёмный
A31: 3 | B31: FX_SPREAD | C31: Комиссия и спред за конвертацию, % от объёма | D31: Вводная | E31: % | F31: =INDEX(Модель!$E$8:$E$101,MATCH($B31,Модель!$A$8:$A$101,0)) -> 0.005 | G31: =INDEX(Модель!$F$8:$F$101,MATCH($B31,Модель!$A$8:$A$101,0)) -> 0.003 | H31: =INDEX(Модель!$G$8:$G$101,MATCH($B31,Модель!$A$8:$A$101,0)) -> 0.0005 | J31: Вводная: ценовой
A32: 2 | B32: R5 | C32: Размещения и продукты | D32: PRDVOLUME × PRD_FEE | E32: у.е. | F32: =INDEX(Модель!$E$8:$E$101,MATCH($B32,Модель!$A$8:$A$101,0)) -> 1217100 | G32: =INDEX(Модель!$F$8:$F$101,MATCH($B32,Модель!$A$8:$A$101,0)) -> 5076960 | H32: =INDEX(Модель!$G$8:$G$101,MATCH($B32,Модель!$A$8:$A$101,0)) -> 10050000 | I32: =INDEX(Модель!$H$8:$H$101,MATCH($B32,Модель!$A$8:$A$101,0)) -> 16344060 | J32: Расчёт
A33: 3 | B33: PRDVOLUME | C33: Объём продаж продуктов и размещений | D33: N_AVG × PRD_PEN × PRD_VOL | E33: у.е. | F33: =INDEX(Модель!$E$8:$E$101,MATCH($B33,Модель!$A$8:$A$101,0)) -> 121710000 | G33: =INDEX(Модель!$F$8:$F$101,MATCH($B33,Модель!$A$8:$A$101,0)) -> 423080000 | H33: =INDEX(Модель!$G$8:$G$101,MATCH($B33,Модель!$A$8:$A$101,0)) -> 1005000000 | I33: =INDEX(Модель!$H$8:$H$101,MATCH($B33,Модель!$A$8:$A$101,0)) -> 1549790000 | J33: Расчёт
A34: 4 | B34: PRD_PEN | C34: Доля фондированных клиентов, купивших размещения или продукты за год (ИК — доля клиентов-эмитентов, проведших размещение) | D34: Вводная | E34: % | F34: =INDEX(Модель!$E$8:$E$101,MATCH($B34,Модель!$A$8:$A$101,0)) -> 0.08 | G34: =INDEX(Модель!$F$8:$F$101,MATCH($B34,Модель!$A$8:$A$101,0)) -> 0.35 | H34: =INDEX(Модель!$G$8:$G$101,MATCH($B34,Модель!$A$8:$A$101,0)) -> 0.05 | J34: Вводная: объёмный
A35: 4 | B35: PRD_VOL | C35: Средний объём покупок продуктов на клиента в год (ИК — средний объём размещения) | D35: Вводная | E35: у.е. | F35: =INDEX(Модель!$E$8:$E$101,MATCH($B35,Модель!$A$8:$A$101,0)) -> 3000 | G35: =INDEX(Модель!$F$8:$F$101,MATCH($B35,Модель!$A$8:$A$101,0)) -> 80000 | H35: =INDEX(Модель!$G$8:$G$101,MATCH($B35,Модель!$A$8:$A$101,0)) -> 50000000 | J35: Вводная: объёмный
A36: 3 | B36: PRD_FEE | C36: Средняя комиссия или маржа по продуктам и размещениям, % от объёма | D36: Вводная | E36: % | F36: =INDEX(Модель!$E$8:$E$101,MATCH($B36,Модель!$A$8:$A$101,0)) -> 0.01 | G36: =INDEX(Модель!$F$8:$F$101,MATCH($B36,Модель!$A$8:$A$101,0)) -> 0.012 | H36: =INDEX(Модель!$G$8:$G$101,MATCH($B36,Модель!$A$8:$A$101,0)) -> 0.01 | J36: Вводная: ценовой
A37: 2 | B37: R6 | C37: ДУ и консультирование | D37: AUM × AM_FEE | E37: у.е. | F37: =INDEX(Модель!$E$8:$E$101,MATCH($B37,Модель!$A$8:$A$101,0)) -> 811400 | G37: =INDEX(Модель!$F$8:$F$101,MATCH($B37,Модель!$A$8:$A$101,0)) -> 6044000 | H37: =INDEX(Модель!$G$8:$G$101,MATCH($B37,Модель!$A$8:$A$101,0)) -> 1507500 | I37: =INDEX(Модель!$H$8:$H$101,MATCH($B37,Модель!$A$8:$A$101,0)) -> 8362900 | J37: Расчёт
A38: 3 | B38: AUM | C38: Активы в ДУ и на консультировании | D38: AUC × AM_SHARE | E38: у.е. | F38: =INDEX(Модель!$E$8:$E$101,MATCH($B38,Модель!$A$8:$A$101,0)) -> 81140000 | G38: =INDEX(Модель!$F$8:$F$101,MATCH($B38,Модель!$A$8:$A$101,0)) -> 604400000 | H38: =INDEX(Модель!$G$8:$G$101,MATCH($B38,Модель!$A$8:$A$101,0)) -> 502500000 | I38: =INDEX(Модель!$H$8:$H$101,MATCH($B38,Модель!$A$8:$A$101,0)) -> 1188040000 | J38: Расчёт
A39: 4 | B39: AM_SHARE | C39: Доля активов клиентов в ДУ, модельных портфелях и на консультировании | D39: Вводная | E39: % | F39: =INDEX(Модель!$E$8:$E$101,MATCH($B39,Модель!$A$8:$A$101,0)) -> 0.02 | G39: =INDEX(Модель!$F$8:$F$101,MATCH($B39,Модель!$A$8:$A$101,0)) -> 0.2 | H39: =INDEX(Модель!$G$8:$G$101,MATCH($B39,Модель!$A$8:$A$101,0)) -> 0.05 | J39: Вводная: объёмный
A40: 3 | B40: AM_FEE | C40: Комиссия за управление и консультирование, % годовых (вкл. success fee) | D40: Вводная | E40: % | F40: =INDEX(Модель!$E$8:$E$101,MATCH($B40,Модель!$A$8:$A$101,0)) -> 0.01 | G40: =INDEX(Модель!$F$8:$F$101,MATCH($B40,Модель!$A$8:$A$101,0)) -> 0.01 | H40: =INDEX(Модель!$G$8:$G$101,MATCH($B40,Модель!$A$8:$A$101,0)) -> 0.003 | J40: Вводная: ценовой
A41: 2 | B41: R7 | C41: Подписки и сервисные комиссии | D41: SUBS × SUB_PRICE + AUC × CUST_FEE | E41: у.е. | F41: =INDEX(Модель!$E$8:$E$101,MATCH($B41,Модель!$A$8:$A$101,0)) -> 3245600 | G41: =INDEX(Модель!$F$8:$F$101,MATCH($B41,Модель!$A$8:$A$101,0)) -> 3777500 | H41: =INDEX(Модель!$G$8:$G$101,MATCH($B41,Модель!$A$8:$A$101,0)) -> 3015000 | I41: =INDEX(Модель!$H$8:$H$101,MATCH($B41,Модель!$A$8:$A$101,0)) -> 10038100 | J41: Расчёт
A42: 3 | B42: SUBS | C42: Платные подписчики | D42: N_AVG × SUB_PEN | E42: чел. | F42: =INDEX(Модель!$E$8:$E$101,MATCH($B42,Модель!$A$8:$A$101,0)) -> 40570 | G42: =INDEX(Модель!$F$8:$F$101,MATCH($B42,Модель!$A$8:$A$101,0)) -> 2266.5 | H42: =INDEX(Модель!$G$8:$G$101,MATCH($B42,Модель!$A$8:$A$101,0)) -> 0 | I42: =INDEX(Модель!$H$8:$H$101,MATCH($B42,Модель!$A$8:$A$101,0)) -> 42836.5 | J42: Расчёт
A43: 4 | B43: SUB_PEN | C43: Доля фондированных клиентов с платной подпиской или премиальным тарифом | D43: Вводная | E43: % | F43: =INDEX(Модель!$E$8:$E$101,MATCH($B43,Модель!$A$8:$A$101,0)) -> 0.08 | G43: =INDEX(Модель!$F$8:$F$101,MATCH($B43,Модель!$A$8:$A$101,0)) -> 0.15 | H43: =INDEX(Модель!$G$8:$G$101,MATCH($B43,Модель!$A$8:$A$101,0)) -> 0 | J43: Вводная: объёмный
A44: 3 | B44: SUB_PRICE | C44: Стоимость подписки или премиального обслуживания в год | D44: Вводная | E44: у.е. | F44: =INDEX(Модель!$E$8:$E$101,MATCH($B44,Модель!$A$8:$A$101,0)) -> 60 | G44: =INDEX(Модель!$F$8:$F$101,MATCH($B44,Модель!$A$8:$A$101,0)) -> 1000 | H44: =INDEX(Модель!$G$8:$G$101,MATCH($B44,Модель!$A$8:$A$101,0)) -> 0 | J44: Вводная: ценовой
A45: 3 | B45: CUST_FEE | C45: Депозитарная и кастодиальная комиссия, % от активов в год | D45: Вводная | E45: % | F45: =INDEX(Модель!$E$8:$E$101,MATCH($B45,Модель!$A$8:$A$101,0)) -> 0.0002 | G45: =INDEX(Модель!$F$8:$F$101,MATCH($B45,Модель!$A$8:$A$101,0)) -> 0.0005 | H45: =INDEX(Модель!$G$8:$G$101,MATCH($B45,Модель!$A$8:$A$101,0)) -> 0.0003 | J45: Вводная: ценовой
A46: 1 | B46: CTS | C46: ЗО — затраты на обслуживание | D46: C1 + C2 + C3 + C4 | E46: у.е. | F46: =INDEX(Модель!$E$8:$E$101,MATCH($B46,Модель!$A$8:$A$101,0)) -> 4618450 | G46: =INDEX(Модель!$F$8:$F$101,MATCH($B46,Модель!$A$8:$A$101,0)) -> 7344575 | H46: =INDEX(Модель!$G$8:$G$101,MATCH($B46,Модель!$A$8:$A$101,0)) -> 4953720 | I46: =INDEX(Модель!$H$8:$H$101,MATCH($B46,Модель!$A$8:$A$101,0)) -> 16916745 | J46: Расчёт
A47: 2 | B47: C1 | C47: Поддержка клиентов | D47: N_AVG × SUP_RATE × SUP_COST | E47: у.е. | F47: =INDEX(Модель!$E$8:$E$101,MATCH($B47,Модель!$A$8:$A$101,0)) -> 2535625 | G47: =INDEX(Модель!$F$8:$F$101,MATCH($B47,Модель!$A$8:$A$101,0)) -> 679950 | H47: =INDEX(Модель!$G$8:$G$101,MATCH($B47,Модель!$A$8:$A$101,0)) -> 144720 | I47: =INDEX(Модель!$H$8:$H$101,MATCH($B47,Модель!$A$8:$A$101,0)) -> 3360295 | J47: Расчёт
A48: 3 | B48: SUP_RATE | C48: Обращений в поддержку на фондированного клиента в год | D48: Вводная | E48: шт./клиент | F48: =INDEX(Модель!$E$8:$E$101,MATCH($B48,Модель!$A$8:$A$101,0)) -> 1 | G48: =INDEX(Модель!$F$8:$F$101,MATCH($B48,Модель!$A$8:$A$101,0)) -> 3 | H48: =INDEX(Модель!$G$8:$G$101,MATCH($B48,Модель!$A$8:$A$101,0)) -> 12 | J48: Вводная: затратный
A49: 3 | B49: SUP_COST | C49: Стоимость обработки одного обращения | D49: Вводная | E49: у.е. | F49: =INDEX(Модель!$E$8:$E$101,MATCH($B49,Модель!$A$8:$A$101,0)) -> 5 | G49: =INDEX(Модель!$F$8:$F$101,MATCH($B49,Модель!$A$8:$A$101,0)) -> 15 | H49: =INDEX(Модель!$G$8:$G$101,MATCH($B49,Модель!$A$8:$A$101,0)) -> 30 | J49: Вводная: затратный
A50: 2 | B50: C2 | C50: Онбординг и KYC | D50: LEADS × (KYC_UNIT + KYC_MAN × KYC_MAN_COST) | E50: у.е. | F50: =INDEX(Модель!$E$8:$E$101,MATCH($B50,Модель!$A$8:$A$101,0)) -> 1170000 | G50: =INDEX(Модель!$F$8:$F$101,MATCH($B50,Модель!$A$8:$A$101,0)) -> 54000 | H50: =INDEX(Модель!$G$8:$G$101,MATCH($B50,Модель!$A$8:$A$101,0)) -> 186000 | I50: =INDEX(Модель!$H$8:$H$101,MATCH($B50,Модель!$A$8:$A$101,0)) -> 1410000 | J50: Расчёт
A51: 3 | B51: LEADS | C51: Заявки на открытие счёта за период (ИК — потенциальные клиенты в воронке продаж) | D51: Вводная | E51: шт. | F51: =INDEX(Модель!$E$8:$E$101,MATCH($B51,Модель!$A$8:$A$101,0)) -> 300000 | G51: =INDEX(Модель!$F$8:$F$101,MATCH($B51,Модель!$A$8:$A$101,0)) -> 2000 | H51: =INDEX(Модель!$G$8:$G$101,MATCH($B51,Модель!$A$8:$A$101,0)) -> 120 | I51: =INDEX(Модель!$H$8:$H$101,MATCH($B51,Модель!$A$8:$A$101,0)) -> 302120 | J51: Вводная: объёмный
A52: 3 | B52: KYC_UNIT | C52: Стоимость автоматической проверки заявки (KYC/AML-сервисы, документы) | D52: Вводная | E52: у.е. | F52: =INDEX(Модель!$E$8:$E$101,MATCH($B52,Модель!$A$8:$A$101,0)) -> 1.5 | G52: =INDEX(Модель!$F$8:$F$101,MATCH($B52,Модель!$A$8:$A$101,0)) -> 3 | H52: =INDEX(Модель!$G$8:$G$101,MATCH($B52,Модель!$A$8:$A$101,0)) -> 50 | J52: Вводная: затратный
A53: 3 | B53: KYC_MAN | C53: Доля заявок, требующих ручной проверки | D53: Вводная | E53: % | F53: =INDEX(Модель!$E$8:$E$101,MATCH($B53,Модель!$A$8:$A$101,0)) -> 0.3 | G53: =INDEX(Модель!$F$8:$F$101,MATCH($B53,Модель!$A$8:$A$101,0)) -> 0.6 | H53: =INDEX(Модель!$G$8:$G$101,MATCH($B53,Модель!$A$8:$A$101,0)) -> 1 | J53: Вводная: затратный
A54: 3 | B54: KYC_MAN_COST | C54: Стоимость ручной проверки заявки | D54: Вводная | E54: у.е. | F54: =INDEX(Модель!$E$8:$E$101,MATCH($B54,Модель!$A$8:$A$101,0)) -> 8 | G54: =INDEX(Модель!$F$8:$F$101,MATCH($B54,Модель!$A$8:$A$101,0)) -> 40 | H54: =INDEX(Модель!$G$8:$G$101,MATCH($B54,Модель!$A$8:$A$101,0)) -> 1500 | J54: Вводная: затратный
A55: 2 | B55: C3 | C55: Бэк-офис: ручные операции | D55: N_AVG × OPS_PC × OPS_MAN × OPS_COST | E55: у.е. | F55: =INDEX(Модель!$E$8:$E$101,MATCH($B55,Модель!$A$8:$A$101,0)) -> 912825 | G55: =INDEX(Модель!$F$8:$F$101,MATCH($B55,Модель!$A$8:$A$101,0)) -> 566625 | H55: =INDEX(Модель!$G$8:$G$101,MATCH($B55,Модель!$A$8:$A$101,0)) -> 603000 | I55: =INDEX(Модель!$H$8:$H$101,MATCH($B55,Модель!$A$8:$A$101,0)) -> 2082450 | J55: Расчёт
A56: 3 | B56: OPS_PC | C56: Операций бэк-офиса на фондированного клиента в год (вводы/выводы, переводы ЦБ, корп. действия, заявления) | D56: Вводная | E56: шт./клиент | F56: =INDEX(Модель!$E$8:$E$101,MATCH($B56,Модель!$A$8:$A$101,0)) -> 6 | G56: =INDEX(Модель!$F$8:$F$101,MATCH($B56,Модель!$A$8:$A$101,0)) -> 15 | H56: =INDEX(Модель!$G$8:$G$101,MATCH($B56,Модель!$A$8:$A$101,0)) -> 200 | J56: Вводная: затратный
A57: 3 | B57: OPS_MAN | C57: Доля операций с ручной обработкой (не STP) | D57: Вводная | E57: % | F57: =INDEX(Модель!$E$8:$E$101,MATCH($B57,Модель!$A$8:$A$101,0)) -> 0.1 | G57: =INDEX(Модель!$F$8:$F$101,MATCH($B57,Модель!$A$8:$A$101,0)) -> 0.25 | H57: =INDEX(Модель!$G$8:$G$101,MATCH($B57,Модель!$A$8:$A$101,0)) -> 0.3 | J57: Вводная: затратный
A58: 3 | B58: OPS_COST | C58: Стоимость ручной обработки одной операции | D58: Вводная | E58: у.е. | F58: =INDEX(Модель!$E$8:$E$101,MATCH($B58,Модель!$A$8:$A$101,0)) -> 3 | G58: =INDEX(Модель!$F$8:$F$101,MATCH($B58,Модель!$A$8:$A$101,0)) -> 10 | H58: =INDEX(Модель!$G$8:$G$101,MATCH($B58,Модель!$A$8:$A$101,0)) -> 25 | J58: Вводная: затратный
A59: 2 | B59: C4 | C59: Персональные менеджеры и покрытие | D59: N_AVG ÷ RM_LOAD × RM_COST | E59: у.е. | F59: =INDEX(Модель!$E$8:$E$101,MATCH($B59,Модель!$A$8:$A$101,0)) -> 0 | G59: =INDEX(Модель!$F$8:$F$101,MATCH($B59,Модель!$A$8:$A$101,0)) -> 6044000 | H59: =INDEX(Модель!$G$8:$G$101,MATCH($B59,Модель!$A$8:$A$101,0)) -> 4020000 | I59: =INDEX(Модель!$H$8:$H$101,MATCH($B59,Модель!$A$8:$A$101,0)) -> 10064000 | J59: Расчёт
A60: 3 | B60: RM_LOAD | C60: Клиентов на одного персонального менеджера / сотрудника покрытия (0 — модели нет) | D60: Вводная | E60: чел. | F60: =INDEX(Модель!$E$8:$E$101,MATCH($B60,Модель!$A$8:$A$101,0)) -> 0 | G60: =INDEX(Модель!$F$8:$F$101,MATCH($B60,Модель!$A$8:$A$101,0)) -> 150 | H60: =INDEX(Модель!$G$8:$G$101,MATCH($B60,Модель!$A$8:$A$101,0)) -> 15 | J60: Вводная: затратный
A61: 3 | B61: RM_COST | C61: Полная годовая стоимость менеджера (ФОТ, налоги, бонусы, рабочее место) | D61: Вводная | E61: у.е. | F61: =INDEX(Модель!$E$8:$E$101,MATCH($B61,Модель!$A$8:$A$101,0)) -> 0 | G61: =INDEX(Модель!$F$8:$F$101,MATCH($B61,Модель!$A$8:$A$101,0)) -> 60000 | H61: =INDEX(Модель!$G$8:$G$101,MATCH($B61,Модель!$A$8:$A$101,0)) -> 150000 | J61: Вводная: затратный
A62: 1 | B62: ACQ | C62: ЗП — затраты на привлечение | D62: NEW × CAC | E62: у.е. | F62: =INDEX(Модель!$E$8:$E$101,MATCH($B62,Модель!$A$8:$A$101,0)) -> 5940000 | G62: =INDEX(Модель!$F$8:$F$101,MATCH($B62,Модель!$A$8:$A$101,0)) -> 1680000 | H62: =INDEX(Модель!$G$8:$G$101,MATCH($B62,Модель!$A$8:$A$101,0)) -> 540000 | I62: =INDEX(Модель!$H$8:$H$101,MATCH($B62,Модель!$A$8:$A$101,0)) -> 8160000 | J62: Расчёт
A63: 2 | B63: NEW | C63: Новые фондированные клиенты | D63: LEADS × CR_OPEN × CR_FUND | E63: чел. | F63: =INDEX(Модель!$E$8:$E$101,MATCH($B63,Модель!$A$8:$A$101,0)) -> 74250 | G63: =INDEX(Модель!$F$8:$F$101,MATCH($B63,Модель!$A$8:$A$101,0)) -> 1120 | H63: =INDEX(Модель!$G$8:$G$101,MATCH($B63,Модель!$A$8:$A$101,0)) -> 36 | I63: =INDEX(Модель!$H$8:$H$101,MATCH($B63,Модель!$A$8:$A$101,0)) -> 75406 | J63: Расчёт
A64: 2 | B64: CAC | C64: Затраты на привлечение одного фондированного клиента (маркетинг, агентские, бонусы) | D64: Вводная | E64: у.е. | F64: =INDEX(Модель!$E$8:$E$101,MATCH($B64,Модель!$A$8:$A$101,0)) -> 80 | G64: =INDEX(Модель!$F$8:$F$101,MATCH($B64,Модель!$A$8:$A$101,0)) -> 1500 | H64: =INDEX(Модель!$G$8:$G$101,MATCH($B64,Модель!$A$8:$A$101,0)) -> 15000 | J64: Вводная: затратный
A65: 1 | B65: LOSS | C65: ПТ — потери | D65: C5 + C6 | E65: у.е. | F65: =INDEX(Модель!$E$8:$E$101,MATCH($B65,Модель!$A$8:$A$101,0)) -> 1314250 | G65: =INDEX(Модель!$F$8:$F$101,MATCH($B65,Модель!$A$8:$A$101,0)) -> 553300 | H65: =INDEX(Модель!$G$8:$G$101,MATCH($B65,Модель!$A$8:$A$101,0)) -> 602000 | I65: =INDEX(Модель!$H$8:$H$101,MATCH($B65,Модель!$A$8:$A$101,0)) -> 2469550 | J65: Расчёт
A66: 2 | B66: C5 | C66: Кредитные потери | D66: MPORT × CL | E66: у.е. | F66: =INDEX(Модель!$E$8:$E$101,MATCH($B66,Модель!$A$8:$A$101,0)) -> 1014250 | G66: =INDEX(Модель!$F$8:$F$101,MATCH($B66,Модель!$A$8:$A$101,0)) -> 453300 | H66: =INDEX(Модель!$G$8:$G$101,MATCH($B66,Модель!$A$8:$A$101,0)) -> 402000 | I66: =INDEX(Модель!$H$8:$H$101,MATCH($B66,Модель!$A$8:$A$101,0)) -> 1869550 | J66: Расчёт
A67: 3 | B67: CL | C67: Кредитные потери по маржинальному портфелю, % в год | D67: Вводная | E67: % | F67: =INDEX(Модель!$E$8:$E$101,MATCH($B67,Модель!$A$8:$A$101,0)) -> 0.005 | G67: =INDEX(Модель!$F$8:$F$101,MATCH($B67,Модель!$A$8:$A$101,0)) -> 0.002 | H67: =INDEX(Модель!$G$8:$G$101,MATCH($B67,Модель!$A$8:$A$101,0)) -> 0.001 | J67: Вводная: затратный
A68: 2 | B68: C6 | C68: Операционные потери | D68: OPLOSS | E68: у.е. | F68: =INDEX(Модель!$E$8:$E$101,MATCH($B68,Модель!$A$8:$A$101,0)) -> 300000 | G68: =INDEX(Модель!$F$8:$F$101,MATCH($B68,Модель!$A$8:$A$101,0)) -> 100000 | H68: =INDEX(Модель!$G$8:$G$101,MATCH($B68,Модель!$A$8:$A$101,0)) -> 200000 | I68: =INDEX(Модель!$H$8:$H$101,MATCH($B68,Модель!$A$8:$A$101,0)) -> 600000 | J68: Расчёт
A69: 3 | B69: OPLOSS | C69: Операционные потери за период: ошибки, компенсации клиентам, штрафы | D69: Вводная | E69: у.е. | F69: =INDEX(Модель!$E$8:$E$101,MATCH($B69,Модель!$A$8:$A$101,0)) -> 300000 | G69: =INDEX(Модель!$F$8:$F$101,MATCH($B69,Модель!$A$8:$A$101,0)) -> 100000 | H69: =INDEX(Модель!$G$8:$G$101,MATCH($B69,Модель!$A$8:$A$101,0)) -> 200000 | I69: =INDEX(Модель!$H$8:$H$101,MATCH($B69,Модель!$A$8:$A$101,0)) -> 600000 | J69: Вводная: затратный
A70: Клиентская база — общий драйвер веток R1–R7 и затрат
A71: 1 | B71: N_AVG | C71: Фондированные клиенты, среднее за период | D71: Горизонт 1: N0 + ½(NEW − CHURNED); 2: N0 + NEW − CHURNED; 3: NEW ÷ CHURN | E71: чел. | F71: =INDEX(Модель!$E$8:$E$101,MATCH($B71,Модель!$A$8:$A$101,0)) -> 507125 | G71: =INDEX(Модель!$F$8:$F$101,MATCH($B71,Модель!$A$8:$A$101,0)) -> 15110 | H71: =INDEX(Модель!$G$8:$G$101,MATCH($B71,Модель!$A$8:$A$101,0)) -> 402 | I71: =INDEX(Модель!$H$8:$H$101,MATCH($B71,Модель!$A$8:$A$101,0)) -> 522637 | J71: Расчёт
A72: 2 | B72: N0 | C72: Фондированные клиенты на начало периода | D72: Вводная | E72: чел. | F72: =INDEX(Модель!$E$8:$E$101,MATCH($B72,Модель!$A$8:$A$101,0)) -> 500000 | G72: =INDEX(Модель!$F$8:$F$101,MATCH($B72,Модель!$A$8:$A$101,0)) -> 15000 | H72: =INDEX(Модель!$G$8:$G$101,MATCH($B72,Модель!$A$8:$A$101,0)) -> 400 | I72: =INDEX(Модель!$H$8:$H$101,MATCH($B72,Модель!$A$8:$A$101,0)) -> 515400 | J72: Вводная: база
A73: 2 | B73: NEW | C73: Новые фондированные клиенты | D73: LEADS × CR_OPEN × CR_FUND | E73: чел. | F73: =INDEX(Модель!$E$8:$E$101,MATCH($B73,Модель!$A$8:$A$101,0)) -> 74250 | G73: =INDEX(Модель!$F$8:$F$101,MATCH($B73,Модель!$A$8:$A$101,0)) -> 1120 | H73: =INDEX(Модель!$G$8:$G$101,MATCH($B73,Модель!$A$8:$A$101,0)) -> 36 | I73: =INDEX(Модель!$H$8:$H$101,MATCH($B73,Модель!$A$8:$A$101,0)) -> 75406 | J73: Расчёт
A74: 3 | B74: LEADS | C74: Заявки на открытие счёта за период (ИК — потенциальные клиенты в воронке продаж) | D74: Вводная | E74: шт. | F74: =INDEX(Модель!$E$8:$E$101,MATCH($B74,Модель!$A$8:$A$101,0)) -> 300000 | G74: =INDEX(Модель!$F$8:$F$101,MATCH($B74,Модель!$A$8:$A$101,0)) -> 2000 | H74: =INDEX(Модель!$G$8:$G$101,MATCH($B74,Модель!$A$8:$A$101,0)) -> 120 | I74: =INDEX(Модель!$H$8:$H$101,MATCH($B74,Модель!$A$8:$A$101,0)) -> 302120 | J74: Вводная: объёмный
A75: 3 | B75: CR_OPEN | C75: Конверсия: заявка → открытый счёт (KYC пройден; ИК — договор подписан) | D75: Вводная | E75: % | F75: =INDEX(Модель!$E$8:$E$101,MATCH($B75,Модель!$A$8:$A$101,0)) -> 0.45 | G75: =INDEX(Модель!$F$8:$F$101,MATCH($B75,Модель!$A$8:$A$101,0)) -> 0.7 | H75: =INDEX(Модель!$G$8:$G$101,MATCH($B75,Модель!$A$8:$A$101,0)) -> 0.4 | J75: Вводная: объёмный
A76: 3 | B76: CR_FUND | C76: Конверсия: открытый счёт → фондированный (первое пополнение) | D76: Вводная | E76: % | F76: =INDEX(Модель!$E$8:$E$101,MATCH($B76,Модель!$A$8:$A$101,0)) -> 0.55 | G76: =INDEX(Модель!$F$8:$F$101,MATCH($B76,Модель!$A$8:$A$101,0)) -> 0.8 | H76: =INDEX(Модель!$G$8:$G$101,MATCH($B76,Модель!$A$8:$A$101,0)) -> 0.75 | J76: Вводная: объёмный
A77: 2 | B77: CHURNED | C77: Ушедшие фондированные клиенты | D77: N0 × CHURN | E77: чел. | F77: =INDEX(Модель!$E$8:$E$101,MATCH($B77,Модель!$A$8:$A$101,0)) -> 60000 | G77: =INDEX(Модель!$F$8:$F$101,MATCH($B77,Модель!$A$8:$A$101,0)) -> 900 | H77: =INDEX(Модель!$G$8:$G$101,MATCH($B77,Модель!$A$8:$A$101,0)) -> 32 | I77: =INDEX(Модель!$H$8:$H$101,MATCH($B77,Модель!$A$8:$A$101,0)) -> 60932 | J77: Расчёт
A78: 3 | B78: CHURN | C78: Годовой отток фондированных клиентов (вывели активы ниже порога или закрыли счёт) | D78: Вводная | E78: % | F78: =INDEX(Модель!$E$8:$E$101,MATCH($B78,Модель!$A$8:$A$101,0)) -> 0.12 | G78: =INDEX(Модель!$F$8:$F$101,MATCH($B78,Модель!$A$8:$A$101,0)) -> 0.06 | H78: =INDEX(Модель!$G$8:$G$101,MATCH($B78,Модель!$A$8:$A$101,0)) -> 0.08 | J78: Вводная: объёмный
A79: 1 | B79: ACTIVE | C79: Активные клиенты (среднемесячно) | D79: N_AVG × ACT | E79: чел. | F79: =INDEX(Модель!$E$8:$E$101,MATCH($B79,Модель!$A$8:$A$101,0)) -> 177493.75 | G79: =INDEX(Модель!$F$8:$F$101,MATCH($B79,Модель!$A$8:$A$101,0)) -> 8310.5 | H79: =INDEX(Модель!$G$8:$G$101,MATCH($B79,Модель!$A$8:$A$101,0)) -> 321.6 | I79: =INDEX(Модель!$H$8:$H$101,MATCH($B79,Модель!$A$8:$A$101,0)) -> 186125.85 | J79: Расчёт
A80: 2 | B80: ACT | C80: Доля активных: среднемесячная доля фондированных клиентов с ≥1 операцией (сделка, пополнение, покупка продукта или подписки) | D80: Вводная | E80: % | F80: =INDEX(Модель!$E$8:$E$101,MATCH($B80,Модель!$A$8:$A$101,0)) -> 0.35 | G80: =INDEX(Модель!$F$8:$F$101,MATCH($B80,Модель!$A$8:$A$101,0)) -> 0.55 | H80: =INDEX(Модель!$G$8:$G$101,MATCH($B80,Модель!$A$8:$A$101,0)) -> 0.8 | J80: Вводная: объёмный
A81: Производные KPI
A82: 1 | B82: ARPU | C82: Чистая выручка на фондированного клиента | D82: NR ÷ N_AVG | E82: у.е. | F82: =INDEX(Модель!$E$8:$E$101,MATCH($B82,Модель!$A$8:$A$101,0)) -> 86.092 | G82: =INDEX(Модель!$F$8:$F$101,MATCH($B82,Модель!$A$8:$A$101,0)) -> 2183.2 | H82: =INDEX(Модель!$G$8:$G$101,MATCH($B82,Модель!$A$8:$A$101,0)) -> 80726 | I82: =INDEX(Модель!$H$8:$H$101,MATCH($B82,Модель!$A$8:$A$101,0)) -> 208.74796 | J82: Расчёт
A83: 1 | B83: YIELD | C83: Доходность активов клиентов | D83: NR ÷ AUC × 10 000 | E83: б.п. | F83: =INDEX(Модель!$E$8:$E$101,MATCH($B83,Модель!$A$8:$A$101,0)) -> 107.615 | G83: =INDEX(Модель!$F$8:$F$101,MATCH($B83,Модель!$A$8:$A$101,0)) -> 109.16 | H83: =INDEX(Модель!$G$8:$G$101,MATCH($B83,Модель!$A$8:$A$101,0)) -> 32.2904 | I83: =INDEX(Модель!$H$8:$H$101,MATCH($B83,Модель!$A$8:$A$101,0)) -> 63.692807 | J83: Расчёт
A84: 1 | B84: CM_MARGIN | C84: Маржинальность (МД ÷ ЧВ) | D84: CM ÷ NR | E84: % | F84: =INDEX(Модель!$E$8:$E$101,MATCH($B84,Модель!$A$8:$A$101,0)) -> 0.72806089 | G84: =INDEX(Модель!$F$8:$F$101,MATCH($B84,Модель!$A$8:$A$101,0)) -> 0.70965712 | H84: =INDEX(Модель!$G$8:$G$101,MATCH($B84,Модель!$A$8:$A$101,0)) -> 0.81216111 | I84: =INDEX(Модель!$H$8:$H$101,MATCH($B84,Модель!$A$8:$A$101,0)) -> 0.74751197 | J84: Расчёт
A85: 1 | B85: CM_PC | C85: МД на фондированного клиента | D85: CM ÷ N_AVG | E85: у.е. | F85: =INDEX(Модель!$E$8:$E$101,MATCH($B85,Модель!$A$8:$A$101,0)) -> 62.680218 | G85: =INDEX(Модель!$F$8:$F$101,MATCH($B85,Модель!$A$8:$A$101,0)) -> 1549.3234 | H85: =INDEX(Модель!$G$8:$G$101,MATCH($B85,Модель!$A$8:$A$101,0)) -> 65562.517 | I85: =INDEX(Модель!$H$8:$H$101,MATCH($B85,Модель!$A$8:$A$101,0)) -> 156.0416 | J85: Расчёт
A86: 1 | B86: CONTRIB_PC | C86: Вклад клиента до затрат на привлечение, в год | D86: (NR − CTS − LOSS) ÷ N_AVG | E86: у.е. | F86: =INDEX(Модель!$E$8:$E$101,MATCH($B86,Модель!$A$8:$A$101,0)) -> 74.393306 | G86: =INDEX(Модель!$F$8:$F$101,MATCH($B86,Модель!$A$8:$A$101,0)) -> 1660.5081 | H86: =INDEX(Модель!$G$8:$G$101,MATCH($B86,Модель!$A$8:$A$101,0)) -> 66905.801 | I86: =INDEX(Модель!$H$8:$H$101,MATCH($B86,Модель!$A$8:$A$101,0)) -> 171.65473 | J86: Расчёт
A87: 1 | B87: LTV | C87: LTV — вклад клиента за срок жизни | D87: CONTRIB_PC ÷ (CHURNED ÷ N0) | E87: у.е. | F87: =INDEX(Модель!$E$8:$E$101,MATCH($B87,Модель!$A$8:$A$101,0)) -> 619.94422 | G87: =INDEX(Модель!$F$8:$F$101,MATCH($B87,Модель!$A$8:$A$101,0)) -> 27675.135 | H87: =INDEX(Модель!$G$8:$G$101,MATCH($B87,Модель!$A$8:$A$101,0)) -> 836322.51 | I87: =INDEX(Модель!$H$8:$H$101,MATCH($B87,Модель!$A$8:$A$101,0)) -> 1451.9604 | J87: Расчёт
A88: 1 | B88: LTV_CAC | C88: LTV ÷ CAC | D88: LTV ÷ (ACQ ÷ NEW) | E88: x | F88: =INDEX(Модель!$E$8:$E$101,MATCH($B88,Модель!$A$8:$A$101,0)) -> 7.7493027 | G88: =INDEX(Модель!$F$8:$F$101,MATCH($B88,Модель!$A$8:$A$101,0)) -> 18.45009 | H88: =INDEX(Модель!$G$8:$G$101,MATCH($B88,Модель!$A$8:$A$101,0)) -> 55.754834 | I88: =INDEX(Модель!$H$8:$H$101,MATCH($B88,Модель!$A$8:$A$101,0)) -> 13.417466 | J88: Расчёт
A89: 1 | B89: PAYBACK | C89: Срок окупаемости привлечения | D89: (ACQ ÷ NEW) ÷ (CONTRIB_PC ÷ 12) | E89: мес. | F89: =INDEX(Модель!$E$8:$E$101,MATCH($B89,Модель!$A$8:$A$101,0)) -> 12.904387 | G89: =INDEX(Модель!$F$8:$F$101,MATCH($B89,Модель!$A$8:$A$101,0)) -> 10.840056 | H89: =INDEX(Модель!$G$8:$G$101,MATCH($B89,Модель!$A$8:$A$101,0)) -> 2.6903497 | I89: =INDEX(Модель!$H$8:$H$101,MATCH($B89,Модель!$A$8:$A$101,0)) -> 7.5650137 | J89: Расчёт
A90: 1 | B90: RATE_SHARE | C90: Доля ЧВ, зависящая от процентных ставок | D90: (R2 + R3) ÷ NR | E90: % | F90: =INDEX(Модель!$E$8:$E$101,MATCH($B90,Модель!$A$8:$A$101,0)) -> 0.51108117 | G90: =INDEX(Модель!$F$8:$F$101,MATCH($B90,Модель!$A$8:$A$101,0)) -> 0.35269329 | H90: =INDEX(Модель!$G$8:$G$101,MATCH($B90,Модель!$A$8:$A$101,0)) -> 0.34065852 | I90: =INDEX(Модель!$H$8:$H$101,MATCH($B90,Модель!$A$8:$A$101,0)) -> 0.41249719 | J90: Расчёт

Sheet Вводные
A1: Вводные модели по сегментам
A2: Синий шрифт на жёлтом фоне — вводные. Значения иллюстративные: замените их фактическими данными. Все суммы — в условных единицах (у.е.) за период (год).
A4: Глобальные параметры
A5: SHOCK | B5: Шаг анализа чувствительности (улучшение драйвера, относительное) | C5: % | D5: 0.01 | L5: 1% — стандарт; модель линейна по каждому драйверу, поэтому эффект +5% = 5 × эффект +1%.
A6: HORIZON | B6: Горизонт оценки для листов «Сводка», «Дерево» и колонок E–H «Модели» | C6: режим | D6: 1 | L6: 1 — год 1: P&L плана, новые и ушедшие клиенты учитываются за полгода; 2 — run-rate на конец года; 3 — долгосрочно: база сходится к NEW ÷ CHURN. Чувствительность всегда считается в режимах 1 и 3.
A7: RATE_SHIFT | B7: Сценарий ставок: сдвиг рыночных ставок к текущим (FLOAT_Y, FUND_RATE) | C7: сдвиг | D7: -0.01 | L7: Решение 07.10.2026: план строится только на сценарии снижения ставок. Величина −1 п.п. — допущение, поменяйте при необходимости.
A8: PT_MRG | B8: Доля сдвига ставок, которая переходит в ставку по марже для клиентов | C8: коэф. | D8: 1 | L8: 1 — ставка по марже следует за рынком полностью, спред по марже сохраняется.
A9: PT_FLOAT | B9: Доля сдвига ставок, которая переходит в ставку клиентам на остатки | C9: коэф. | D9: 0.5 | L9: 0,5 — брокер снижает ставку клиентам вдвое медленнее рынка; спред на остатках сужается.
A11: коды сегментов → | D11: MR | E11: AF | F11: IC
A12: Код | B12: Параметр | C12: Ед. | D12: Масс-розница | E12: Состоятельные | F12: Институционалы и корп. | G12: Направление | H12: Управляемость | I12: Тип рычага | J12: Влияет на | K12: Источник / ориентир | L12: Комментарий
A13: Клиентская база и воронка
A14: N0 | B14: Фондированные клиенты на начало периода | C14: чел. | D14: 500000 | E14: 15000 | F14: 400 | G14: 1 | H14: Состояние | I14: База | J14: Все ветки | K14: Масштаб условный. | L14: Фондированный клиент — активы от ≈$100 в эквиваленте (решение 07.10.2026).
A15: LEADS | B15: Заявки на открытие счёта за период (ИК — потенциальные клиенты в воронке продаж) | C15: шт. | D15: 300000 | E15: 2000 | F15: 120 | G15: 1 | H15: Управляемый | I15: Объёмный | J15: NEW, C2 | K15: Масштаб условный.
A16: CR_OPEN | B16: Конверсия: заявка → открытый счёт (KYC пройден; ИК — договор подписан) | C16: % | D16: 0.45 | E16: 0.7 | F16: 0.4 | G16: 1 | H16: Управляемый | I16: Объёмный | J16: NEW | K16: Futu 2025: пользователь приложения → брокерский счёт 20,4%. Цифровой KYC завершают 60–90% начавших (вендорные данные).
A17: CR_FUND | B17: Конверсия: открытый счёт → фондированный (первое пополнение) | C17: % | D17: 0.55 | E17: 0.8 | F17: 0.75 | G17: 1 | H17: Управляемый | I17: Объёмный | J17: NEW | K17: Futu 2025: счёт → фондированный 56,6%. Регистрация → фондированный: eToro ≈9%, Webull 19–23%.
A18: CHURN | B18: Годовой отток фондированных клиентов (вывели активы ниже порога или закрыли счёт) | C18: % | D18: 0.12 | E18: 0.06 | F18: 0.08 | G18: -1 | H18: Управляемый | I18: Объёмный | J18: CHURNED → N_AVG, LTV | K18: Удержание клиентов в год: Webull и Futu ≈88–92%, Wealthfront 95%, AJ Bell 94,2%, Hargreaves Lansdown 91–92% (2023–2025).
A19: ACT | B19: Доля активных: среднемесячная доля фондированных клиентов с ≥1 операцией (сделка, пополнение, покупка продукта или подписки) | C19: % | D19: 0.35 | E19: 0.55 | F19: 0.8 | G19: 1 | H19: Управляемый | I19: Объёмный | J19: ACTIVE → TURN → R1 | K19: Активность «любая операция» лежит между торговой и заходами в приложение: Мосбиржа 2025 — в среднем месяце торгуют ≈24% непустых счетов [расчёт]; Robinhood — MAU ÷ фондированные ≈47% (2023).
A20: Торговая активность и комиссии
A21: TPA | B21: Сделок в месяц на активного клиента | C21: шт./клиент | D21: 6 | E21: 3.5 | F21: 130 | G21: 1 | H21: Частично | I21: Объёмный | J21: TURN → R1 | K21: Сделок на клиента в год: flatexDEGIRO 23–26, Nordnet ≈25–30 (в модели МР: ACT × TPA × 12 ≈ 25); счёт Schwab ≈75; IBKR ≈160 (2025–2026). | L21: Зависит от волатильности рынка.
A22: TICKET | B22: Средний объём сделки | C22: у.е. | D22: 800 | E22: 15000 | F22: 100000 | G22: 1 | H22: Частично | I22: Объёмный | J22: TURN → R1 | K22: Условно.
A23: TAKE | B23: Комиссия брокера, % от оборота (эффективная, с учётом тарифов и скидок) | C23: % | D23: 0.0015 | E23: 0.001 | F23: 0.0002 | G23: 1 | H23: Управляемый | I23: Ценовой | J23: R1 | K23: Тарифы: Россия 0,3% без абонплаты и 0,018–0,06% на активных тарифах; Казахстан: Freedom 0,085%, Halyk 0,03%. Эффективная ставка зависит от микса тарифов. | L23: Ценовой рычаг: эффект показан при неизменном обороте; учитывать эластичность.
A24: EXEC | B24: Затраты на исполнение (биржевые, клиринговые, депозитарные сборы, вышестоящий брокер), % от оборота | C24: % | D24: 0.0003 | E24: 0.0002 | F24: 8e-05 | G24: -1 | H24: Частично | I24: Затратный | J24: R1 | K24: IBKR 2025: затраты на исполнение и клиринг ≈21% от комиссий.
A25: Активы клиентов и свободные остатки
A26: AUC_PC | B26: Средние активы на фондированного клиента | C26: у.е. | D26: 8000 | E26: 200000 | F26: 25000000 | G26: 1 | H26: Частично | I26: Объёмный | J26: AUC → R3, R6, R7 | K26: Robinhood ≈ $10 тыс. на фондированного [расчёт: ARPU $171 ÷ 173 б.п.]; T-Investments ≈219 тыс. ₽ на клиента (2026); РФ: 2,3 млн ₽ на клиента с активами > 10 тыс. ₽ (ЦБ РФ, Q2 2026). | L26: Управляемая часть — чистый приток (NNA); переоценка — рыночный эффект.
A27: CASH | B27: Доля свободных денежных средств в активах клиентов | C27: % | D27: 0.12 | E27: 0.08 | F27: 0.05 | G27: 1 | H27: Частично | I27: Объёмный | J27: CASHBAL → R3 | K27: Свободные остатки к активам: Robinhood 8,1% (08.2026), Schwab 8,8–9,7%, IBKR 19–21% (2026). | L27: Рост доли кэша повышает R3, но может снижать оборот и продажи продуктов.
A28: FLOAT_Y | B28: Доходность размещения свободных остатков клиентов | C28: % | D28: 0.05 | E28: 0.05 | F28: 0.05 | G28: 1 | H28: Внешний | I28: Внешний | J28: R3 | K28: Внешний фактор: текущая ставка денежного рынка, к ней применяется сценарий RATE_SHIFT. | L28: Определяется ставками денежного рынка и правилами размещения клиентских средств.
A29: FLOAT_P | B29: Ставка, выплачиваемая клиентам на свободные остатки | C29: % | D29: 0.02 | E29: 0.025 | F29: 0.035 | G29: -1 | H29: Управляемый | I29: Ценовой | J29: R3 | K29: Условно: зависит от тарифной политики и конкурентов. | L29: Ценовой рычаг: снижение ставки может вызвать отток остатков.
A30: Маржинальное кредитование
A31: MRG_PEN | B31: Проникновение маржинальной торговли: доля фондированных клиентов с задолженностью | C31: % | D31: 0.05 | E31: 0.1 | F31: 0.2 | G31: 1 | H31: Управляемый | I31: Объёмный | J31: MPORT → R2, C5 | K31: Маржинальный портфель к активам: Robinhood 5,6% (08.2026), IBKR 10,9–11,7%, Schwab ≈1–1,3%. Доля клиентов с маржой публично не раскрывается.
A32: MRG_DEBT | B32: Средняя задолженность маржинального клиента | C32: у.е. | D32: 8000 | E32: 150000 | F32: 5000000 | G32: 1 | H32: Частично | I32: Объёмный | J32: MPORT → R2, C5 | K32: Через портфель к активам (см. MRG_PEN).
A33: MRG_RATE | B33: Ставка для клиента по маржинальному кредиту (деньги и ценные бумаги) | C33: % | D33: 0.12 | E33: 0.1 | F33: 0.08 | G33: 1 | H33: Управляемый | I33: Ценовой | J33: R2 | K33: Freedom (РК): базовая ставка НБРК + 4 п.п., не ниже 15%; T-Investments Premium ≈14–26% годовых [расчёт]. | L33: Ценовой рычаг: учитывать эластичность спроса на плечо.
A34: FUND_RATE | B34: Стоимость фондирования маржинального портфеля | C34: % | D34: 0.07 | E34: 0.07 | F34: 0.065 | G34: -1 | H34: Внешний | I34: Внешний | J34: R2 | K34: Внешний фактор: текущая стоимость фондирования, к ней применяется сценарий RATE_SHIFT.
A35: CL | B35: Кредитные потери по маржинальному портфелю, % в год | C35: % | D35: 0.005 | E35: 0.002 | F35: 0.001 | G35: -1 | H35: Частично | I35: Затратный | J35: C5 | K35: Условно; ориентир — данные риск-менеджмента.
A36: Валютообменные операции
A37: FX_PEN | B37: Доля фондированных клиентов, совершающих конвертации | C37: % | D37: 0.3 | E37: 0.5 | F37: 0.4 | G37: 1 | H37: Управляемый | I37: Объёмный | J37: FXVOLUME → R4 | K37: Условно: доля конвертирующих клиентов в открытых источниках не найдена.
A38: FX_VOL | B38: Объём конвертаций на конвертирующего клиента в год | C38: у.е. | D38: 5000 | E38: 100000 | F38: 10000000 | G38: 1 | H38: Частично | I38: Объёмный | J38: FXVOLUME → R4 | K38: Условно.
A39: FX_SPREAD | B39: Комиссия и спред за конвертацию, % от объёма | C39: % | D39: 0.005 | E39: 0.003 | F39: 0.0005 | G39: 1 | H39: Управляемый | I39: Ценовой | J39: R4 | K39: Условно; у Swissquote валютные операции ≈13% выручки (2025).
A40: Размещения и продукты
A41: PRD_PEN | B41: Доля фондированных клиентов, купивших размещения или продукты за год (ИК — доля клиентов-эмитентов, проведших размещение) | C41: % | D41: 0.08 | E41: 0.35 | F41: 0.05 | G41: 1 | H41: Управляемый | I41: Объёмный | J41: PRDVOLUME → R5 | K41: Условно; российские брокеры: комиссии за размещения выросли в 1,5 раза в 1П 2026.
A42: PRD_VOL | B42: Средний объём покупок продуктов на клиента в год (ИК — средний объём размещения) | C42: у.е. | D42: 3000 | E42: 80000 | F42: 50000000 | G42: 1 | H42: Частично | I42: Объёмный | J42: PRDVOLUME → R5 | K42: Условно.
A43: PRD_FEE | B43: Средняя комиссия или маржа по продуктам и размещениям, % от объёма | C43: % | D43: 0.01 | E43: 0.012 | F43: 0.01 | G43: 1 | H43: Управляемый | I43: Ценовой | J43: R5 | K43: Условно; диапазоны комиссий андеррайтинга не подтверждены источниками.
A44: ДУ и консультирование
A45: AM_SHARE | B45: Доля активов клиентов в ДУ, модельных портфелях и на консультировании | C45: % | D45: 0.02 | E45: 0.2 | F45: 0.05 | G45: 1 | H45: Управляемый | I45: Объёмный | J45: AUM → R6 | K45: UBS GWM: доля мандатов ≈38% (2024); активы с комиссией ≈44% инвестированных [расчёт].
A46: AM_FEE | B46: Комиссия за управление и консультирование, % годовых (вкл. success fee) | C46: % | D46: 0.01 | E46: 0.01 | F46: 0.003 | G46: 1 | H46: Управляемый | I46: Ценовой | J46: R6 | K46: Частные банки: валовая маржа на активы 82–91 б.п. (Julius Baer, EFG, 2025–2026).
A47: Подписки и сервисные комиссии
A48: SUB_PEN | B48: Доля фондированных клиентов с платной подпиской или премиальным тарифом | C48: % | D48: 0.08 | E48: 0.15 | F48: 0 | G48: 1 | H48: Управляемый | I48: Объёмный | J48: SUBS → R7 | K48: Robinhood Gold: 4,8 млн подписчиков ≈17% фондированных; ≈40% новых клиентов оформляют подписку (2026).
A49: SUB_PRICE | B49: Стоимость подписки или премиального обслуживания в год | C49: у.е. | D49: 60 | E49: 1000 | F49: 0 | G49: 1 | H49: Управляемый | I49: Ценовой | J49: R7 | K49: Robinhood Gold ≈ $5 в месяц; T «Трейдер» 290–390 ₽ в месяц.
A50: CUST_FEE | B50: Депозитарная и кастодиальная комиссия, % от активов в год | C50: % | D50: 0.0002 | E50: 0.0005 | F50: 0.0003 | G50: 1 | H50: Управляемый | I50: Ценовой | J50: R7 | K50: Условно: кастодиальные ставки не подтверждены источниками.
A51: Затраты на обслуживание
A52: SUP_RATE | B52: Обращений в поддержку на фондированного клиента в год | C52: шт./клиент | D52: 1 | E52: 3 | F52: 12 | G52: -1 | H52: Управляемый | I52: Затратный | J52: C1 | K52: Условно: нагрузку на поддержку брокеры не раскрывают.
A53: SUP_COST | B53: Стоимость обработки одного обращения | C53: у.е. | D53: 5 | E53: 15 | F53: 30 | G53: -1 | H53: Управляемый | I53: Затратный | J53: C1 | K53: Gartner (2019): $8,01 за живой контакт против $0,10 за самообслуживание.
A54: KYC_UNIT | B54: Стоимость автоматической проверки заявки (KYC/AML-сервисы, документы) | C54: у.е. | D54: 1.5 | E54: 3 | F54: 50 | G54: -1 | H54: Управляемый | I54: Затратный | J54: C2 | K54: Прайс-листы KYC-провайдеров (Sumsub, Veriff): $0,80–1,85 за проверку.
A55: KYC_MAN | B55: Доля заявок, требующих ручной проверки | C55: % | D55: 0.3 | E55: 0.6 | F55: 1 | G55: -1 | H55: Управляемый | I55: Затратный | J55: C2 | K55: Условно. | L55: Ручная проверка также удлиняет онбординг и снижает CR_OPEN.
A56: KYC_MAN_COST | B56: Стоимость ручной проверки заявки | C56: у.е. | D56: 8 | E56: 40 | F56: 1500 | G56: -1 | H56: Управляемый | I56: Затратный | J56: C2 | K56: Условно.
A57: OPS_PC | B57: Операций бэк-офиса на фондированного клиента в год (вводы/выводы, переводы ЦБ, корп. действия, заявления) | C57: шт./клиент | D57: 6 | E57: 15 | F57: 200 | G57: -1 | H57: Частично | I57: Затратный | J57: C3 | K57: Условно.
A58: OPS_MAN | B58: Доля операций с ручной обработкой (не STP) | C58: % | D58: 0.1 | E58: 0.25 | F58: 0.3 | G58: -1 | H58: Управляемый | I58: Затратный | J58: C3 | K58: Условно; DTCC: подтверждение сделки в день сделки ≈94,5–94,8% после перехода США на T+1 (институциональный ориентир STP).
A59: OPS_COST | B59: Стоимость ручной обработки одной операции | C59: у.е. | D59: 3 | E59: 10 | F59: 25 | G59: -1 | H59: Управляемый | I59: Затратный | J59: C3 | K59: Условно.
A60: RM_LOAD | B60: Клиентов на одного персонального менеджера / сотрудника покрытия (0 — модели нет) | C60: чел. | D60: 0 | E60: 150 | F60: 15 | G60: 1 | H60: Управляемый | I60: Затратный | J60: C4 | K60: Julius Baer: ≈ CHF 438 млн активов на менеджера (частный банк, верхняя граница). | L60: Затраты обратно пропорциональны нагрузке — эффект почти, но не строго линеен.
A61: RM_COST | B61: Полная годовая стоимость менеджера (ФОТ, налоги, бонусы, рабочее место) | C61: у.е. | D61: 0 | E61: 60000 | F61: 150000 | G61: -1 | H61: Частично | I61: Затратный | J61: C4 | K61: Условно.
A62: Привлечение и потери
A63: CAC | B63: Затраты на привлечение одного фондированного клиента (маркетинг, агентские, бонусы) | C63: у.е. | D63: 80 | E63: 1500 | F63: 15000 | G63: -1 | H63: Управляемый | I63: Затратный | J63: ACQ | K63: Robinhood: $15–53 на нового фондированного (2019–2021), ≈ $222 верхняя граница (2025); Wealthfront $85–131; Futu ≈ $295; Tiger $150–400; eToro ≈ $575 (верхняя граница). Маркетинг: 8,9% выручки Robinhood, 20% net contribution eToro.
A64: OPLOSS | B64: Операционные потери за период: ошибки, компенсации клиентам, штрафы | C64: у.е. | D64: 300000 | E64: 100000 | F64: 200000 | G64: -1 | H64: Управляемый | I64: Затратный | J64: C6 | K64: Условно.

Sheet Чувствительность
A1: Чувствительность маржинального дохода к драйверам
A2: Сколько у.е. МД в год даёт улучшение драйвера на 1% (относительно текущего значения) или на практический шаг, при прочих равных — в двух горизонтах: «год 1» (P&L плана) и «долгосрочно» (база сходится к NEW ÷ CHURN). Чувствительность — не приоритет: приоритет = ценность × достижимый сдвиг × вероятность ÷ трудозатраты.
J3: Базовый МД, год 1: | M3: =INDEX(Модель!$J$91:$JA$91,MATCH("MR|"&"BASE"&"|1",Модель!$J$6:$JA$6,0))+INDEX(Модель!$J$91:$JA$91,MATCH("AF|"&"BASE"&"|1",Модель!$J$6:$JA$6,0))+INDEX(Модель!$J$91:$JA$91,MATCH("IC|"&"BASE"&"|1",Модель!$J$6:$JA$6,0)) -> 81553114 | N3: Базовый МД, долгосрочно: | Q3: =INDEX(Модель!$J$91:$JA$91,MATCH("MR|"&"BASE"&"|3",Модель!$J$6:$JA$6,0))+INDEX(Модель!$J$91:$JA$91,MATCH("AF|"&"BASE"&"|3",Модель!$J$6:$JA$6,0))+INDEX(Модель!$J$91:$JA$91,MATCH("IC|"&"BASE"&"|3",Модель!$J$6:$JA$6,0)) -> 99380525
A4: Код | B4: Драйвер | C4: Ед. | D4: Направление | E4: Управляемость | F4: Тип рычага | G4: Значение: МР | H4: Значение: СК | I4: Значение: ИК | J4: ΔМД +1%, год 1: МР | K4: ΔМД +1%, год 1: СК | L4: ΔМД +1%, год 1: ИК | M4: ΔМД +1%, год 1: итого | N4: ΔМД +1%, долгосрочно: МР | O4: ΔМД +1%, долгосрочно: СК | P4: ΔМД +1%, долгосрочно: ИК | Q4: ΔМД +1%, долгосрочно: итого | R4: Доля от МД (долгосрочно) | S4: Ранг в группе (долгосрочно) | T4: Практический шаг | U4: ΔМД за шаг, год 1: итого | V4: ΔМД за шаг, долгосрочно: итого | W4: Комментарий | X4: ключ: объёмные и затратные | Y4: ключ: ценовые
A5: LEADS | B5: Заявки на открытие счёта за период (ИК — потенциальные клиенты в воронке продаж) | C5: шт. | D5: 1 | E5: Управляемый | F5: Объёмный | G5: =INDEX(Вводные!$D$13:$D$64,MATCH($A5,Вводные!$A$13:$A$64,0)) -> 300000 | H5: =INDEX(Вводные!$E$13:$E$64,MATCH($A5,Вводные!$A$13:$A$64,0)) -> 2000 | I5: =INDEX(Вводные!$F$13:$F$64,MATCH($A5,Вводные!$A$13:$A$64,0)) -> 120 | J5: =INDEX(Модель!$J$91:$JA$91,MATCH("MR|"&$A5&"|1",Модель!$J$6:$JA$6,0))-INDEX(Модель!$J$91:$JA$91,MATCH("MR|"&"BASE"&"|1",Модель!$J$6:$JA$6,0)) -> -42405.345 | K5: =INDEX(Модель!$J$91:$JA$91,MATCH("AF|"&$A5&"|1",Модель!$J$6:$JA$6,0))-INDEX(Модель!$J$91:$JA$91,MATCH("AF|"&"BASE"&"|1",Модель!$J$6:$JA$6,0)) -> -7984.08 | L5: =INDEX(Модель!$J$91:$JA$91,MATCH("IC|"&$A5&"|1",Модель!$J$6:$JA$6,0))-INDEX(Модель!$J$91:$JA$91,MATCH("IC|"&"BASE"&"|1",Модель!$J$6:$JA$6,0)) -> 4955.88 | M5: =SUM(J5:L5) -> -45433.545 | N5: =INDEX(Модель!$J$91:$JA$91,MATCH("MR|"&$A5&"|3",Модель!$J$6:$JA$6,0))-INDEX(Модель!$J$91:$JA$91,MATCH("MR|"&"BASE"&"|3",Модель!$J$6:$JA$6,0)) -> 407144.25 | O5: =INDEX(Модель!$J$91:$JA$91,MATCH("AF|"&$A5&"|3",Модель!$J$6:$JA$6,0))-INDEX(Модель!$J$91:$JA$91,MATCH("AF|"&"BASE"&"|3",Модель!$J$6:$JA$6,0)) -> 294524 | P5: =INDEX(Модель!$J$91:$JA$91,MATCH("IC|"&$A5&"|3",Модель!$J$6:$JA$6,0))-INDEX(Модель!$J$91:$JA$91,MATCH("IC|"&"BASE"&"|3",Модель!$J$6:$JA$6,0)) -> 298137 | Q5: =SUM(N5:P5) -> 999805.25 | R5: =IF($Q$3<>0,Q5/$Q$3,0) -> 0.010060374 | S5: =IF($E5="Внешний","",IF($F5="Ценовой",RANK(Y5,$Y$5:$Y$45),RANK(X5,$X$5:$X$45))) -> 4 | W5: В горизонте «год 1» рост привлечения снижает МД: CAC платится сразу, доход приходит позже. | X5: =IF(OR($E5="Внешний",$F5="Ценовой"),-1000000000000000,Q5)+ROW()/1000000000 -> 999805.25 | Y5: =IF($F5<>"Ценовой",-1000000000000000,Q5)+ROW()/1000000000 -> -1e+15
A6: CR_OPEN | B6: Конверсия: заявка → открытый счёт (KYC пройден; ИК — договор подписан) | C6: % | D6: 1 | E6: Управляемый | F6: Объёмный | G6: =INDEX(Вводные!$D$13:$D$64,MATCH($A6,Вводные!$A$13:$A$64,0)) -> 0.45 | H6: =INDEX(Вводные!$E$13:$E$64,MATCH($A6,Вводные!$A$13:$A$64,0)) -> 0.7 | I6: =INDEX(Вводные!$F$13:$F$64,MATCH($A6,Вводные!$A$13:$A$64,0)) -> 0.4 | J6: =INDEX(Модель!$J$91:$JA$91,MATCH("MR|"&$A6&"|1",Модель!$J$6:$JA$6,0))-INDEX(Модель!$J$91:$JA$91,MATCH("MR|"&"BASE"&"|1",Модель!$J$6:$JA$6,0)) -> -30705.345 | K6: =INDEX(Модель!$J$91:$JA$91,MATCH("AF|"&$A6&"|1",Модель!$J$6:$JA$6,0))-INDEX(Модель!$J$91:$JA$91,MATCH("AF|"&"BASE"&"|1",Модель!$J$6:$JA$6,0)) -> -7444.08 | L6: =INDEX(Модель!$J$91:$JA$91,MATCH("IC|"&$A6&"|1",Модель!$J$6:$JA$6,0))-INDEX(Модель!$J$91:$JA$91,MATCH("IC|"&"BASE"&"|1",Модель!$J$6:$JA$6,0)) -> 6815.88 | M6: =SUM(J6:L6) -> -31333.545 | N6: =INDEX(Модель!$J$91:$JA$91,MATCH("MR|"&$A6&"|3",Модель!$J$6:$JA$6,0))-INDEX(Модель!$J$91:$JA$91,MATCH("MR|"&"BASE"&"|3",Модель!$J$6:$JA$6,0)) -> 418844.25 | O6: =INDEX(Модель!$J$91:$JA$91,MATCH("AF|"&$A6&"|3",Модель!$J$6:$JA$6,0))-INDEX(Модель!$J$91:$JA$91,MATCH("AF|"&"BASE"&"|3",Модель!$J$6:$JA$6,0)) -> 295064 | P6: =INDEX(Модель!$J$91:$JA$91,MATCH("IC|"&$A6&"|3",Модель!$J$6:$JA$6,0))-INDEX(Модель!$J$91:$JA$91,MATCH("IC|"&"BASE"&"|3",Модель!$J$6:$JA$6,0)) -> 299997 | Q6: =SUM(N6:P6) -> 1013905.3 | R6: =IF($Q$3<>0,Q6/$Q$3,0) -> 0.010202253 | S6: =IF($E6="Внешний","",IF($F6="Ценовой",RANK(Y6,$Y$5:$Y$45),RANK(X6,$X$5:$X$45))) -> 3 | T6: 1 п.п. | U6: =IF(G6<>0,J6*0.01/(G6*Вводные!$D$5),0)+IF(H6<>0,K6*0.01/(H6*Вводные!$D$5),0)+IF(I6<>0,L6*0.01/(I6*Вводные!$D$5),0) -> -61828.8 | V6: =IF(G6<>0,N6*0.01/(G6*Вводные!$D$5),0)+IF(H6<>0,O6*0.01/(H6*Вводные!$D$5),0)+IF(I6<>0,P6*0.01/(I6*Вводные!$D$5),0) -> 2102277.5 | W6: В горизонте «год 1» рост привлечения снижает МД: CAC платится сразу, доход приходит позже. | X6: =IF(OR($E6="Внешний",$F6="Ценовой"),-1000000000000000,Q6)+ROW()/1000000000 -> 1013905.3 | Y6: =IF($F6<>"Ценовой",-1000000000000000,Q6)+ROW()/1000000000 -> -1e+15
A7: CR_FUND | B7: Конверсия: открытый счёт → фондированный (первое пополнение) | C7: % | D7: 1 | E7: Управляемый | F7: Объёмный | G7: =INDEX(Вводные!$D$13:$D$64,MATCH($A7,Вводные!$A$13:$A$64,0)) -> 0.55 | H7: =INDEX(Вводные!$E$13:$E$64,MATCH($A7,Вводные!$A$13:$A$64,0)) -> 0.8 | I7: =INDEX(Вводные!$F$13:$F$64,MATCH($A7,Вводные!$A$13:$A$64,0)) -> 0.75 | J7: =INDEX(Модель!$J$91:$JA$91,MATCH("MR|"&$A7&"|1",Модель!$J$6:$JA$6,0))-INDEX(Модель!$J$91:$JA$91,MATCH("MR|"&"BASE"&"|1",Модель!$J$6:$JA$6,0)) -> -30705.345 | K7: =INDEX(Модель!$J$91:$JA$91,MATCH("AF|"&$A7&"|1",Модель!$J$6:$JA$6,0))-INDEX(Модель!$J$91:$JA$91,MATCH("AF|"&"BASE"&"|1",Модель!$J$6:$JA$6,0)) -> -7444.08 | L7: =INDEX(Модель!$J$91:$JA$91,MATCH("IC|"&$A7&"|1",Модель!$J$6:$JA$6,0))-INDEX(Модель!$J$91:$JA$91,MATCH("IC|"&"BASE"&"|1",Модель!$J$6:$JA$6,0)) -> 6815.88 | M7: =SUM(J7:L7) -> -31333.545 | N7: =INDEX(Модель!$J$91:$JA$91,MATCH("MR|"&$A7&"|3",Модель!$J$6:$JA$6,0))-INDEX(Модель!$J$91:$JA$91,MATCH("MR|"&"BASE"&"|3",Модель!$J$6:$JA$6,0)) -> 418844.25 | O7: =INDEX(Модель!$J$91:$JA$91,MATCH("AF|"&$A7&"|3",Модель!$J$6:$JA$6,0))-INDEX(Модель!$J$91:$JA$91,MATCH("AF|"&"BASE"&"|3",Модель!$J$6:$JA$6,0)) -> 295064 | P7: =INDEX(Модель!$J$91:$JA$91,MATCH("IC|"&$A7&"|3",Модель!$J$6:$JA$6,0))-INDEX(Модель!$J$91:$JA$91,MATCH("IC|"&"BASE"&"|3",Модель!$J$6:$JA$6,0)) -> 299997 | Q7: =SUM(N7:P7) -> 1013905.3 | R7: =IF($Q$3<>0,Q7/$Q$3,0) -> 0.010202253 | S7: =IF($E7="Внешний","",IF($F7="Ценовой",RANK(Y7,$Y$5:$Y$45),RANK(X7,$X$5:$X$45))) -> 2 | T7: 1 п.п. | U7: =IF(G7<>0,J7*0.01/(G7*Вводные!$D$5),0)+IF(H7<>0,K7*0.01/(H7*Вводные!$D$5),0)+IF(I7<>0,L7*0.01/(I7*Вводные!$D$5),0) -> -56045.16 | V7: =IF(G7<>0,N7*0.01/(G7*Вводные!$D$5),0)+IF(H7<>0,O7*0.01/(H7*Вводные!$D$5),0)+IF(I7<>0,P7*0.01/(I7*Вводные!$D$5),0) -> 1530361 | W7: В горизонте «год 1» рост привлечения снижает МД: CAC платится сразу, доход приходит позже. | X7: =IF(OR($E7="Внешний",$F7="Ценовой"),-1000000000000000,Q7)+ROW()/1000000000 -> 1013905.3 | Y7: =IF($F7<>"Ценовой",-1000000000000000,Q7)+ROW()/1000000000 -> -1e+15
A8: CHURN | B8: Годовой отток фондированных клиентов (вывели активы ниже порога или закрыли счёт) | C8: % | D8: -1 | E8: Управляемый | F8: Объёмный | G8: =INDEX(Вводные!$D$13:$D$64,MATCH($A8,Вводные!$A$13:$A$64,0)) -> 0.12 | H8: =INDEX(Вводные!$E$13:$E$64,MATCH($A8,Вводные!$A$13:$A$64,0)) -> 0.06 | I8: =INDEX(Вводные!$F$13:$F$64,MATCH($A8,Вводные!$A$13:$A$64,0)) -> 0.08 | J8: =INDEX(Модель!$J$91:$JA$91,MATCH("MR|"&$A8&"|1",Модель!$J$6:$JA$6,0))-INDEX(Модель!$J$91:$JA$91,MATCH("MR|"&"BASE"&"|1",Модель!$J$6:$JA$6,0)) -> 23187.6 | K8: =INDEX(Модель!$J$91:$JA$91,MATCH("AF|"&$A8&"|1",Модель!$J$6:$JA$6,0))-INDEX(Модель!$J$91:$JA$91,MATCH("AF|"&"BASE"&"|1",Модель!$J$6:$JA$6,0)) -> 7518.15 | L8: =INDEX(Модель!$J$91:$JA$91,MATCH("IC|"&$A8&"|1",Модель!$J$6:$JA$6,0))-INDEX(Модель!$J$91:$JA$91,MATCH("IC|"&"BASE"&"|1",Модель!$J$6:$JA$6,0)) -> 10858.56 | M8: =SUM(J8:L8) -> 41564.31 | N8: =INDEX(Модель!$J$91:$JA$91,MATCH("MR|"&$A8&"|3",Модель!$J$6:$JA$6,0))-INDEX(Модель!$J$91:$JA$91,MATCH("MR|"&"BASE"&"|3",Модель!$J$6:$JA$6,0)) -> 483075 | O8: =INDEX(Модель!$J$91:$JA$91,MATCH("AF|"&$A8&"|3",Модель!$J$6:$JA$6,0))-INDEX(Модель!$J$91:$JA$91,MATCH("AF|"&"BASE"&"|3",Модель!$J$6:$JA$6,0)) -> 315014.14 | P8: =INDEX(Модель!$J$91:$JA$91,MATCH("IC|"&$A8&"|3",Модель!$J$6:$JA$6,0))-INDEX(Модель!$J$91:$JA$91,MATCH("IC|"&"BASE"&"|3",Модель!$J$6:$JA$6,0)) -> 308481.82 | Q8: =SUM(N8:P8) -> 1106571 | R8: =IF($Q$3<>0,Q8/$Q$3,0) -> 0.011134686 | S8: =IF($E8="Внешний","",IF($F8="Ценовой",RANK(Y8,$Y$5:$Y$45),RANK(X8,$X$5:$X$45))) -> 1 | T8: 1 п.п. | U8: =IF(G8<>0,J8*0.01/(G8*Вводные!$D$5),0)+IF(H8<>0,K8*0.01/(H8*Вводные!$D$5),0)+IF(I8<>0,L8*0.01/(I8*Вводные!$D$5),0) -> 454264.5 | V8: =IF(G8<>0,N8*0.01/(G8*Вводные!$D$5),0)+IF(H8<>0,O8*0.01/(H8*Вводные!$D$5),0)+IF(I8<>0,P8*0.01/(I8*Вводные!$D$5),0) -> 13131883 | W8: Долгосрочный эффект нелинеен (база = NEW ÷ CHURN): шаг в 1 п.п. оценён приблизительно. | X8: =IF(OR($E8="Внешний",$F8="Ценовой"),-1000000000000000,Q8)+ROW()/1000000000 -> 1106571 | Y8: =IF($F8<>"Ценовой",-1000000000000000,Q8)+ROW()/1000000000 -> -1e+15
A9: ACT | B9: Доля активных: среднемесячная доля фондированных клиентов с ≥1 операцией (сделка, пополнение, покупка продукта или подписки) | C9: % | D9: 1 | E9: Управляемый | F9: Объёмный | G9: =INDEX(Вводные!$D$13:$D$64,MATCH($A9,Вводные!$A$13:$A$64,0)) -> 0.35 | H9: =INDEX(Вводные!$E$13:$E$64,MATCH($A9,Вводные!$A$13:$A$64,0)) -> 0.55 | I9: =INDEX(Вводные!$F$13:$F$64,MATCH($A9,Вводные!$A$13:$A$64,0)) -> 0.8 | J9: =INDEX(Модель!$J$91:$JA$91,MATCH("MR|"&$A9&"|1",Модель!$J$6:$JA$6,0))-INDEX(Модель!$J$91:$JA$91,MATCH("MR|"&"BASE"&"|1",Модель!$J$6:$JA$6,0)) -> 122683.68 | K9: =INDEX(Модель!$J$91:$JA$91,MATCH("AF|"&$A9&"|1",Модель!$J$6:$JA$6,0))-INDEX(Модель!$J$91:$JA$91,MATCH("AF|"&"BASE"&"|1",Модель!$J$6:$JA$6,0)) -> 41884.92 | L9: =INDEX(Модель!$J$91:$JA$91,MATCH("IC|"&$A9&"|1",Модель!$J$6:$JA$6,0))-INDEX(Модель!$J$91:$JA$91,MATCH("IC|"&"BASE"&"|1",Модель!$J$6:$JA$6,0)) -> 60203.52 | M9: =SUM(J9:L9) -> 224772.12 | N9: =INDEX(Модель!$J$91:$JA$91,MATCH("MR|"&$A9&"|3",Модель!$J$6:$JA$6,0))-INDEX(Модель!$J$91:$JA$91,MATCH("MR|"&"BASE"&"|3",Модель!$J$6:$JA$6,0)) -> 149688 | O9: =INDEX(Модель!$J$91:$JA$91,MATCH("AF|"&$A9&"|3",Модель!$J$6:$JA$6,0))-INDEX(Модель!$J$91:$JA$91,MATCH("AF|"&"BASE"&"|3",Модель!$J$6:$JA$6,0)) -> 51744 | P9: =INDEX(Модель!$J$91:$JA$91,MATCH("IC|"&$A9&"|3",Модель!$J$6:$JA$6,0))-INDEX(Модель!$J$91:$JA$91,MATCH("IC|"&"BASE"&"|3",Модель!$J$6:$JA$6,0)) -> 67392 | Q9: =SUM(N9:P9) -> 268824 | R9: =IF($Q$3<>0,Q9/$Q$3,0) -> 0.0027049968 | S9: =IF($E9="Внешний","",IF($F9="Ценовой",RANK(Y9,$Y$5:$Y$45),RANK(X9,$X$5:$X$45))) -> 8 | T9: 1 п.п. | U9: =IF(G9<>0,J9*0.01/(G9*Вводные!$D$5),0)+IF(H9<>0,K9*0.01/(H9*Вводные!$D$5),0)+IF(I9<>0,L9*0.01/(I9*Вводные!$D$5),0) -> 501933.6 | V9: =IF(G9<>0,N9*0.01/(G9*Вводные!$D$5),0)+IF(H9<>0,O9*0.01/(H9*Вводные!$D$5),0)+IF(I9<>0,P9*0.01/(I9*Вводные!$D$5),0) -> 606000 | X9: =IF(OR($E9="Внешний",$F9="Ценовой"),-1000000000000000,Q9)+ROW()/1000000000 -> 268824 | Y9: =IF($F9<>"Ценовой",-1000000000000000,Q9)+ROW()/1000000000 -> -1e+15
A10: TPA | B10: Сделок в месяц на активного клиента | C10: шт./клиент | D10: 1 | E10: Частично | F10: Объёмный | G10: =INDEX(Вводные!$D$13:$D$64,MATCH($A10,Вводные!$A$13:$A$64,0)) -> 6 | H10: =INDEX(Вводные!$E$13:$E$64,MATCH($A10,Вводные!$A$13:$A$64,0)) -> 3.5 | I10: =INDEX(Вводные!$F$13:$F$64,MATCH($A10,Вводные!$A$13:$A$64,0)) -> 130 | J10: =INDEX(Модель!$J$91:$JA$91,MATCH("MR|"&$A10&"|1",Модель!$J$6:$JA$6,0))-INDEX(Модель!$J$91:$JA$91,MATCH("MR|"&"BASE"&"|1",Модель!$J$6:$JA$6,0)) -> 122683.68 | K10: =INDEX(Модель!$J$91:$JA$91,MATCH("AF|"&$A10&"|1",Модель!$J$6:$JA$6,0))-INDEX(Модель!$J$91:$JA$91,MATCH("AF|"&"BASE"&"|1",Модель!$J$6:$JA$6,0)) -> 41884.92 | L10: =INDEX(Модель!$J$91:$JA$91,MATCH("IC|"&$A10&"|1",Модель!$J$6:$JA$6,0))-INDEX(Модель!$J$91:$JA$91,MATCH("IC|"&"BASE"&"|1",Модель!$J$6:$JA$6,0)) -> 60203.52 | M10: =SUM(J10:L10) -> 224772.12 | N10: =INDEX(Модель!$J$91:$JA$91,MATCH("MR|"&$A10&"|3",Модель!$J$6:$JA$6,0))-INDEX(Модель!$J$91:$JA$91,MATCH("MR|"&"BASE"&"|3",Модель!$J$6:$JA$6,0)) -> 149688 | O10: =INDEX(Модель!$J$91:$JA$91,MATCH("AF|"&$A10&"|3",Модель!$J$6:$JA$6,0))-INDEX(Модель!$J$91:$JA$91,MATCH("AF|"&"BASE"&"|3",Модель!$J$6:$JA$6,0)) -> 51744 | P10: =INDEX(Модель!$J$91:$JA$91,MATCH("IC|"&$A10&"|3",Модель!$J$6:$JA$6,0))-INDEX(Модель!$J$91:$JA$91,MATCH("IC|"&"BASE"&"|3",Модель!$J$6:$JA$6,0)) -> 67392 | Q10: =SUM(N10:P10) -> 268824 | R10: =IF($Q$3<>0,Q10/$Q$3,0) -> 0.0027049968 | S10: =IF($E10="Внешний","",IF($F10="Ценовой",RANK(Y10,$Y$5:$Y$45),RANK(X10,$X$5:$X$45))) -> 7 | X10: =IF(OR($E10="Внешний",$F10="Ценовой"),-1000000000000000,Q10)+ROW()/1000000000 -> 268824 | Y10: =IF($F10<>"Ценовой",-1000000000000000,Q10)+ROW()/1000000000 -> -1e+15
A11: TICKET | B11: Средний объём сделки | C11: у.е. | D11: 1 | E11: Частично | F11: Объёмный | G11: =INDEX(Вводные!$D$13:$D$64,MATCH($A11,Вводные!$A$13:$A$64,0)) -> 800 | H11: =INDEX(Вводные!$E$13:$E$64,MATCH($A11,Вводные!$A$13:$A$64,0)) -> 15000 | I11: =INDEX(Вводные!$F$13:$F$64,MATCH($A11,Вводные!$A$13:$A$64,0)) -> 100000 | J11: =INDEX(Модель!$J$91:$JA$91,MATCH("MR|"&$A11&"|1",Модель!$J$6:$JA$6,0))-INDEX(Модель!$J$91:$JA$91,MATCH("MR|"&"BASE"&"|1",Модель!$J$6:$JA$6,0)) -> 122683.68 | K11: =INDEX(Модель!$J$91:$JA$91,MATCH("AF|"&$A11&"|1",Модель!$J$6:$JA$6,0))-INDEX(Модель!$J$91:$JA$91,MATCH("AF|"&"BASE"&"|1",Модель!$J$6:$JA$6,0)) -> 41884.92 | L11: =INDEX(Модель!$J$91:$JA$91,MATCH("IC|"&$A11&"|1",Модель!$J$6:$JA$6,0))-INDEX(Модель!$J$91:$JA$91,MATCH("IC|"&"BASE"&"|1",Модель!$J$6:$JA$6,0)) -> 60203.52 | M11: =SUM(J11:L11) -> 224772.12 | N11: =INDEX(Модель!$J$91:$JA$91,MATCH("MR|"&$A11&"|3",Модель!$J$6:$JA$6,0))-INDEX(Модель!$J$91:$JA$91,MATCH("MR|"&"BASE"&"|3",Модель!$J$6:$JA$6,0)) -> 149688 | O11: =INDEX(Модель!$J$91:$JA$91,MATCH("AF|"&$A11&"|3",Модель!$J$6:$JA$6,0))-INDEX(Модель!$J$91:$JA$91,MATCH("AF|"&"BASE"&"|3",Модель!$J$6:$JA$6,0)) -> 51744 | P11: =INDEX(Модель!$J$91:$JA$91,MATCH("IC|"&$A11&"|3",Модель!$J$6:$JA$6,0))-INDEX(Модель!$J$91:$JA$91,MATCH("IC|"&"BASE"&"|3",Модель!$J$6:$JA$6,0)) -> 67392 | Q11: =SUM(N11:P11) -> 268824 | R11: =IF($Q$3<>0,Q11/$Q$3,0) -> 0.0027049968 | S11: =IF($E11="Внешний","",IF($F11="Ценовой",RANK(Y11,$Y$5:$Y$45),RANK(X11,$X$5:$X$45))) -> 6 | X11: =IF(OR($E11="Внешний",$F11="Ценовой"),-1000000000000000,Q11)+ROW()/1000000000 -> 268824 | Y11: =IF($F11<>"Ценовой",-1000000000000000,Q11)+ROW()/1000000000 -> -1e+15
A12: TAKE | B12: Комиссия брокера, % от оборота (эффективная, с учётом тарифов и скидок) | C12: % | D12: 1 | E12: Управляемый | F12: Ценовой | G12: =INDEX(Вводные!$D$13:$D$64,MATCH($A12,Вводные!$A$13:$A$64,0)) -> 0.0015 | H12: =INDEX(Вводные!$E$13:$E$64,MATCH($A12,Вводные!$A$13:$A$64,0)) -> 0.001 | I12: =INDEX(Вводные!$F$13:$F$64,MATCH($A12,Вводные!$A$13:$A$64,0)) -> 0.0002 | J12: =INDEX(Модель!$J$91:$JA$91,MATCH("MR|"&$A12&"|1",Модель!$J$6:$JA$6,0))-INDEX(Модель!$J$91:$JA$91,MATCH("MR|"&"BASE"&"|1",Модель!$J$6:$JA$6,0)) -> 153354.6 | K12: =INDEX(Модель!$J$91:$JA$91,MATCH("AF|"&$A12&"|1",Модель!$J$6:$JA$6,0))-INDEX(Модель!$J$91:$JA$91,MATCH("AF|"&"BASE"&"|1",Модель!$J$6:$JA$6,0)) -> 52356.15 | L12: =INDEX(Модель!$J$91:$JA$91,MATCH("IC|"&$A12&"|1",Модель!$J$6:$JA$6,0))-INDEX(Модель!$J$91:$JA$91,MATCH("IC|"&"BASE"&"|1",Модель!$J$6:$JA$6,0)) -> 100339.2 | M12: =SUM(J12:L12) -> 306049.95 | N12: =INDEX(Модель!$J$91:$JA$91,MATCH("MR|"&$A12&"|3",Модель!$J$6:$JA$6,0))-INDEX(Модель!$J$91:$JA$91,MATCH("MR|"&"BASE"&"|3",Модель!$J$6:$JA$6,0)) -> 187110 | O12: =INDEX(Модель!$J$91:$JA$91,MATCH("AF|"&$A12&"|3",Модель!$J$6:$JA$6,0))-INDEX(Модель!$J$91:$JA$91,MATCH("AF|"&"BASE"&"|3",Модель!$J$6:$JA$6,0)) -> 64680 | P12: =INDEX(Модель!$J$91:$JA$91,MATCH("IC|"&$A12&"|3",Модель!$J$6:$JA$6,0))-INDEX(Модель!$J$91:$JA$91,MATCH("IC|"&"BASE"&"|3",Модель!$J$6:$JA$6,0)) -> 112320 | Q12: =SUM(N12:P12) -> 364110 | R12: =IF($Q$3<>0,Q12/$Q$3,0) -> 0.0036637963 | S12: =IF($E12="Внешний","",IF($F12="Ценовой",RANK(Y12,$Y$5:$Y$45),RANK(X12,$X$5:$X$45))) -> 3 | T12: 1 б.п. | U12: =IF(G12<>0,J12*0.0001/(G12*Вводные!$D$5),0)+IF(H12<>0,K12*0.0001/(H12*Вводные!$D$5),0)+IF(I12<>0,L12*0.0001/(I12*Вводные!$D$5),0) -> 6562885.5 | V12: =IF(G12<>0,N12*0.0001/(G12*Вводные!$D$5),0)+IF(H12<>0,O12*0.0001/(H12*Вводные!$D$5),0)+IF(I12<>0,P12*0.0001/(I12*Вводные!$D$5),0) -> 7510200 | W12: Ценовой рычаг: эффект при неизменных объёмах — учитывать эластичность. | X12: =IF(OR($E12="Внешний",$F12="Ценовой"),-1000000000000000,Q12)+ROW()/1000000000 -> -1e+15 | Y12: =IF($F12<>"Ценовой",-1000000000000000,Q12)+ROW()/1000000000 -> 364110
A13: EXEC | B13: Затраты на исполнение (биржевые, клиринговые, депозитарные сборы, вышестоящий брокер), % от оборота | C13: % | D13: -1 | E13: Частично | F13: Затратный | G13: =INDEX(Вводные!$D$13:$D$64,MATCH($A13,Вводные!$A$13:$A$64,0)) -> 0.0003 | H13: =INDEX(Вводные!$E$13:$E$64,MATCH($A13,Вводные!$A$13:$A$64,0)) -> 0.0002 | I13: =INDEX(Вводные!$F$13:$F$64,MATCH($A13,Вводные!$A$13:$A$64,0)) -> 8e-05 | J13: =INDEX(Модель!$J$91:$JA$91,MATCH("MR|"&$A13&"|1",Модель!$J$6:$JA$6,0))-INDEX(Модель!$J$91:$JA$91,MATCH("MR|"&"BASE"&"|1",Модель!$J$6:$JA$6,0)) -> 30670.92 | K13: =INDEX(Модель!$J$91:$JA$91,MATCH("AF|"&$A13&"|1",Модель!$J$6:$JA$6,0))-INDEX(Модель!$J$91:$JA$91,MATCH("AF|"&"BASE"&"|1",Модель!$J$6:$JA$6,0)) -> 10471.23 | L13: =INDEX(Модель!$J$91:$JA$91,MATCH("IC|"&$A13&"|1",Модель!$J$6:$JA$6,0))-INDEX(Модель!$J$91:$JA$91,MATCH("IC|"&"BASE"&"|1",Модель!$J$6:$JA$6,0)) -> 40135.68 | M13: =SUM(J13:L13) -> 81277.83 | N13: =INDEX(Модель!$J$91:$JA$91,MATCH("MR|"&$A13&"|3",Модель!$J$6:$JA$6,0))-INDEX(Модель!$J$91:$JA$91,MATCH("MR|"&"BASE"&"|3",Модель!$J$6:$JA$6,0)) -> 37422 | O13: =INDEX(Модель!$J$91:$JA$91,MATCH("AF|"&$A13&"|3",Модель!$J$6:$JA$6,0))-INDEX(Модель!$J$91:$JA$91,MATCH("AF|"&"BASE"&"|3",Модель!$J$6:$JA$6,0)) -> 12936 | P13: =INDEX(Модель!$J$91:$JA$91,MATCH("IC|"&$A13&"|3",Модель!$J$6:$JA$6,0))-INDEX(Модель!$J$91:$JA$91,MATCH("IC|"&"BASE"&"|3",Модель!$J$6:$JA$6,0)) -> 44928 | Q13: =SUM(N13:P13) -> 95286 | R13: =IF($Q$3<>0,Q13/$Q$3,0) -> 0.00095879952 | S13: =IF($E13="Внешний","",IF($F13="Ценовой",RANK(Y13,$Y$5:$Y$45),RANK(X13,$X$5:$X$45))) -> 17 | T13: 1 б.п. | U13: =IF(G13<>0,J13*0.0001/(G13*Вводные!$D$5),0)+IF(H13<>0,K13*0.0001/(H13*Вводные!$D$5),0)+IF(I13<>0,L13*0.0001/(I13*Вводные!$D$5),0) -> 6562885.5 | V13: =IF(G13<>0,N13*0.0001/(G13*Вводные!$D$5),0)+IF(H13<>0,O13*0.0001/(H13*Вводные!$D$5),0)+IF(I13<>0,P13*0.0001/(I13*Вводные!$D$5),0) -> 7510200 | X13: =IF(OR($E13="Внешний",$F13="Ценовой"),-1000000000000000,Q13)+ROW()/1000000000 -> 95286 | Y13: =IF($F13<>"Ценовой",-1000000000000000,Q13)+ROW()/1000000000 -> -1e+15
A14: AUC_PC | B14: Средние активы на фондированного клиента | C14: у.е. | D14: 1 | E14: Частично | F14: Объёмный | G14: =INDEX(Вводные!$D$13:$D$64,MATCH($A14,Вводные!$A$13:$A$64,0)) -> 8000 | H14: =INDEX(Вводные!$E$13:$E$64,MATCH($A14,Вводные!$A$13:$A$64,0)) -> 200000 | I14: =INDEX(Вводные!$F$13:$F$64,MATCH($A14,Вводные!$A$13:$A$64,0)) -> 25000000 | J14: =INDEX(Модель!$J$91:$JA$91,MATCH("MR|"&$A14&"|1",Модель!$J$6:$JA$6,0))-INDEX(Модель!$J$91:$JA$91,MATCH("MR|"&"BASE"&"|1",Модель!$J$6:$JA$6,0)) -> 137938 | K14: =INDEX(Модель!$J$91:$JA$91,MATCH("AF|"&$A14&"|1",Модель!$J$6:$JA$6,0))-INDEX(Модель!$J$91:$JA$91,MATCH("AF|"&"BASE"&"|1",Модель!$J$6:$JA$6,0)) -> 123902 | L14: =INDEX(Модель!$J$91:$JA$91,MATCH("IC|"&$A14&"|1",Модель!$J$6:$JA$6,0))-INDEX(Модель!$J$91:$JA$91,MATCH("IC|"&"BASE"&"|1",Модель!$J$6:$JA$6,0)) -> 95475 | M14: =SUM(J14:L14) -> 357315 | N14: =INDEX(Модель!$J$91:$JA$91,MATCH("MR|"&$A14&"|3",Модель!$J$6:$JA$6,0))-INDEX(Модель!$J$91:$JA$91,MATCH("MR|"&"BASE"&"|3",Модель!$J$6:$JA$6,0)) -> 168300 | O14: =INDEX(Модель!$J$91:$JA$91,MATCH("AF|"&$A14&"|3",Модель!$J$6:$JA$6,0))-INDEX(Модель!$J$91:$JA$91,MATCH("AF|"&"BASE"&"|3",Модель!$J$6:$JA$6,0)) -> 153066.67 | P14: =INDEX(Модель!$J$91:$JA$91,MATCH("IC|"&$A14&"|3",Модель!$J$6:$JA$6,0))-INDEX(Модель!$J$91:$JA$91,MATCH("IC|"&"BASE"&"|3",Модель!$J$6:$JA$6,0)) -> 106875 | Q14: =SUM(N14:P14) -> 428241.67 | R14: =IF($Q$3<>0,Q14/$Q$3,0) -> 0.0043091105 | S14: =IF($E14="Внешний","",IF($F14="Ценовой",RANK(Y14,$Y$5:$Y$45),RANK(X14,$X$5:$X$45))) -> 5 | X14: =IF(OR($E14="Внешний",$F14="Ценовой"),-1000000000000000,Q14)+ROW()/1000000000 -> 428241.67 | Y14: =IF($F14<>"Ценовой",-1000000000000000,Q14)+ROW()/1000000000 -> -1e+15
A15: CASH | B15: Доля свободных денежных средств в активах клиентов | C15: % | D15: 1 | E15: Частично | F15: Объёмный | G15: =INDEX(Вводные!$D$13:$D$64,MATCH($A15,Вводные!$A$13:$A$64,0)) -> 0.12 | H15: =INDEX(Вводные!$E$13:$E$64,MATCH($A15,Вводные!$A$13:$A$64,0)) -> 0.08 | I15: =INDEX(Вводные!$F$13:$F$64,MATCH($A15,Вводные!$A$13:$A$64,0)) -> 0.05 | J15: =INDEX(Модель!$J$91:$JA$91,MATCH("MR|"&$A15&"|1",Модель!$J$6:$JA$6,0))-INDEX(Модель!$J$91:$JA$91,MATCH("MR|"&"BASE"&"|1",Модель!$J$6:$JA$6,0)) -> 121710 | K15: =INDEX(Модель!$J$91:$JA$91,MATCH("AF|"&$A15&"|1",Модель!$J$6:$JA$6,0))-INDEX(Модель!$J$91:$JA$91,MATCH("AF|"&"BASE"&"|1",Модель!$J$6:$JA$6,0)) -> 48352 | L15: =INDEX(Модель!$J$91:$JA$91,MATCH("IC|"&$A15&"|1",Модель!$J$6:$JA$6,0))-INDEX(Модель!$J$91:$JA$91,MATCH("IC|"&"BASE"&"|1",Модель!$J$6:$JA$6,0)) -> 50250 | M15: =SUM(J15:L15) -> 220312 | N15: =INDEX(Модель!$J$91:$JA$91,MATCH("MR|"&$A15&"|3",Модель!$J$6:$JA$6,0))-INDEX(Модель!$J$91:$JA$91,MATCH("MR|"&"BASE"&"|3",Модель!$J$6:$JA$6,0)) -> 148500 | O15: =INDEX(Модель!$J$91:$JA$91,MATCH("AF|"&$A15&"|3",Модель!$J$6:$JA$6,0))-INDEX(Модель!$J$91:$JA$91,MATCH("AF|"&"BASE"&"|3",Модель!$J$6:$JA$6,0)) -> 59733.333 | P15: =INDEX(Модель!$J$91:$JA$91,MATCH("IC|"&$A15&"|3",Модель!$J$6:$JA$6,0))-INDEX(Модель!$J$91:$JA$91,MATCH("IC|"&"BASE"&"|3",Модель!$J$6:$JA$6,0)) -> 56250 | Q15: =SUM(N15:P15) -> 264483.33 | R15: =IF($Q$3<>0,Q15/$Q$3,0) -> 0.0026613195 | S15: =IF($E15="Внешний","",IF($F15="Ценовой",RANK(Y15,$Y$5:$Y$45),RANK(X15,$X$5:$X$45))) -> 9 | T15: 1 п.п. | U15: =IF(G15<>0,J15*0.01/(G15*Вводные!$D$5),0)+IF(H15<>0,K15*0.01/(H15*Вводные!$D$5),0)+IF(I15<>0,L15*0.01/(I15*Вводные!$D$5),0) -> 2623650 | V15: =IF(G15<>0,N15*0.01/(G15*Вводные!$D$5),0)+IF(H15<>0,O15*0.01/(H15*Вводные!$D$5),0)+IF(I15<>0,P15*0.01/(I15*Вводные!$D$5),0) -> 3109166.7 | X15: =IF(OR($E15="Внешний",$F15="Ценовой"),-1000000000000000,Q15)+ROW()/1000000000 -> 264483.33 | Y15: =IF($F15<>"Ценовой",-1000000000000000,Q15)+ROW()/1000000000 -> -1e+15
A16: FLOAT_Y | B16: Доходность размещения свободных остатков клиентов | C16: % | D16: 1 | E16: Внешний | F16: Внешний | G16: =INDEX(Вводные!$D$13:$D$64,MATCH($A16,Вводные!$A$13:$A$64,0)) -> 0.05 | H16: =INDEX(Вводные!$E$13:$E$64,MATCH($A16,Вводные!$A$13:$A$64,0)) -> 0.05 | I16: =INDEX(Вводные!$F$13:$F$64,MATCH($A16,Вводные!$A$13:$A$64,0)) -> 0.05 | J16: =INDEX(Модель!$J$91:$JA$91,MATCH("MR|"&$A16&"|1",Модель!$J$6:$JA$6,0))-INDEX(Модель!$J$91:$JA$91,MATCH("MR|"&"BASE"&"|1",Модель!$J$6:$JA$6,0)) -> 243420 | K16: =INDEX(Модель!$J$91:$JA$91,MATCH("AF|"&$A16&"|1",Модель!$J$6:$JA$6,0))-INDEX(Модель!$J$91:$JA$91,MATCH("AF|"&"BASE"&"|1",Модель!$J$6:$JA$6,0)) -> 120880 | L16: =INDEX(Модель!$J$91:$JA$91,MATCH("IC|"&$A16&"|1",Модель!$J$6:$JA$6,0))-INDEX(Модель!$J$91:$JA$91,MATCH("IC|"&"BASE"&"|1",Модель!$J$6:$JA$6,0)) -> 251250 | M16: =SUM(J16:L16) -> 615550 | N16: =INDEX(Модель!$J$91:$JA$91,MATCH("MR|"&$A16&"|3",Модель!$J$6:$JA$6,0))-INDEX(Модель!$J$91:$JA$91,MATCH("MR|"&"BASE"&"|3",Модель!$J$6:$JA$6,0)) -> 297000 | O16: =INDEX(Модель!$J$91:$JA$91,MATCH("AF|"&$A16&"|3",Модель!$J$6:$JA$6,0))-INDEX(Модель!$J$91:$JA$91,MATCH("AF|"&"BASE"&"|3",Модель!$J$6:$JA$6,0)) -> 149333.33 | P16: =INDEX(Модель!$J$91:$JA$91,MATCH("IC|"&$A16&"|3",Модель!$J$6:$JA$6,0))-INDEX(Модель!$J$91:$JA$91,MATCH("IC|"&"BASE"&"|3",Модель!$J$6:$JA$6,0)) -> 281250 | Q16: =SUM(N16:P16) -> 727583.33 | R16: =IF($Q$3<>0,Q16/$Q$3,0) -> 0.0073211863 | S16: =IF($E16="Внешний","",IF($F16="Ценовой",RANK(Y16,$Y$5:$Y$45),RANK(X16,$X$5:$X$45))) | T16: 1 п.п. | U16: =IF(G16<>0,J16*0.01/(G16*Вводные!$D$5),0)+IF(H16<>0,K16*0.01/(H16*Вводные!$D$5),0)+IF(I16<>0,L16*0.01/(I16*Вводные!$D$5),0) -> 12311000 | V16: =IF(G16<>0,N16*0.01/(G16*Вводные!$D$5),0)+IF(H16<>0,O16*0.01/(H16*Вводные!$D$5),0)+IF(I16<>0,P16*0.01/(I16*Вводные!$D$5),0) -> 14551667 | W16: Внешний фактор: гипотезы на него не претендуют, используется для сценариев. | X16: =IF(OR($E16="Внешний",$F16="Ценовой"),-1000000000000000,Q16)+ROW()/1000000000 -> -1e+15 | Y16: =IF($F16<>"Ценовой",-1000000000000000,Q16)+ROW()/1000000000 -> -1e+15
A17: FLOAT_P | B17: Ставка, выплачиваемая клиентам на свободные остатки | C17: % | D17: -1 | E17: Управляемый | F17: Ценовой | G17: =INDEX(Вводные!$D$13:$D$64,MATCH($A17,Вводные!$A$13:$A$64,0)) -> 0.02 | H17: =INDEX(Вводные!$E$13:$E$64,MATCH($A17,Вводные!$A$13:$A$64,0)) -> 0.025 | I17: =INDEX(Вводные!$F$13:$F$64,MATCH($A17,Вводные!$A$13:$A$64,0)) -> 0.035 | J17: =INDEX(Модель!$J$91:$JA$91,MATCH("MR|"&$A17&"|1",Модель!$J$6:$JA$6,0))-INDEX(Модель!$J$91:$JA$91,MATCH("MR|"&"BASE"&"|1",Модель!$J$6:$JA$6,0)) -> 97368 | K17: =INDEX(Модель!$J$91:$JA$91,MATCH("AF|"&$A17&"|1",Модель!$J$6:$JA$6,0))-INDEX(Модель!$J$91:$JA$91,MATCH("AF|"&"BASE"&"|1",Модель!$J$6:$JA$6,0)) -> 60440 | L17: =INDEX(Модель!$J$91:$JA$91,MATCH("IC|"&$A17&"|1",Модель!$J$6:$JA$6,0))-INDEX(Модель!$J$91:$JA$91,MATCH("IC|"&"BASE"&"|1",Модель!$J$6:$JA$6,0)) -> 175875 | M17: =SUM(J17:L17) -> 333683 | N17: =INDEX(Модель!$J$91:$JA$91,MATCH("MR|"&$A17&"|3",Модель!$J$6:$JA$6,0))-INDEX(Модель!$J$91:$JA$91,MATCH("MR|"&"BASE"&"|3",Модель!$J$6:$JA$6,0)) -> 118800 | O17: =INDEX(Модель!$J$91:$JA$91,MATCH("AF|"&$A17&"|3",Модель!$J$6:$JA$6,0))-INDEX(Модель!$J$91:$JA$91,MATCH("AF|"&"BASE"&"|3",Модель!$J$6:$JA$6,0)) -> 74666.667 | P17: =INDEX(Модель!$J$91:$JA$91,MATCH("IC|"&$A17&"|3",Модель!$J$6:$JA$6,0))-INDEX(Модель!$J$91:$JA$91,MATCH("IC|"&"BASE"&"|3",Модель!$J$6:$JA$6,0)) -> 196875 | Q17: =SUM(N17:P17) -> 390341.67 | R17: =IF($Q$3<>0,Q17/$Q$3,0) -> 0.0039277481 | S17: =IF($E17="Внешний","",IF($F17="Ценовой",RANK(Y17,$Y$5:$Y$45),RANK(X17,$X$5:$X$45))) -> 2 | T17: 1 п.п. | U17: =IF(G17<>0,J17*0.01/(G17*Вводные!$D$5),0)+IF(H17<>0,K17*0.01/(H17*Вводные!$D$5),0)+IF(I17<>0,L17*0.01/(I17*Вводные!$D$5),0) -> 12311000 | V17: =IF(G17<>0,N17*0.01/(G17*Вводные!$D$5),0)+IF(H17<>0,O17*0.01/(H17*Вводные!$D$5),0)+IF(I17<>0,P17*0.01/(I17*Вводные!$D$5),0) -> 14551667 | W17: Ценовой рычаг: эффект при неизменных объёмах — учитывать эластичность. | X17: =IF(OR($E17="Внешний",$F17="Ценовой"),-1000000000000000,Q17)+ROW()/1000000000 -> -1e+15 | Y17: =IF($F17<>"Ценовой",-1000000000000000,Q17)+ROW()/1000000000 -> 390341.67
A18: MRG_PEN | B18: Проникновение маржинальной торговли: доля фондированных клиентов с задолженностью | C18: % | D18: 1 | E18: Управляемый | F18: Объёмный | G18: =INDEX(Вводные!$D$13:$D$64,MATCH($A18,Вводные!$A$13:$A$64,0)) -> 0.05 | H18: =INDEX(Вводные!$E$13:$E$64,MATCH($A18,Вводные!$A$13:$A$64,0)) -> 0.1 | I18: =INDEX(Вводные!$F$13:$F$64,MATCH($A18,Вводные!$A$13:$A$64,0)) -> 0.2 | J18: =INDEX(Модель!$J$91:$JA$91,MATCH("MR|"&$A18&"|1",Модель!$J$6:$JA$6,0))-INDEX(Модель!$J$91:$JA$91,MATCH("MR|"&"BASE"&"|1",Модель!$J$6:$JA$6,0)) -> 91282.5 | K18: =INDEX(Модель!$J$91:$JA$91,MATCH("AF|"&$A18&"|1",Модель!$J$6:$JA$6,0))-INDEX(Модель!$J$91:$JA$91,MATCH("AF|"&"BASE"&"|1",Модель!$J$6:$JA$6,0)) -> 63462 | L18: =INDEX(Модель!$J$91:$JA$91,MATCH("IC|"&$A18&"|1",Модель!$J$6:$JA$6,0))-INDEX(Модель!$J$91:$JA$91,MATCH("IC|"&"BASE"&"|1",Модель!$J$6:$JA$6,0)) -> 56280 | M18: =SUM(J18:L18) -> 211024.5 | N18: =INDEX(Модель!$J$91:$JA$91,MATCH("MR|"&$A18&"|3",Модель!$J$6:$JA$6,0))-INDEX(Модель!$J$91:$JA$91,MATCH("MR|"&"BASE"&"|3",Модель!$J$6:$JA$6,0)) -> 111375 | O18: =INDEX(Модель!$J$91:$JA$91,MATCH("AF|"&$A18&"|3",Модель!$J$6:$JA$6,0))-INDEX(Модель!$J$91:$JA$91,MATCH("AF|"&"BASE"&"|3",Модель!$J$6:$JA$6,0)) -> 78400 | P18: =INDEX(Модель!$J$91:$JA$91,MATCH("IC|"&$A18&"|3",Модель!$J$6:$JA$6,0))-INDEX(Модель!$J$91:$JA$91,MATCH("IC|"&"BASE"&"|3",Модель!$J$6:$JA$6,0)) -> 63000 | Q18: =SUM(N18:P18) -> 252775 | R18: =IF($Q$3<>0,Q18/$Q$3,0) -> 0.0025435064 | S18: =IF($E18="Внешний","",IF($F18="Ценовой",RANK(Y18,$Y$5:$Y$45),RANK(X18,$X$5:$X$45))) -> 11 | T18: 1 п.п. | U18: =IF(G18<>0,J18*0.01/(G18*Вводные!$D$5),0)+IF(H18<>0,K18*0.01/(H18*Вводные!$D$5),0)+IF(I18<>0,L18*0.01/(I18*Вводные!$D$5),0) -> 2741670 | V18: =IF(G18<>0,N18*0.01/(G18*Вводные!$D$5),0)+IF(H18<>0,O18*0.01/(H18*Вводные!$D$5),0)+IF(I18<>0,P18*0.01/(I18*Вводные!$D$5),0) -> 3326500 | X18: =IF(OR($E18="Внешний",$F18="Ценовой"),-1000000000000000,Q18)+ROW()/1000000000 -> 252775 | Y18: =IF($F18<>"Ценовой",-1000000000000000,Q18)+ROW()/1000000000 -> -1e+15
A19: MRG_DEBT | B19: Средняя задолженность маржинального клиента | C19: у.е. | D19: 1 | E19: Частично | F19: Объёмный | G19: =INDEX(Вводные!$D$13:$D$64,MATCH($A19,Вводные!$A$13:$A$64,0)) -> 8000 | H19: =INDEX(Вводные!$E$13:$E$64,MATCH($A19,Вводные!$A$13:$A$64,0)) -> 150000 | I19: =INDEX(Вводные!$F$13:$F$64,MATCH($A19,Вводные!$A$13:$A$64,0)) -> 5000000 | J19: =INDEX(Модель!$J$91:$JA$91,MATCH("MR|"&$A19&"|1",Модель!$J$6:$JA$6,0))-INDEX(Модель!$J$91:$JA$91,MATCH("MR|"&"BASE"&"|1",Модель!$J$6:$JA$6,0)) -> 91282.5 | K19: =INDEX(Модель!$J$91:$JA$91,MATCH("AF|"&$A19&"|1",Модель!$J$6:$JA$6,0))-INDEX(Модель!$J$91:$JA$91,MATCH("AF|"&"BASE"&"|1",Модель!$J$6:$JA$6,0)) -> 63462 | L19: =INDEX(Модель!$J$91:$JA$91,MATCH("IC|"&$A19&"|1",Модель!$J$6:$JA$6,0))-INDEX(Модель!$J$91:$JA$91,MATCH("IC|"&"BASE"&"|1",Модель!$J$6:$JA$6,0)) -> 56280 | M19: =SUM(J19:L19) -> 211024.5 | N19: =INDEX(Модель!$J$91:$JA$91,MATCH("MR|"&$A19&"|3",Модель!$J$6:$JA$6,0))-INDEX(Модель!$J$91:$JA$91,MATCH("MR|"&"BASE"&"|3",Модель!$J$6:$JA$6,0)) -> 111375 | O19: =INDEX(Модель!$J$91:$JA$91,MATCH("AF|"&$A19&"|3",Модель!$J$6:$JA$6,0))-INDEX(Модель!$J$91:$JA$91,MATCH("AF|"&"BASE"&"|3",Модель!$J$6:$JA$6,0)) -> 78400 | P19: =INDEX(Модель!$J$91:$JA$91,MATCH("IC|"&$A19&"|3",Модель!$J$6:$JA$6,0))-INDEX(Модель!$J$91:$JA$91,MATCH("IC|"&"BASE"&"|3",Модель!$J$6:$JA$6,0)) -> 63000 | Q19: =SUM(N19:P19) -> 252775 | R19: =IF($Q$3<>0,Q19/$Q$3,0) -> 0.0025435064 | S19: =IF($E19="Внешний","",IF($F19="Ценовой",RANK(Y19,$Y$5:$Y$45),RANK(X19,$X$5:$X$45))) -> 10 | X19: =IF(OR($E19="Внешний",$F19="Ценовой"),-1000000000000000,Q19)+ROW()/1000000000 -> 252775 | Y19: =IF($F19<>"Ценовой",-1000000000000000,Q19)+ROW()/1000000000 -> -1e+15
A20: MRG_RATE | B20: Ставка для клиента по маржинальному кредиту (деньги и ценные бумаги) | C20: % | D20: 1 | E20: Управляемый | F20: Ценовой | G20: =INDEX(Вводные!$D$13:$D$64,MATCH($A20,Вводные!$A$13:$A$64,0)) -> 0.12 | H20: =INDEX(Вводные!$E$13:$E$64,MATCH($A20,Вводные!$A$13:$A$64,0)) -> 0.1 | I20: =INDEX(Вводные!$F$13:$F$64,MATCH($A20,Вводные!$A$13:$A$64,0)) -> 0.08 | J20: =INDEX(Модель!$J$91:$JA$91,MATCH("MR|"&$A20&"|1",Модель!$J$6:$JA$6,0))-INDEX(Модель!$J$91:$JA$91,MATCH("MR|"&"BASE"&"|1",Модель!$J$6:$JA$6,0)) -> 243420 | K20: =INDEX(Модель!$J$91:$JA$91,MATCH("AF|"&$A20&"|1",Модель!$J$6:$JA$6,0))-INDEX(Модель!$J$91:$JA$91,MATCH("AF|"&"BASE"&"|1",Модель!$J$6:$JA$6,0)) -> 226650 | L20: =INDEX(Модель!$J$91:$JA$91,MATCH("IC|"&$A20&"|1",Модель!$J$6:$JA$6,0))-INDEX(Модель!$J$91:$JA$91,MATCH("IC|"&"BASE"&"|1",Модель!$J$6:$JA$6,0)) -> 321600 | M20: =SUM(J20:L20) -> 791670 | N20: =INDEX(Модель!$J$91:$JA$91,MATCH("MR|"&$A20&"|3",Модель!$J$6:$JA$6,0))-INDEX(Модель!$J$91:$JA$91,MATCH("MR|"&"BASE"&"|3",Модель!$J$6:$JA$6,0)) -> 297000 | O20: =INDEX(Модель!$J$91:$JA$91,MATCH("AF|"&$A20&"|3",Модель!$J$6:$JA$6,0))-INDEX(Модель!$J$91:$JA$91,MATCH("AF|"&"BASE"&"|3",Модель!$J$6:$JA$6,0)) -> 280000 | P20: =INDEX(Модель!$J$91:$JA$91,MATCH("IC|"&$A20&"|3",Модель!$J$6:$JA$6,0))-INDEX(Модель!$J$91:$JA$91,MATCH("IC|"&"BASE"&"|3",Модель!$J$6:$JA$6,0)) -> 360000 | Q20: =SUM(N20:P20) -> 937000 | R20: =IF($Q$3<>0,Q20/$Q$3,0) -> 0.0094284066 | S20: =IF($E20="Внешний","",IF($F20="Ценовой",RANK(Y20,$Y$5:$Y$45),RANK(X20,$X$5:$X$45))) -> 1 | T20: 1 п.п. | U20: =IF(G20<>0,J20*0.01/(G20*Вводные!$D$5),0)+IF(H20<>0,K20*0.01/(H20*Вводные!$D$5),0)+IF(I20<>0,L20*0.01/(I20*Вводные!$D$5),0) -> 8315000 | V20: =IF(G20<>0,N20*0.01/(G20*Вводные!$D$5),0)+IF(H20<>0,O20*0.01/(H20*Вводные!$D$5),0)+IF(I20<>0,P20*0.01/(I20*Вводные!$D$5),0) -> 9775000 | W20: Ценовой рычаг: эффект при неизменных объёмах — учитывать эластичность. | X20: =IF(OR($E20="Внешний",$F20="Ценовой"),-1000000000000000,Q20)+ROW()/1000000000 -> -1e+15 | Y20: =IF($F20<>"Ценовой",-1000000000000000,Q20)+ROW()/1000000000 -> 937000
A21: FUND_RATE | B21: Стоимость фондирования маржинального портфеля | C21: % | D21: -1 | E21: Внешний | F21: Внешний | G21: =INDEX(Вводные!$D$13:$D$64,MATCH($A21,Вводные!$A$13:$A$64,0)) -> 0.07 | H21: =INDEX(Вводные!$E$13:$E$64,MATCH($A21,Вводные!$A$13:$A$64,0)) -> 0.07 | I21: =INDEX(Вводные!$F$13:$F$64,MATCH($A21,Вводные!$A$13:$A$64,0)) -> 0.065 | J21: =INDEX(Модель!$J$91:$JA$91,MATCH("MR|"&$A21&"|1",Модель!$J$6:$JA$6,0))-INDEX(Модель!$J$91:$JA$91,MATCH("MR|"&"BASE"&"|1",Модель!$J$6:$JA$6,0)) -> 141995 | K21: =INDEX(Модель!$J$91:$JA$91,MATCH("AF|"&$A21&"|1",Модель!$J$6:$JA$6,0))-INDEX(Модель!$J$91:$JA$91,MATCH("AF|"&"BASE"&"|1",Модель!$J$6:$JA$6,0)) -> 158655 | L21: =INDEX(Модель!$J$91:$JA$91,MATCH("IC|"&$A21&"|1",Модель!$J$6:$JA$6,0))-INDEX(Модель!$J$91:$JA$91,MATCH("IC|"&"BASE"&"|1",Модель!$J$6:$JA$6,0)) -> 261300 | M21: =SUM(J21:L21) -> 561950 | N21: =INDEX(Модель!$J$91:$JA$91,MATCH("MR|"&$A21&"|3",Модель!$J$6:$JA$6,0))-INDEX(Модель!$J$91:$JA$91,MATCH("MR|"&"BASE"&"|3",Модель!$J$6:$JA$6,0)) -> 173250 | O21: =INDEX(Модель!$J$91:$JA$91,MATCH("AF|"&$A21&"|3",Модель!$J$6:$JA$6,0))-INDEX(Модель!$J$91:$JA$91,MATCH("AF|"&"BASE"&"|3",Модель!$J$6:$JA$6,0)) -> 196000 | P21: =INDEX(Модель!$J$91:$JA$91,MATCH("IC|"&$A21&"|3",Модель!$J$6:$JA$6,0))-INDEX(Модель!$J$91:$JA$91,MATCH("IC|"&"BASE"&"|3",Модель!$J$6:$JA$6,0)) -> 292500 | Q21: =SUM(N21:P21) -> 661750 | R21: =IF($Q$3<>0,Q21/$Q$3,0) -> 0.0066587493 | S21: =IF($E21="Внешний","",IF($F21="Ценовой",RANK(Y21,$Y$5:$Y$45),RANK(X21,$X$5:$X$45))) | T21: 1 п.п. | U21: =IF(G21<>0,J21*0.01/(G21*Вводные!$D$5),0)+IF(H21<>0,K21*0.01/(H21*Вводные!$D$5),0)+IF(I21<>0,L21*0.01/(I21*Вводные!$D$5),0) -> 8315000 | V21: =IF(G21<>0,N21*0.01/(G21*Вводные!$D$5),0)+IF(H21<>0,O21*0.01/(H21*Вводные!$D$5),0)+IF(I21<>0,P21*0.01/(I21*Вводные!$D$5),0) -> 9775000 | W21: Внешний фактор: гипотезы на него не претендуют, используется для сценариев. | X21: =IF(OR($E21="Внешний",$F21="Ценовой"),-1000000000000000,Q21)+ROW()/1000000000 -> -1e+15 | Y21: =IF($F21<>"Ценовой",-1000000000000000,Q21)+ROW()/1000000000 -> -1e+15
A22: CL | B22: Кредитные потери по маржинальному портфелю, % в год | C22: % | D22: -1 | E22: Частично | F22: Затратный | G22: =INDEX(Вводные!$D$13:$D$64,MATCH($A22,Вводные!$A$13:$A$64,0)) -> 0.005 | H22: =INDEX(Вводные!$E$13:$E$64,MATCH($A22,Вводные!$A$13:$A$64,0)) -> 0.002 | I22: =INDEX(Вводные!$F$13:$F$64,MATCH($A22,Вводные!$A$13:$A$64,0)) -> 0.001 | J22: =INDEX(Модель!$J$91:$JA$91,MATCH("MR|"&$A22&"|1",Модель!$J$6:$JA$6,0))-INDEX(Модель!$J$91:$JA$91,MATCH("MR|"&"BASE"&"|1",Модель!$J$6:$JA$6,0)) -> 10142.5 | K22: =INDEX(Модель!$J$91:$JA$91,MATCH("AF|"&$A22&"|1",Модель!$J$6:$JA$6,0))-INDEX(Модель!$J$91:$JA$91,MATCH("AF|"&"BASE"&"|1",Модель!$J$6:$JA$6,0)) -> 4533 | L22: =INDEX(Модель!$J$91:$JA$91,MATCH("IC|"&$A22&"|1",Модель!$J$6:$JA$6,0))-INDEX(Модель!$J$91:$JA$91,MATCH("IC|"&"BASE"&"|1",Модель!$J$6:$JA$6,0)) -> 4020 | M22: =SUM(J22:L22) -> 18695.5 | N22: =INDEX(Модель!$J$91:$JA$91,MATCH("MR|"&$A22&"|3",Модель!$J$6:$JA$6,0))-INDEX(Модель!$J$91:$JA$91,MATCH("MR|"&"BASE"&"|3",Модель!$J$6:$JA$6,0)) -> 12375 | O22: =INDEX(Модель!$J$91:$JA$91,MATCH("AF|"&$A22&"|3",Модель!$J$6:$JA$6,0))-INDEX(Модель!$J$91:$JA$91,MATCH("AF|"&"BASE"&"|3",Модель!$J$6:$JA$6,0)) -> 5600 | P22: =INDEX(Модель!$J$91:$JA$91,MATCH("IC|"&$A22&"|3",Модель!$J$6:$JA$6,0))-INDEX(Модель!$J$91:$JA$91,MATCH("IC|"&"BASE"&"|3",Модель!$J$6:$JA$6,0)) -> 4500 | Q22: =SUM(N22:P22) -> 22475 | R22: =IF($Q$3<>0,Q22/$Q$3,0) -> 0.00022615095 | S22: =IF($E22="Внешний","",IF($F22="Ценовой",RANK(Y22,$Y$5:$Y$45),RANK(X22,$X$5:$X$45))) -> 27 | T22: 0,1 п.п. | U22: =IF(G22<>0,J22*0.001/(G22*Вводные!$D$5),0)+IF(H22<>0,K22*0.001/(H22*Вводные!$D$5),0)+IF(I22<>0,L22*0.001/(I22*Вводные!$D$5),0) -> 831500 | V22: =IF(G22<>0,N22*0.001/(G22*Вводные!$D$5),0)+IF(H22<>0,O22*0.001/(H22*Вводные!$D$5),0)+IF(I22<>0,P22*0.001/(I22*Вводные!$D$5),0) -> 977500 | X22: =IF(OR($E22="Внешний",$F22="Ценовой"),-1000000000000000,Q22)+ROW()/1000000000 -> 22475 | Y22: =IF($F22<>"Ценовой",-1000000000000000,Q22)+ROW()/1000000000 -> -1e+15
A23: FX_PEN | B23: Доля фондированных клиентов, совершающих конвертации | C23: % | D23: 1 | E23: Управляемый | F23: Объёмный | G23: =INDEX(Вводные!$D$13:$D$64,MATCH($A23,Вводные!$A$13:$A$64,0)) -> 0.3 | H23: =INDEX(Вводные!$E$13:$E$64,MATCH($A23,Вводные!$A$13:$A$64,0)) -> 0.5 | I23: =INDEX(Вводные!$F$13:$F$64,MATCH($A23,Вводные!$A$13:$A$64,0)) -> 0.4 | J23: =INDEX(Модель!$J$91:$JA$91,MATCH("MR|"&$A23&"|1",Модель!$J$6:$JA$6,0))-INDEX(Модель!$J$91:$JA$91,MATCH("MR|"&"BASE"&"|1",Модель!$J$6:$JA$6,0)) -> 38034.375 | K23: =INDEX(Модель!$J$91:$JA$91,MATCH("AF|"&$A23&"|1",Модель!$J$6:$JA$6,0))-INDEX(Модель!$J$91:$JA$91,MATCH("AF|"&"BASE"&"|1",Модель!$J$6:$JA$6,0)) -> 22665 | L23: =INDEX(Модель!$J$91:$JA$91,MATCH("IC|"&$A23&"|1",Модель!$J$6:$JA$6,0))-INDEX(Модель!$J$91:$JA$91,MATCH("IC|"&"BASE"&"|1",Модель!$J$6:$JA$6,0)) -> 8040 | M23: =SUM(J23:L23) -> 68739.375 | N23: =INDEX(Модель!$J$91:$JA$91,MATCH("MR|"&$A23&"|3",Модель!$J$6:$JA$6,0))-INDEX(Модель!$J$91:$JA$91,MATCH("MR|"&"BASE"&"|3",Модель!$J$6:$JA$6,0)) -> 46406.25 | O23: =INDEX(Модель!$J$91:$JA$91,MATCH("AF|"&$A23&"|3",Модель!$J$6:$JA$6,0))-INDEX(Модель!$J$91:$JA$91,MATCH("AF|"&"BASE"&"|3",Модель!$J$6:$JA$6,0)) -> 28000 | P23: =INDEX(Модель!$J$91:$JA$91,MATCH("IC|"&$A23&"|3",Модель!$J$6:$JA$6,0))-INDEX(Модель!$J$91:$JA$91,MATCH("IC|"&"BASE"&"|3",Модель!$J$6:$JA$6,0)) -> 9000 | Q23: =SUM(N23:P23) -> 83406.25 | R23: =IF($Q$3<>0,Q23/$Q$3,0) -> 0.00083926152 | S23: =IF($E23="Внешний","",IF($F23="Ценовой",RANK(Y23,$Y$5:$Y$45),RANK(X23,$X$5:$X$45))) -> 19 | T23: 1 п.п. | U23: =IF(G23<>0,J23*0.01/(G23*Вводные!$D$5),0)+IF(H23<>0,K23*0.01/(H23*Вводные!$D$5),0)+IF(I23<>0,L23*0.01/(I23*Вводные!$D$5),0) -> 192211.25 | V23: =IF(G23<>0,N23*0.01/(G23*Вводные!$D$5),0)+IF(H23<>0,O23*0.01/(H23*Вводные!$D$5),0)+IF(I23<>0,P23*0.01/(I23*Вводные!$D$5),0) -> 233187.5 | X23: =IF(OR($E23="Внешний",$F23="Ценовой"),-1000000000000000,Q23)+ROW()/1000000000 -> 83406.25 | Y23: =IF($F23<>"Ценовой",-1000000000000000,Q23)+ROW()/1000000000 -> -1e+15
A24: FX_VOL | B24: Объём конвертаций на конвертирующего клиента в год | C24: у.е. | D24: 1 | E24: Частично | F24: Объёмный | G24: =INDEX(Вводные!$D$13:$D$64,MATCH($A24,Вводные!$A$13:$A$64,0)) -> 5000 | H24: =INDEX(Вводные!$E$13:$E$64,MATCH($A24,Вводные!$A$13:$A$64,0)) -> 100000 | I24: =INDEX(Вводные!$F$13:$F$64,MATCH($A24,Вводные!$A$13:$A$64,0)) -> 10000000 | J24: =INDEX(Модель!$J$91:$JA$91,MATCH("MR|"&$A24&"|1",Модель!$J$6:$JA$6,0))-INDEX(Модель!$J$91:$JA$91,MATCH("MR|"&"BASE"&"|1",Модель!$J$6:$JA$6,0)) -> 38034.375 | K24: =INDEX(Модель!$J$91:$JA$91,MATCH("AF|"&$A24&"|1",Модель!$J$6:$JA$6,0))-INDEX(Модель!$J$91:$JA$91,MATCH("AF|"&"BASE"&"|1",Модель!$J$6:$JA$6,0)) -> 22665 | L24: =INDEX(Модель!$J$91:$JA$91,MATCH("IC|"&$A24&"|1",Модель!$J$6:$JA$6,0))-INDEX(Модель!$J$91:$JA$91,MATCH("IC|"&"BASE"&"|1",Модель!$J$6:$JA$6,0)) -> 8040 | M24: =SUM(J24:L24) -> 68739.375 | N24: =INDEX(Модель!$J$91:$JA$91,MATCH("MR|"&$A24&"|3",Модель!$J$6:$JA$6,0))-INDEX(Модель!$J$91:$JA$91,MATCH("MR|"&"BASE"&"|3",Модель!$J$6:$JA$6,0)) -> 46406.25 | O24: =INDEX(Модель!$J$91:$JA$91,MATCH("AF|"&$A24&"|3",Модель!$J$6:$JA$6,0))-INDEX(Модель!$J$91:$JA$91,MATCH("AF|"&"BASE"&"|3",Модель!$J$6:$JA$6,0)) -> 28000 | P24: =INDEX(Модель!$J$91:$JA$91,MATCH("IC|"&$A24&"|3",Модель!$J$6:$JA$6,0))-INDEX(Модель!$J$91:$JA$91,MATCH("IC|"&"BASE"&"|3",Модель!$J$6:$JA$6,0)) -> 9000 | Q24: =SUM(N24:P24) -> 83406.25 | R24: =IF($Q$3<>0,Q24/$Q$3,0) -> 0.00083926152 | S24: =IF($E24="Внешний","",IF($F24="Ценовой",RANK(Y24,$Y$5:$Y$45),RANK(X24,$X$5:$X$45))) -> 18 | X24: =IF(OR($E24="Внешний",$F24="Ценовой"),-1000000000000000,Q24)+ROW()/1000000000 -> 83406.25 | Y24: =IF($F24<>"Ценовой",-1000000000000000,Q24)+ROW()/1000000000 -> -1e+15
A25: FX_SPREAD | B25: Комиссия и спред за конвертацию, % от объёма | C25: % | D25: 1 | E25: Управляемый | F25: Ценовой | G25: =INDEX(Вводные!$D$13:$D$64,MATCH($A25,Вводные!$A$13:$A$64,0)) -> 0.005 | H25: =INDEX(Вводные!$E$13:$E$64,MATCH($A25,Вводные!$A$13:$A$64,0)) -> 0.003 | I25: =INDEX(Вводные!$F$13:$F$64,MATCH($A25,Вводные!$A$13:$A$64,0)) -> 0.0005 | J25: =INDEX(Модель!$J$91:$JA$91,MATCH("MR|"&$A25&"|1",Модель!$J$6:$JA$6,0))-INDEX(Модель!$J$91:$JA$91,MATCH("MR|"&"BASE"&"|1",Модель!$J$6:$JA$6,0)) -> 38034.375 | K25: =INDEX(Модель!$J$91:$JA$91,MATCH("AF|"&$A25&"|1",Модель!$J$6:$JA$6,0))-INDEX(Модель!$J$91:$JA$91,MATCH("AF|"&"BASE"&"|1",Модель!$J$6:$JA$6,0)) -> 22665 | L25: =INDEX(Модель!$J$91:$JA$91,MATCH("IC|"&$A25&"|1",Модель!$J$6:$JA$6,0))-INDEX(Модель!$J$91:$JA$91,MATCH("IC|"&"BASE"&"|1",Модель!$J$6:$JA$6,0)) -> 8040 | M25: =SUM(J25:L25) -> 68739.375 | N25: =INDEX(Модель!$J$91:$JA$91,MATCH("MR|"&$A25&"|3",Модель!$J$6:$JA$6,0))-INDEX(Модель!$J$91:$JA$91,MATCH("MR|"&"BASE"&"|3",Модель!$J$6:$JA$6,0)) -> 46406.25 | O25: =INDEX(Модель!$J$91:$JA$91,MATCH("AF|"&$A25&"|3",Модель!$J$6:$JA$6,0))-INDEX(Модель!$J$91:$JA$91,MATCH("AF|"&"BASE"&"|3",Модель!$J$6:$JA$6,0)) -> 28000 | P25: =INDEX(Модель!$J$91:$JA$91,MATCH("IC|"&$A25&"|3",Модель!$J$6:$JA$6,0))-INDEX(Модель!$J$91:$JA$91,MATCH("IC|"&"BASE"&"|3",Модель!$J$6:$JA$6,0)) -> 9000 | Q25: =SUM(N25:P25) -> 83406.25 | R25: =IF($Q$3<>0,Q25/$Q$3,0) -> 0.00083926152 | S25: =IF($E25="Внешний","",IF($F25="Ценовой",RANK(Y25,$Y$5:$Y$45),RANK(X25,$X$5:$X$45))) -> 6 | T25: 1 б.п. | U25: =IF(G25<>0,J25*0.0001/(G25*Вводные!$D$5),0)+IF(H25<>0,K25*0.0001/(H25*Вводные!$D$5),0)+IF(I25<>0,L25*0.0001/(I25*Вводные!$D$5),0) -> 312418.75 | V25: =IF(G25<>0,N25*0.0001/(G25*Вводные!$D$5),0)+IF(H25<>0,O25*0.0001/(H25*Вводные!$D$5),0)+IF(I25<>0,P25*0.0001/(I25*Вводные!$D$5),0) -> 366145.83 | W25: Ценовой рычаг: эффект при неизменных объёмах — учитывать эластичность. | X25: =IF(OR($E25="Внешний",$F25="Ценовой"),-1000000000000000,Q25)+ROW()/1000000000 -> -1e+15 | Y25: =IF($F25<>"Ценовой",-1000000000000000,Q25)+ROW()/1000000000 -> 83406.25
A26: PRD_PEN | B26: Доля фондированных клиентов, купивших размещения или продукты за год (ИК — доля клиентов-эмитентов, проведших размещение) | C26: % | D26: 1 | E26: Управляемый | F26: Объёмный | G26: =INDEX(Вводные!$D$13:$D$64,MATCH($A26,Вводные!$A$13:$A$64,0)) -> 0.08 | H26: =INDEX(Вводные!$E$13:$E$64,MATCH($A26,Вводные!$A$13:$A$64,0)) -> 0.35 | I26: =INDEX(Вводные!$F$13:$F$64,MATCH($A26,Вводные!$A$13:$A$64,0)) -> 0.05 | J26: =INDEX(Модель!$J$91:$JA$91,MATCH("MR|"&$A26&"|1",Модель!$J$6:$JA$6,0))-INDEX(Модель!$J$91:$JA$91,MATCH("MR|"&"BASE"&"|1",Модель!$J$6:$JA$6,0)) -> 12171 | K26: =INDEX(Модель!$J$91:$JA$91,MATCH("AF|"&$A26&"|1",Модель!$J$6:$JA$6,0))-INDEX(Модель!$J$91:$JA$91,MATCH("AF|"&"BASE"&"|1",Модель!$J$6:$JA$6,0)) -> 50769.6 | L26: =INDEX(Модель!$J$91:$JA$91,MATCH("IC|"&$A26&"|1",Модель!$J$6:$JA$6,0))-INDEX(Модель!$J$91:$JA$91,MATCH("IC|"&"BASE"&"|1",Модель!$J$6:$JA$6,0)) -> 100500 | M26: =SUM(J26:L26) -> 163440.6 | N26: =INDEX(Модель!$J$91:$JA$91,MATCH("MR|"&$A26&"|3",Модель!$J$6:$JA$6,0))-INDEX(Модель!$J$91:$JA$91,MATCH("MR|"&"BASE"&"|3",Модель!$J$6:$JA$6,0)) -> 14850 | O26: =INDEX(Модель!$J$91:$JA$91,MATCH("AF|"&$A26&"|3",Модель!$J$6:$JA$6,0))-INDEX(Модель!$J$91:$JA$91,MATCH("AF|"&"BASE"&"|3",Модель!$J$6:$JA$6,0)) -> 62720 | P26: =INDEX(Модель!$J$91:$JA$91,MATCH("IC|"&$A26&"|3",Модель!$J$6:$JA$6,0))-INDEX(Модель!$J$91:$JA$91,MATCH("IC|"&"BASE"&"|3",Модель!$J$6:$JA$6,0)) -> 112500 | Q26: =SUM(N26:P26) -> 190070 | R26: =IF($Q$3<>0,Q26/$Q$3,0) -> 0.0019125478 | S26: =IF($E26="Внешний","",IF($F26="Ценовой",RANK(Y26,$Y$5:$Y$45),RANK(X26,$X$5:$X$45))) -> 13 | T26: 1 п.п. | U26: =IF(G26<>0,J26*0.01/(G26*Вводные!$D$5),0)+IF(H26<>0,K26*0.01/(H26*Вводные!$D$5),0)+IF(I26<>0,L26*0.01/(I26*Вводные!$D$5),0) -> 2307193.5 | V26: =IF(G26<>0,N26*0.01/(G26*Вводные!$D$5),0)+IF(H26<>0,O26*0.01/(H26*Вводные!$D$5),0)+IF(I26<>0,P26*0.01/(I26*Вводные!$D$5),0) -> 2614825 | X26: =IF(OR($E26="Внешний",$F26="Ценовой"),-1000000000000000,Q26)+ROW()/1000000000 -> 190070 | Y26: =IF($F26<>"Ценовой",-1000000000000000,Q26)+ROW()/1000000000 -> -1e+15
A27: PRD_VOL | B27: Средний объём покупок продуктов на клиента в год (ИК — средний объём размещения) | C27: у.е. | D27: 1 | E27: Частично | F27: Объёмный | G27: =INDEX(Вводные!$D$13:$D$64,MATCH($A27,Вводные!$A$13:$A$64,0)) -> 3000 | H27: =INDEX(Вводные!$E$13:$E$64,MATCH($A27,Вводные!$A$13:$A$64,0)) -> 80000 | I27: =INDEX(Вводные!$F$13:$F$64,MATCH($A27,Вводные!$A$13:$A$64,0)) -> 50000000 | J27: =INDEX(Модель!$J$91:$JA$91,MATCH("MR|"&$A27&"|1",Модель!$J$6:$JA$6,0))-INDEX(Модель!$J$91:$JA$91,MATCH("MR|"&"BASE"&"|1",Модель!$J$6:$JA$6,0)) -> 12171 | K27: =INDEX(Модель!$J$91:$JA$91,MATCH("AF|"&$A27&"|1",Модель!$J$6:$JA$6,0))-INDEX(Модель!$J$91:$JA$91,MATCH("AF|"&"BASE"&"|1",Модель!$J$6:$JA$6,0)) -> 50769.6 | L27: =INDEX(Модель!$J$91:$JA$91,MATCH("IC|"&$A27&"|1",Модель!$J$6:$JA$6,0))-INDEX(Модель!$J$91:$JA$91,MATCH("IC|"&"BASE"&"|1",Модель!$J$6:$JA$6,0)) -> 100500 | M27: =SUM(J27:L27) -> 163440.6 | N27: =INDEX(Модель!$J$91:$JA$91,MATCH("MR|"&$A27&"|3",Модель!$J$6:$JA$6,0))-INDEX(Модель!$J$91:$JA$91,MATCH("MR|"&"BASE"&"|3",Модель!$J$6:$JA$6,0)) -> 14850 | O27: =INDEX(Модель!$J$91:$JA$91,MATCH("AF|"&$A27&"|3",Модель!$J$6:$JA$6,0))-INDEX(Модель!$J$91:$JA$91,MATCH("AF|"&"BASE"&"|3",Модель!$J$6:$JA$6,0)) -> 62720 | P27: =INDEX(Модель!$J$91:$JA$91,MATCH("IC|"&$A27&"|3",Модель!$J$6:$JA$6,0))-INDEX(Модель!$J$91:$JA$91,MATCH("IC|"&"BASE"&"|3",Модель!$J$6:$JA$6,0)) -> 112500 | Q27: =SUM(N27:P27) -> 190070 | R27: =IF($Q$3<>0,Q27/$Q$3,0) -> 0.0019125478 | S27: =IF($E27="Внешний","",IF($F27="Ценовой",RANK(Y27,$Y$5:$Y$45),RANK(X27,$X$5:$X$45))) -> 12 | X27: =IF(OR($E27="Внешний",$F27="Ценовой"),-1000000000000000,Q27)+ROW()/1000000000 -> 190070 | Y27: =IF($F27<>"Ценовой",-1000000000000000,Q27)+ROW()/1000000000 -> -1e+15
A28: PRD_FEE | B28: Средняя комиссия или маржа по продуктам и размещениям, % от объёма | C28: % | D28: 1 | E28: Управляемый | F28: Ценовой | G28: =INDEX(Вводные!$D$13:$D$64,MATCH($A28,Вводные!$A$13:$A$64,0)) -> 0.01 | H28: =INDEX(Вводные!$E$13:$E$64,MATCH($A28,Вводные!$A$13:$A$64,0)) -> 0.012 | I28: =INDEX(Вводные!$F$13:$F$64,MATCH($A28,Вводные!$A$13:$A$64,0)) -> 0.01 | J28: =INDEX(Модель!$J$91:$JA$91,MATCH("MR|"&$A28&"|1",Модель!$J$6:$JA$6,0))-INDEX(Модель!$J$91:$JA$91,MATCH("MR|"&"BASE"&"|1",Модель!$J$6:$JA$6,0)) -> 12171 | K28: =INDEX(Модель!$J$91:$JA$91,MATCH("AF|"&$A28&"|1",Модель!$J$6:$JA$6,0))-INDEX(Модель!$J$91:$JA$91,MATCH("AF|"&"BASE"&"|1",Модель!$J$6:$JA$6,0)) -> 50769.6 | L28: =INDEX(Модель!$J$91:$JA$91,MATCH("IC|"&$A28&"|1",Модель!$J$6:$JA$6,0))-INDEX(Модель!$J$91:$JA$91,MATCH("IC|"&"BASE"&"|1",Модель!$J$6:$JA$6,0)) -> 100500 | M28: =SUM(J28:L28) -> 163440.6 | N28: =INDEX(Модель!$J$91:$JA$91,MATCH("MR|"&$A28&"|3",Модель!$J$6:$JA$6,0))-INDEX(Модель!$J$91:$JA$91,MATCH("MR|"&"BASE"&"|3",Модель!$J$6:$JA$6,0)) -> 14850 | O28: =INDEX(Модель!$J$91:$JA$91,MATCH("AF|"&$A28&"|3",Модель!$J$6:$JA$6,0))-INDEX(Модель!$J$91:$JA$91,MATCH("AF|"&"BASE"&"|3",Модель!$J$6:$JA$6,0)) -> 62720 | P28: =INDEX(Модель!$J$91:$JA$91,MATCH("IC|"&$A28&"|3",Модель!$J$6:$JA$6,0))-INDEX(Модель!$J$91:$JA$91,MATCH("IC|"&"BASE"&"|3",Модель!$J$6:$JA$6,0)) -> 112500 | Q28: =SUM(N28:P28) -> 190070 | R28: =IF($Q$3<>0,Q28/$Q$3,0) -> 0.0019125478 | S28: =IF($E28="Внешний","",IF($F28="Ценовой",RANK(Y28,$Y$5:$Y$45),RANK(X28,$X$5:$X$45))) -> 4 | T28: 10 б.п. | U28: =IF(G28<>0,J28*0.001/(G28*Вводные!$D$5),0)+IF(H28<>0,K28*0.001/(H28*Вводные!$D$5),0)+IF(I28<>0,L28*0.001/(I28*Вводные!$D$5),0) -> 1549790 | V28: =IF(G28<>0,N28*0.001/(G28*Вводные!$D$5),0)+IF(H28<>0,O28*0.001/(H28*Вводные!$D$5),0)+IF(I28<>0,P28*0.001/(I28*Вводные!$D$5),0) -> 1796166.7 | W28: Ценовой рычаг: эффект при неизменных объёмах — учитывать эластичность. | X28: =IF(OR($E28="Внешний",$F28="Ценовой"),-1000000000000000,Q28)+ROW()/1000000000 -> -1e+15 | Y28: =IF($F28<>"Ценовой",-1000000000000000,Q28)+ROW()/1000000000 -> 190070
A29: AM_SHARE | B29: Доля активов клиентов в ДУ, модельных портфелях и на консультировании | C29: % | D29: 1 | E29: Управляемый | F29: Объёмный | G29: =INDEX(Вводные!$D$13:$D$64,MATCH($A29,Вводные!$A$13:$A$64,0)) -> 0.02 | H29: =INDEX(Вводные!$E$13:$E$64,MATCH($A29,Вводные!$A$13:$A$64,0)) -> 0.2 | I29: =INDEX(Вводные!$F$13:$F$64,MATCH($A29,Вводные!$A$13:$A$64,0)) -> 0.05 | J29: =INDEX(Модель!$J$91:$JA$91,MATCH("MR|"&$A29&"|1",Модель!$J$6:$JA$6,0))-INDEX(Модель!$J$91:$JA$91,MATCH("MR|"&"BASE"&"|1",Модель!$J$6:$JA$6,0)) -> 8114 | K29: =INDEX(Модель!$J$91:$JA$91,MATCH("AF|"&$A29&"|1",Модель!$J$6:$JA$6,0))-INDEX(Модель!$J$91:$JA$91,MATCH("AF|"&"BASE"&"|1",Модель!$J$6:$JA$6,0)) -> 60440 | L29: =INDEX(Модель!$J$91:$JA$91,MATCH("IC|"&$A29&"|1",Модель!$J$6:$JA$6,0))-INDEX(Модель!$J$91:$JA$91,MATCH("IC|"&"BASE"&"|1",Модель!$J$6:$JA$6,0)) -> 15075 | M29: =SUM(J29:L29) -> 83629 | N29: =INDEX(Модель!$J$91:$JA$91,MATCH("MR|"&$A29&"|3",Модель!$J$6:$JA$6,0))-INDEX(Модель!$J$91:$JA$91,MATCH("MR|"&"BASE"&"|3",Модель!$J$6:$JA$6,0)) -> 9900 | O29: =INDEX(Модель!$J$91:$JA$91,MATCH("AF|"&$A29&"|3",Модель!$J$6:$JA$6,0))-INDEX(Модель!$J$91:$JA$91,MATCH("AF|"&"BASE"&"|3",Модель!$J$6:$JA$6,0)) -> 74666.667 | P29: =INDEX(Модель!$J$91:$JA$91,MATCH("IC|"&$A29&"|3",Модель!$J$6:$JA$6,0))-INDEX(Модель!$J$91:$JA$91,MATCH("IC|"&"BASE"&"|3",Модель!$J$6:$JA$6,0)) -> 16875 | Q29: =SUM(N29:P29) -> 101441.67 | R29: =IF($Q$3<>0,Q29/$Q$3,0) -> 0.0010207399 | S29: =IF($E29="Внешний","",IF($F29="Ценовой",RANK(Y29,$Y$5:$Y$45),RANK(X29,$X$5:$X$45))) -> 16 | T29: 1 п.п. | U29: =IF(G29<>0,J29*0.01/(G29*Вводные!$D$5),0)+IF(H29<>0,K29*0.01/(H29*Вводные!$D$5),0)+IF(I29<>0,L29*0.01/(I29*Вводные!$D$5),0) -> 1009400 | V29: =IF(G29<>0,N29*0.01/(G29*Вводные!$D$5),0)+IF(H29<>0,O29*0.01/(H29*Вводные!$D$5),0)+IF(I29<>0,P29*0.01/(I29*Вводные!$D$5),0) -> 1205833.3 | X29: =IF(OR($E29="Внешний",$F29="Ценовой"),-1000000000000000,Q29)+ROW()/1000000000 -> 101441.67 | Y29: =IF($F29<>"Ценовой",-1000000000000000,Q29)+ROW()/1000000000 -> -1e+15
A30: AM_FEE | B30: Комиссия за управление и консультирование, % годовых (вкл. success fee) | C30: % | D30: 1 | E30: Управляемый | F30: Ценовой | G30: =INDEX(Вводные!$D$13:$D$64,MATCH($A30,Вводные!$A$13:$A$64,0)) -> 0.01 | H30: =INDEX(Вводные!$E$13:$E$64,MATCH($A30,Вводные!$A$13:$A$64,0)) -> 0.01 | I30: =INDEX(Вводные!$F$13:$F$64,MATCH($A30,Вводные!$A$13:$A$64,0)) -> 0.003 | J30: =INDEX(Модель!$J$91:$JA$91,MATCH("MR|"&$A30&"|1",Модель!$J$6:$JA$6,0))-INDEX(Модель!$J$91:$JA$91,MATCH("MR|"&"BASE"&"|1",Модель!$J$6:$JA$6,0)) -> 8114 | K30: =INDEX(Модель!$J$91:$JA$91,MATCH("AF|"&$A30&"|1",Модель!$J$6:$JA$6,0))-INDEX(Модель!$J$91:$JA$91,MATCH("AF|"&"BASE"&"|1",Модель!$J$6:$JA$6,0)) -> 60440 | L30: =INDEX(Модель!$J$91:$JA$91,MATCH("IC|"&$A30&"|1",Модель!$J$6:$JA$6,0))-INDEX(Модель!$J$91:$JA$91,MATCH("IC|"&"BASE"&"|1",Модель!$J$6:$JA$6,0)) -> 15075 | M30: =SUM(J30:L30) -> 83629 | N30: =INDEX(Модель!$J$91:$JA$91,MATCH("MR|"&$A30&"|3",Модель!$J$6:$JA$6,0))-INDEX(Модель!$J$91:$JA$91,MATCH("MR|"&"BASE"&"|3",Модель!$J$6:$JA$6,0)) -> 9900 | O30: =INDEX(Модель!$J$91:$JA$91,MATCH("AF|"&$A30&"|3",Модель!$J$6:$JA$6,0))-INDEX(Модель!$J$91:$JA$91,MATCH("AF|"&"BASE"&"|3",Модель!$J$6:$JA$6,0)) -> 74666.667 | P30: =INDEX(Модель!$J$91:$JA$91,MATCH("IC|"&$A30&"|3",Модель!$J$6:$JA$6,0))-INDEX(Модель!$J$91:$JA$91,MATCH("IC|"&"BASE"&"|3",Модель!$J$6:$JA$6,0)) -> 16875 | Q30: =SUM(N30:P30) -> 101441.67 | R30: =IF($Q$3<>0,Q30/$Q$3,0) -> 0.0010207399 | S30: =IF($E30="Внешний","",IF($F30="Ценовой",RANK(Y30,$Y$5:$Y$45),RANK(X30,$X$5:$X$45))) -> 5 | T30: 10 б.п. | U30: =IF(G30<>0,J30*0.001/(G30*Вводные!$D$5),0)+IF(H30<>0,K30*0.001/(H30*Вводные!$D$5),0)+IF(I30<>0,L30*0.001/(I30*Вводные!$D$5),0) -> 1188040 | V30: =IF(G30<>0,N30*0.001/(G30*Вводные!$D$5),0)+IF(H30<>0,O30*0.001/(H30*Вводные!$D$5),0)+IF(I30<>0,P30*0.001/(I30*Вводные!$D$5),0) -> 1408166.7 | W30: Ценовой рычаг: эффект при неизменных объёмах — учитывать эластичность. | X30: =IF(OR($E30="Внешний",$F30="Ценовой"),-1000000000000000,Q30)+ROW()/1000000000 -> -1e+15 | Y30: =IF($F30<>"Ценовой",-1000000000000000,Q30)+ROW()/1000000000 -> 101441.67
A31: SUB_PEN | B31: Доля фондированных клиентов с платной подпиской или премиальным тарифом | C31: % | D31: 1 | E31: Управляемый | F31: Объёмный | G31: =INDEX(Вводные!$D$13:$D$64,MATCH($A31,Вводные!$A$13:$A$64,0)) -> 0.08 | H31: =INDEX(Вводные!$E$13:$E$64,MATCH($A31,Вводные!$A$13:$A$64,0)) -> 0.15 | I31: =INDEX(Вводные!$F$13:$F$64,MATCH($A31,Вводные!$A$13:$A$64,0)) -> 0 | J31: =INDEX(Модель!$J$91:$JA$91,MATCH("MR|"&$A31&"|1",Модель!$J$6:$JA$6,0))-INDEX(Модель!$J$91:$JA$91,MATCH("MR|"&"BASE"&"|1",Модель!$J$6:$JA$6,0)) -> 24342 | K31: =INDEX(Модель!$J$91:$JA$91,MATCH("AF|"&$A31&"|1",Модель!$J$6:$JA$6,0))-INDEX(Модель!$J$91:$JA$91,MATCH("AF|"&"BASE"&"|1",Модель!$J$6:$JA$6,0)) -> 22665 | L31: =INDEX(Модель!$J$91:$JA$91,MATCH("IC|"&$A31&"|1",Модель!$J$6:$JA$6,0))-INDEX(Модель!$J$91:$JA$91,MATCH("IC|"&"BASE"&"|1",Модель!$J$6:$JA$6,0)) -> 0 | M31: =SUM(J31:L31) -> 47007 | N31: =INDEX(Модель!$J$91:$JA$91,MATCH("MR|"&$A31&"|3",Модель!$J$6:$JA$6,0))-INDEX(Модель!$J$91:$JA$91,MATCH("MR|"&"BASE"&"|3",Модель!$J$6:$JA$6,0)) -> 29700 | O31: =INDEX(Модель!$J$91:$JA$91,MATCH("AF|"&$A31&"|3",Модель!$J$6:$JA$6,0))-INDEX(Модель!$J$91:$JA$91,MATCH("AF|"&"BASE"&"|3",Модель!$J$6:$JA$6,0)) -> 28000 | P31: =INDEX(Модель!$J$91:$JA$91,MATCH("IC|"&$A31&"|3",Модель!$J$6:$JA$6,0))-INDEX(Модель!$J$91:$JA$91,MATCH("IC|"&"BASE"&"|3",Модель!$J$6:$JA$6,0)) -> 0 | Q31: =SUM(N31:P31) -> 57700 | R31: =IF($Q$3<>0,Q31/$Q$3,0) -> 0.00058059665 | S31: =IF($E31="Внешний","",IF($F31="Ценовой",RANK(Y31,$Y$5:$Y$45),RANK(X31,$X$5:$X$45))) -> 21 | T31: 1 п.п. | U31: =IF(G31<>0,J31*0.01/(G31*Вводные!$D$5),0)+IF(H31<>0,K31*0.01/(H31*Вводные!$D$5),0)+IF(I31<>0,L31*0.01/(I31*Вводные!$D$5),0) -> 455375 | V31: =IF(G31<>0,N31*0.01/(G31*Вводные!$D$5),0)+IF(H31<>0,O31*0.01/(H31*Вводные!$D$5),0)+IF(I31<>0,P31*0.01/(I31*Вводные!$D$5),0) -> 557916.67 | X31: =IF(OR($E31="Внешний",$F31="Ценовой"),-1000000000000000,Q31)+ROW()/1000000000 -> 57700 | Y31: =IF($F31<>"Ценовой",-1000000000000000,Q31)+ROW()/1000000000 -> -1e+15
A32: SUB_PRICE | B32: Стоимость подписки или премиального обслуживания в год | C32: у.е. | D32: 1 | E32: Управляемый | F32: Ценовой | G32: =INDEX(Вводные!$D$13:$D$64,MATCH($A32,Вводные!$A$13:$A$64,0)) -> 60 | H32: =INDEX(Вводные!$E$13:$E$64,MATCH($A32,Вводные!$A$13:$A$64,0)) -> 1000 | I32: =INDEX(Вводные!$F$13:$F$64,MATCH($A32,Вводные!$A$13:$A$64,0)) -> 0 | J32: =INDEX(Модель!$J$91:$JA$91,MATCH("MR|"&$A32&"|1",Модель!$J$6:$JA$6,0))-INDEX(Модель!$J$91:$JA$91,MATCH("MR|"&"BASE"&"|1",Модель!$J$6:$JA$6,0)) -> 24342 | K32: =INDEX(Модель!$J$91:$JA$91,MATCH("AF|"&$A32&"|1",Модель!$J$6:$JA$6,0))-INDEX(Модель!$J$91:$JA$91,MATCH("AF|"&"BASE"&"|1",Модель!$J$6:$JA$6,0)) -> 22665 | L32: =INDEX(Модель!$J$91:$JA$91,MATCH("IC|"&$A32&"|1",Модель!$J$6:$JA$6,0))-INDEX(Модель!$J$91:$JA$91,MATCH("IC|"&"BASE"&"|1",Модель!$J$6:$JA$6,0)) -> 0 | M32: =SUM(J32:L32) -> 47007 | N32: =INDEX(Модель!$J$91:$JA$91,MATCH("MR|"&$A32&"|3",Модель!$J$6:$JA$6,0))-INDEX(Модель!$J$91:$JA$91,MATCH("MR|"&"BASE"&"|3",Модель!$J$6:$JA$6,0)) -> 29700 | O32: =INDEX(Модель!$J$91:$JA$91,MATCH("AF|"&$A32&"|3",Модель!$J$6:$JA$6,0))-INDEX(Модель!$J$91:$JA$91,MATCH("AF|"&"BASE"&"|3",Модель!$J$6:$JA$6,0)) -> 28000 | P32: =INDEX(Модель!$J$91:$JA$91,MATCH("IC|"&$A32&"|3",Модель!$J$6:$JA$6,0))-INDEX(Модель!$J$91:$JA$91,MATCH("IC|"&"BASE"&"|3",Модель!$J$6:$JA$6,0)) -> 0 | Q32: =SUM(N32:P32) -> 57700 | R32: =IF($Q$3<>0,Q32/$Q$3,0) -> 0.00058059665 | S32: =IF($E32="Внешний","",IF($F32="Ценовой",RANK(Y32,$Y$5:$Y$45),RANK(X32,$X$5:$X$45))) -> 8 | W32: Ценовой рычаг: эффект при неизменных объёмах — учитывать эластичность. | X32: =IF(OR($E32="Внешний",$F32="Ценовой"),-1000000000000000,Q32)+ROW()/1000000000 -> -1e+15 | Y32: =IF($F32<>"Ценовой",-1000000000000000,Q32)+ROW()/1000000000 -> 57700
A33: CUST_FEE | B33: Депозитарная и кастодиальная комиссия, % от активов в год | C33: % | D33: 1 | E33: Управляемый | F33: Ценовой | G33: =INDEX(Вводные!$D$13:$D$64,MATCH($A33,Вводные!$A$13:$A$64,0)) -> 0.0002 | H33: =INDEX(Вводные!$E$13:$E$64,MATCH($A33,Вводные!$A$13:$A$64,0)) -> 0.0005 | I33: =INDEX(Вводные!$F$13:$F$64,MATCH($A33,Вводные!$A$13:$A$64,0)) -> 0.0003 | J33: =INDEX(Модель!$J$91:$JA$91,MATCH("MR|"&$A33&"|1",Модель!$J$6:$JA$6,0))-INDEX(Модель!$J$91:$JA$91,MATCH("MR|"&"BASE"&"|1",Модель!$J$6:$JA$6,0)) -> 8114 | K33: =INDEX(Модель!$J$91:$JA$91,MATCH("AF|"&$A33&"|1",Модель!$J$6:$JA$6,0))-INDEX(Модель!$J$91:$JA$91,MATCH("AF|"&"BASE"&"|1",Модель!$J$6:$JA$6,0)) -> 15110 | L33: =INDEX(Модель!$J$91:$JA$91,MATCH("IC|"&$A33&"|1",Модель!$J$6:$JA$6,0))-INDEX(Модель!$J$91:$JA$91,MATCH("IC|"&"BASE"&"|1",Модель!$J$6:$JA$6,0)) -> 30150 | M33: =SUM(J33:L33) -> 53374 | N33: =INDEX(Модель!$J$91:$JA$91,MATCH("MR|"&$A33&"|3",Модель!$J$6:$JA$6,0))-INDEX(Модель!$J$91:$JA$91,MATCH("MR|"&"BASE"&"|3",Модель!$J$6:$JA$6,0)) -> 9900 | O33: =INDEX(Модель!$J$91:$JA$91,MATCH("AF|"&$A33&"|3",Модель!$J$6:$JA$6,0))-INDEX(Модель!$J$91:$JA$91,MATCH("AF|"&"BASE"&"|3",Модель!$J$6:$JA$6,0)) -> 18666.667 | P33: =INDEX(Модель!$J$91:$JA$91,MATCH("IC|"&$A33&"|3",Модель!$J$6:$JA$6,0))-INDEX(Модель!$J$91:$JA$91,MATCH("IC|"&"BASE"&"|3",Модель!$J$6:$JA$6,0)) -> 33750 | Q33: =SUM(N33:P33) -> 62316.667 | R33: =IF($Q$3<>0,Q33/$Q$3,0) -> 0.00062705109 | S33: =IF($E33="Внешний","",IF($F33="Ценовой",RANK(Y33,$Y$5:$Y$45),RANK(X33,$X$5:$X$45))) -> 7 | T33: 1 б.п. | U33: =IF(G33<>0,J33*0.0001/(G33*Вводные!$D$5),0)+IF(H33<>0,K33*0.0001/(H33*Вводные!$D$5),0)+IF(I33<>0,L33*0.0001/(I33*Вводные!$D$5),0) -> 1712900 | V33: =IF(G33<>0,N33*0.0001/(G33*Вводные!$D$5),0)+IF(H33<>0,O33*0.0001/(H33*Вводные!$D$5),0)+IF(I33<>0,P33*0.0001/(I33*Вводные!$D$5),0) -> 1993333.3 | W33: Ценовой рычаг: эффект при неизменных объёмах — учитывать эластичность. | X33: =IF(OR($E33="Внешний",$F33="Ценовой"),-1000000000000000,Q33)+ROW()/1000000000 -> -1e+15 | Y33: =IF($F33<>"Ценовой",-1000000000000000,Q33)+ROW()/1000000000 -> 62316.667
A34: SUP_RATE | B34: Обращений в поддержку на фондированного клиента в год | C34: шт./клиент | D34: -1 | E34: Управляемый | F34: Затратный | G34: =INDEX(Вводные!$D$13:$D$64,MATCH($A34,Вводные!$A$13:$A$64,0)) -> 1 | H34: =INDEX(Вводные!$E$13:$E$64,MATCH($A34,Вводные!$A$13:$A$64,0)) -> 3 | I34: =INDEX(Вводные!$F$13:$F$64,MATCH($A34,Вводные!$A$13:$A$64,0)) -> 12 | J34: =INDEX(Модель!$J$91:$JA$91,MATCH("MR|"&$A34&"|1",Модель!$J$6:$JA$6,0))-INDEX(Модель!$J$91:$JA$91,MATCH("MR|"&"BASE"&"|1",Модель!$J$6:$JA$6,0)) -> 25356.25 | K34: =INDEX(Модель!$J$91:$JA$91,MATCH("AF|"&$A34&"|1",Модель!$J$6:$JA$6,0))-INDEX(Модель!$J$91:$JA$91,MATCH("AF|"&"BASE"&"|1",Модель!$J$6:$JA$6,0)) -> 6799.5 | L34: =INDEX(Модель!$J$91:$JA$91,MATCH("IC|"&$A34&"|1",Модель!$J$6:$JA$6,0))-INDEX(Модель!$J$91:$JA$91,MATCH("IC|"&"BASE"&"|1",Модель!$J$6:$JA$6,0)) -> 1447.2 | M34: =SUM(J34:L34) -> 33602.95 | N34: =INDEX(Модель!$J$91:$JA$91,MATCH("MR|"&$A34&"|3",Модель!$J$6:$JA$6,0))-INDEX(Модель!$J$91:$JA$91,MATCH("MR|"&"BASE"&"|3",Модель!$J$6:$JA$6,0)) -> 30937.5 | O34: =INDEX(Модель!$J$91:$JA$91,MATCH("AF|"&$A34&"|3",Модель!$J$6:$JA$6,0))-INDEX(Модель!$J$91:$JA$91,MATCH("AF|"&"BASE"&"|3",Модель!$J$6:$JA$6,0)) -> 8400 | P34: =INDEX(Модель!$J$91:$JA$91,MATCH("IC|"&$A34&"|3",Модель!$J$6:$JA$6,0))-INDEX(Модель!$J$91:$JA$91,MATCH("IC|"&"BASE"&"|3",Модель!$J$6:$JA$6,0)) -> 1620 | Q34: =SUM(N34:P34) -> 40957.5 | R34: =IF($Q$3<>0,Q34/$Q$3,0) -> 0.00041212803 | S34: =IF($E34="Внешний","",IF($F34="Ценовой",RANK(Y34,$Y$5:$Y$45),RANK(X34,$X$5:$X$45))) -> 23 | X34: =IF(OR($E34="Внешний",$F34="Ценовой"),-1000000000000000,Q34)+ROW()/1000000000 -> 40957.5 | Y34: =IF($F34<>"Ценовой",-1000000000000000,Q34)+ROW()/1000000000 -> -1e+15
A35: SUP_COST | B35: Стоимость обработки одного обращения | C35: у.е. | D35: -1 | E35: Управляемый | F35: Затратный | G35: =INDEX(Вводные!$D$13:$D$64,MATCH($A35,Вводные!$A$13:$A$64,0)) -> 5 | H35: =INDEX(Вводные!$E$13:$E$64,MATCH($A35,Вводные!$A$13:$A$64,0)) -> 15 | I35: =INDEX(Вводные!$F$13:$F$64,MATCH($A35,Вводные!$A$13:$A$64,0)) -> 30 | J35: =INDEX(Модель!$J$91:$JA$91,MATCH("MR|"&$A35&"|1",Модель!$J$6:$JA$6,0))-INDEX(Модель!$J$91:$JA$91,MATCH("MR|"&"BASE"&"|1",Модель!$J$6:$JA$6,0)) -> 25356.25 | K35: =INDEX(Модель!$J$91:$JA$91,MATCH("AF|"&$A35&"|1",Модель!$J$6:$JA$6,0))-INDEX(Модель!$J$91:$JA$91,MATCH("AF|"&"BASE"&"|1",Модель!$J$6:$JA$6,0)) -> 6799.5 | L35: =INDEX(Модель!$J$91:$JA$91,MATCH("IC|"&$A35&"|1",Модель!$J$6:$JA$6,0))-INDEX(Модель!$J$91:$JA$91,MATCH("IC|"&"BASE"&"|1",Модель!$J$6:$JA$6,0)) -> 1447.2 | M35: =SUM(J35:L35) -> 33602.95 | N35: =INDEX(Модель!$J$91:$JA$91,MATCH("MR|"&$A35&"|3",Модель!$J$6:$JA$6,0))-INDEX(Модель!$J$91:$JA$91,MATCH("MR|"&"BASE"&"|3",Модель!$J$6:$JA$6,0)) -> 30937.5 | O35: =INDEX(Модель!$J$91:$JA$91,MATCH("AF|"&$A35&"|3",Модель!$J$6:$JA$6,0))-INDEX(Модель!$J$91:$JA$91,MATCH("AF|"&"BASE"&"|3",Модель!$J$6:$JA$6,0)) -> 8400 | P35: =INDEX(Модель!$J$91:$JA$91,MATCH("IC|"&$A35&"|3",Модель!$J$6:$JA$6,0))-INDEX(Модель!$J$91:$JA$91,MATCH("IC|"&"BASE"&"|3",Модель!$J$6:$JA$6,0)) -> 1620 | Q35: =SUM(N35:P35) -> 40957.5 | R35: =IF($Q$3<>0,Q35/$Q$3,0) -> 0.00041212803 | S35: =IF($E35="Внешний","",IF($F35="Ценовой",RANK(Y35,$Y$5:$Y$45),RANK(X35,$X$5:$X$45))) -> 22 | X35: =IF(OR($E35="Внешний",$F35="Ценовой"),-1000000000000000,Q35)+ROW()/1000000000 -> 40957.5 | Y35: =IF($F35<>"Ценовой",-1000000000000000,Q35)+ROW()/1000000000 -> -1e+15
A36: KYC_UNIT | B36: Стоимость автоматической проверки заявки (KYC/AML-сервисы, документы) | C36: у.е. | D36: -1 | E36: Управляемый | F36: Затратный | G36: =INDEX(Вводные!$D$13:$D$64,MATCH($A36,Вводные!$A$13:$A$64,0)) -> 1.5 | H36: =INDEX(Вводные!$E$13:$E$64,MATCH($A36,Вводные!$A$13:$A$64,0)) -> 3 | I36: =INDEX(Вводные!$F$13:$F$64,MATCH($A36,Вводные!$A$13:$A$64,0)) -> 50 | J36: =INDEX(Модель!$J$91:$JA$91,MATCH("MR|"&$A36&"|1",Модель!$J$6:$JA$6,0))-INDEX(Модель!$J$91:$JA$91,MATCH("MR|"&"BASE"&"|1",Модель!$J$6:$JA$6,0)) -> 4500 | K36: =INDEX(Модель!$J$91:$JA$91,MATCH("AF|"&$A36&"|1",Модель!$J$6:$JA$6,0))-INDEX(Модель!$J$91:$JA$91,MATCH("AF|"&"BASE"&"|1",Модель!$J$6:$JA$6,0)) -> 60 | L36: =INDEX(Модель!$J$91:$JA$91,MATCH("IC|"&$A36&"|1",Модель!$J$6:$JA$6,0))-INDEX(Модель!$J$91:$JA$91,MATCH("IC|"&"BASE"&"|1",Модель!$J$6:$JA$6,0)) -> 60 | M36: =SUM(J36:L36) -> 4620 | N36: =INDEX(Модель!$J$91:$JA$91,MATCH("MR|"&$A36&"|3",Модель!$J$6:$JA$6,0))-INDEX(Модель!$J$91:$JA$91,MATCH("MR|"&"BASE"&"|3",Модель!$J$6:$JA$6,0)) -> 4500 | O36: =INDEX(Модель!$J$91:$JA$91,MATCH("AF|"&$A36&"|3",Модель!$J$6:$JA$6,0))-INDEX(Модель!$J$91:$JA$91,MATCH("AF|"&"BASE"&"|3",Модель!$J$6:$JA$6,0)) -> 60 | P36: =INDEX(Модель!$J$91:$JA$91,MATCH("IC|"&$A36&"|3",Модель!$J$6:$JA$6,0))-INDEX(Модель!$J$91:$JA$91,MATCH("IC|"&"BASE"&"|3",Модель!$J$6:$JA$6,0)) -> 60 | Q36: =SUM(N36:P36) -> 4620 | R36: =IF($Q$3<>0,Q36/$Q$3,0) -> 4.6487981e-05 | S36: =IF($E36="Внешний","",IF($F36="Ценовой",RANK(Y36,$Y$5:$Y$45),RANK(X36,$X$5:$X$45))) -> 31 | X36: =IF(OR($E36="Внешний",$F36="Ценовой"),-1000000000000000,Q36)+ROW()/1000000000 -> 4620 | Y36: =IF($F36<>"Ценовой",-1000000000000000,Q36)+ROW()/1000000000 -> -1e+15
A37: KYC_MAN | B37: Доля заявок, требующих ручной проверки | C37: % | D37: -1 | E37: Управляемый | F37: Затратный | G37: =INDEX(Вводные!$D$13:$D$64,MATCH($A37,Вводные!$A$13:$A$64,0)) -> 0.3 | H37: =INDEX(Вводные!$E$13:$E$64,MATCH($A37,Вводные!$A$13:$A$64,0)) -> 0.6 | I37: =INDEX(Вводные!$F$13:$F$64,MATCH($A37,Вводные!$A$13:$A$64,0)) -> 1 | J37: =INDEX(Модель!$J$91:$JA$91,MATCH("MR|"&$A37&"|1",Модель!$J$6:$JA$6,0))-INDEX(Модель!$J$91:$JA$91,MATCH("MR|"&"BASE"&"|1",Модель!$J$6:$JA$6,0)) -> 7200 | K37: =INDEX(Модель!$J$91:$JA$91,MATCH("AF|"&$A37&"|1",Модель!$J$6:$JA$6,0))-INDEX(Модель!$J$91:$JA$91,MATCH("AF|"&"BASE"&"|1",Модель!$J$6:$JA$6,0)) -> 480 | L37: =INDEX(Модель!$J$91:$JA$91,MATCH("IC|"&$A37&"|1",Модель!$J$6:$JA$6,0))-INDEX(Модель!$J$91:$JA$91,MATCH("IC|"&"BASE"&"|1",Модель!$J$6:$JA$6,0)) -> 1800 | M37: =SUM(J37:L37) -> 9480 | N37: =INDEX(Модель!$J$91:$JA$91,MATCH("MR|"&$A37&"|3",Модель!$J$6:$JA$6,0))-INDEX(Модель!$J$91:$JA$91,MATCH("MR|"&"BASE"&"|3",Модель!$J$6:$JA$6,0)) -> 7200 | O37: =INDEX(Модель!$J$91:$JA$91,MATCH("AF|"&$A37&"|3",Модель!$J$6:$JA$6,0))-INDEX(Модель!$J$91:$JA$91,MATCH("AF|"&"BASE"&"|3",Модель!$J$6:$JA$6,0)) -> 480 | P37: =INDEX(Модель!$J$91:$JA$91,MATCH("IC|"&$A37&"|3",Модель!$J$6:$JA$6,0))-INDEX(Модель!$J$91:$JA$91,MATCH("IC|"&"BASE"&"|3",Модель!$J$6:$JA$6,0)) -> 1800 | Q37: =SUM(N37:P37) -> 9480 | R37: =IF($Q$3<>0,Q37/$Q$3,0) -> 9.5390923e-05 | S37: =IF($E37="Внешний","",IF($F37="Ценовой",RANK(Y37,$Y$5:$Y$45),RANK(X37,$X$5:$X$45))) -> 29 | T37: 1 п.п. | U37: =IF(G37<>0,J37*0.01/(G37*Вводные!$D$5),0)+IF(H37<>0,K37*0.01/(H37*Вводные!$D$5),0)+IF(I37<>0,L37*0.01/(I37*Вводные!$D$5),0) -> 26600 | V37: =IF(G37<>0,N37*0.01/(G37*Вводные!$D$5),0)+IF(H37<>0,O37*0.01/(H37*Вводные!$D$5),0)+IF(I37<>0,P37*0.01/(I37*Вводные!$D$5),0) -> 26600 | X37: =IF(OR($E37="Внешний",$F37="Ценовой"),-1000000000000000,Q37)+ROW()/1000000000 -> 9480 | Y37: =IF($F37<>"Ценовой",-1000000000000000,Q37)+ROW()/1000000000 -> -1e+15
A38: KYC_MAN_COST | B38: Стоимость ручной проверки заявки | C38: у.е. | D38: -1 | E38: Управляемый | F38: Затратный | G38: =INDEX(Вводные!$D$13:$D$64,MATCH($A38,Вводные!$A$13:$A$64,0)) -> 8 | H38: =INDEX(Вводные!$E$13:$E$64,MATCH($A38,Вводные!$A$13:$A$64,0)) -> 40 | I38: =INDEX(Вводные!$F$13:$F$64,MATCH($A38,Вводные!$A$13:$A$64,0)) -> 1500 | J38: =INDEX(Модель!$J$91:$JA$91,MATCH("MR|"&$A38&"|1",Модель!$J$6:$JA$6,0))-INDEX(Модель!$J$91:$JA$91,MATCH("MR|"&"BASE"&"|1",Модель!$J$6:$JA$6,0)) -> 7200 | K38: =INDEX(Модель!$J$91:$JA$91,MATCH("AF|"&$A38&"|1",Модель!$J$6:$JA$6,0))-INDEX(Модель!$J$91:$JA$91,MATCH("AF|"&"BASE"&"|1",Модель!$J$6:$JA$6,0)) -> 480 | L38: =INDEX(Модель!$J$91:$JA$91,MATCH("IC|"&$A38&"|1",Модель!$J$6:$JA$6,0))-INDEX(Модель!$J$91:$JA$91,MATCH("IC|"&"BASE"&"|1",Модель!$J$6:$JA$6,0)) -> 1800 | M38: =SUM(J38:L38) -> 9480 | N38: =INDEX(Модель!$J$91:$JA$91,MATCH("MR|"&$A38&"|3",Модель!$J$6:$JA$6,0))-INDEX(Модель!$J$91:$JA$91,MATCH("MR|"&"BASE"&"|3",Модель!$J$6:$JA$6,0)) -> 7200 | O38: =INDEX(Модель!$J$91:$JA$91,MATCH("AF|"&$A38&"|3",Модель!$J$6:$JA$6,0))-INDEX(Модель!$J$91:$JA$91,MATCH("AF|"&"BASE"&"|3",Модель!$J$6:$JA$6,0)) -> 480 | P38: =INDEX(Модель!$J$91:$JA$91,MATCH("IC|"&$A38&"|3",Модель!$J$6:$JA$6,0))-INDEX(Модель!$J$91:$JA$91,MATCH("IC|"&"BASE"&"|3",Модель!$J$6:$JA$6,0)) -> 1800 | Q38: =SUM(N38:P38) -> 9480 | R38: =IF($Q$3<>0,Q38/$Q$3,0) -> 9.5390923e-05 | S38: =IF($E38="Внешний","",IF($F38="Ценовой",RANK(Y38,$Y$5:$Y$45),RANK(X38,$X$5:$X$45))) -> 28 | X38: =IF(OR($E38="Внешний",$F38="Ценовой"),-1000000000000000,Q38)+ROW()/1000000000 -> 9480 | Y38: =IF($F38<>"Ценовой",-1000000000000000,Q38)+ROW()/1000000000 -> -1e+15
A39: OPS_PC | B39: Операций бэк-офиса на фондированного клиента в год (вводы/выводы, переводы ЦБ, корп. действия, заявления) | C39: шт./клиент | D39: -1 | E39: Частично | F39: Затратный | G39: =INDEX(Вводные!$D$13:$D$64,MATCH($A39,Вводные!$A$13:$A$64,0)) -> 6 | H39: =INDEX(Вводные!$E$13:$E$64,MATCH($A39,Вводные!$A$13:$A$64,0)) -> 15 | I39: =INDEX(Вводные!$F$13:$F$64,MATCH($A39,Вводные!$A$13:$A$64,0)) -> 200 | J39: =INDEX(Модель!$J$91:$JA$91,MATCH("MR|"&$A39&"|1",Модель!$J$6:$JA$6,0))-INDEX(Модель!$J$91:$JA$91,MATCH("MR|"&"BASE"&"|1",Модель!$J$6:$JA$6,0)) -> 9128.25 | K39: =INDEX(Модель!$J$91:$JA$91,MATCH("AF|"&$A39&"|1",Модель!$J$6:$JA$6,0))-INDEX(Модель!$J$91:$JA$91,MATCH("AF|"&"BASE"&"|1",Модель!$J$6:$JA$6,0)) -> 5666.25 | L39: =INDEX(Модель!$J$91:$JA$91,MATCH("IC|"&$A39&"|1",Модель!$J$6:$JA$6,0))-INDEX(Модель!$J$91:$JA$91,MATCH("IC|"&"BASE"&"|1",Модель!$J$6:$JA$6,0)) -> 6030 | M39: =SUM(J39:L39) -> 20824.5 | N39: =INDEX(Модель!$J$91:$JA$91,MATCH("MR|"&$A39&"|3",Модель!$J$6:$JA$6,0))-INDEX(Модель!$J$91:$JA$91,MATCH("MR|"&"BASE"&"|3",Модель!$J$6:$JA$6,0)) -> 11137.5 | O39: =INDEX(Модель!$J$91:$JA$91,MATCH("AF|"&$A39&"|3",Модель!$J$6:$JA$6,0))-INDEX(Модель!$J$91:$JA$91,MATCH("AF|"&"BASE"&"|3",Модель!$J$6:$JA$6,0)) -> 7000 | P39: =INDEX(Модель!$J$91:$JA$91,MATCH("IC|"&$A39&"|3",Модель!$J$6:$JA$6,0))-INDEX(Модель!$J$91:$JA$91,MATCH("IC|"&"BASE"&"|3",Модель!$J$6:$JA$6,0)) -> 6750 | Q39: =SUM(N39:P39) -> 24887.5 | R39: =IF($Q$3<>0,Q39/$Q$3,0) -> 0.00025042633 | S39: =IF($E39="Внешний","",IF($F39="Ценовой",RANK(Y39,$Y$5:$Y$45),RANK(X39,$X$5:$X$45))) -> 26 | X39: =IF(OR($E39="Внешний",$F39="Ценовой"),-1000000000000000,Q39)+ROW()/1000000000 -> 24887.5 | Y39: =IF($F39<>"Ценовой",-1000000000000000,Q39)+ROW()/1000000000 -> -1e+15
A40: OPS_MAN | B40: Доля операций с ручной обработкой (не STP) | C40: % | D40: -1 | E40: Управляемый | F40: Затратный | G40: =INDEX(Вводные!$D$13:$D$64,MATCH($A40,Вводные!$A$13:$A$64,0)) -> 0.1 | H40: =INDEX(Вводные!$E$13:$E$64,MATCH($A40,Вводные!$A$13:$A$64,0)) -> 0.25 | I40: =INDEX(Вводные!$F$13:$F$64,MATCH($A40,Вводные!$A$13:$A$64,0)) -> 0.3 | J40: =INDEX(Модель!$J$91:$JA$91,MATCH("MR|"&$A40&"|1",Модель!$J$6:$JA$6,0))-INDEX(Модель!$J$91:$JA$91,MATCH("MR|"&"BASE"&"|1",Модель!$J$6:$JA$6,0)) -> 9128.25 | K40: =INDEX(Модель!$J$91:$JA$91,MATCH("AF|"&$A40&"|1",Модель!$J$6:$JA$6,0))-INDEX(Модель!$J$91:$JA$91,MATCH("AF|"&"BASE"&"|1",Модель!$J$6:$JA$6,0)) -> 5666.25 | L40: =INDEX(Модель!$J$91:$JA$91,MATCH("IC|"&$A40&"|1",Модель!$J$6:$JA$6,0))-INDEX(Модель!$J$91:$JA$91,MATCH("IC|"&"BASE"&"|1",Модель!$J$6:$JA$6,0)) -> 6030 | M40: =SUM(J40:L40) -> 20824.5 | N40: =INDEX(Модель!$J$91:$JA$91,MATCH("MR|"&$A40&"|3",Модель!$J$6:$JA$6,0))-INDEX(Модель!$J$91:$JA$91,MATCH("MR|"&"BASE"&"|3",Модель!$J$6:$JA$6,0)) -> 11137.5 | O40: =INDEX(Модель!$J$91:$JA$91,MATCH("AF|"&$A40&"|3",Модель!$J$6:$JA$6,0))-INDEX(Модель!$J$91:$JA$91,MATCH("AF|"&"BASE"&"|3",Модель!$J$6:$JA$6,0)) -> 7000 | P40: =INDEX(Модель!$J$91:$JA$91,MATCH("IC|"&$A40&"|3",Модель!$J$6:$JA$6,0))-INDEX(Модель!$J$91:$JA$91,MATCH("IC|"&"BASE"&"|3",Модель!$J$6:$JA$6,0)) -> 6750 | Q40: =SUM(N40:P40) -> 24887.5 | R40: =IF($Q$3<>0,Q40/$Q$3,0) -> 0.00025042633 | S40: =IF($E40="Внешний","",IF($F40="Ценовой",RANK(Y40,$Y$5:$Y$45),RANK(X40,$X$5:$X$45))) -> 25 | T40: 1 п.п. | U40: =IF(G40<>0,J40*0.01/(G40*Вводные!$D$5),0)+IF(H40<>0,K40*0.01/(H40*Вводные!$D$5),0)+IF(I40<>0,L40*0.01/(I40*Вводные!$D$5),0) -> 134047.5 | V40: =IF(G40<>0,N40*0.01/(G40*Вводные!$D$5),0)+IF(H40<>0,O40*0.01/(H40*Вводные!$D$5),0)+IF(I40<>0,P40*0.01/(I40*Вводные!$D$5),0) -> 161875 | X40: =IF(OR($E40="Внешний",$F40="Ценовой"),-1000000000000000,Q40)+ROW()/1000000000 -> 24887.5 | Y40: =IF($F40<>"Ценовой",-1000000000000000,Q40)+ROW()/1000000000 -> -1e+15
A41: OPS_COST | B41: Стоимость ручной обработки одной операции | C41: у.е. | D41: -1 | E41: Управляемый | F41: Затратный | G41: =INDEX(Вводные!$D$13:$D$64,MATCH($A41,Вводные!$A$13:$A$64,0)) -> 3 | H41: =INDEX(Вводные!$E$13:$E$64,MATCH($A41,Вводные!$A$13:$A$64,0)) -> 10 | I41: =INDEX(Вводные!$F$13:$F$64,MATCH($A41,Вводные!$A$13:$A$64,0)) -> 25 | J41: =INDEX(Модель!$J$91:$JA$91,MATCH("MR|"&$A41&"|1",Модель!$J$6:$JA$6,0))-INDEX(Модель!$J$91:$JA$91,MATCH("MR|"&"BASE"&"|1",Модель!$J$6:$JA$6,0)) -> 9128.25 | K41: =INDEX(Модель!$J$91:$JA$91,MATCH("AF|"&$A41&"|1",Модель!$J$6:$JA$6,0))-INDEX(Модель!$J$91:$JA$91,MATCH("AF|"&"BASE"&"|1",Модель!$J$6:$JA$6,0)) -> 5666.25 | L41: =INDEX(Модель!$J$91:$JA$91,MATCH("IC|"&$A41&"|1",Модель!$J$6:$JA$6,0))-INDEX(Модель!$J$91:$JA$91,MATCH("IC|"&"BASE"&"|1",Модель!$J$6:$JA$6,0)) -> 6030 | M41: =SUM(J41:L41) -> 20824.5 | N41: =INDEX(Модель!$J$91:$JA$91,MATCH("MR|"&$A41&"|3",Модель!$J$6:$JA$6,0))-INDEX(Модель!$J$91:$JA$91,MATCH("MR|"&"BASE"&"|3",Модель!$J$6:$JA$6,0)) -> 11137.5 | O41: =INDEX(Модель!$J$91:$JA$91,MATCH("AF|"&$A41&"|3",Модель!$J$6:$JA$6,0))-INDEX(Модель!$J$91:$JA$91,MATCH("AF|"&"BASE"&"|3",Модель!$J$6:$JA$6,0)) -> 7000 | P41: =INDEX(Модель!$J$91:$JA$91,MATCH("IC|"&$A41&"|3",Модель!$J$6:$JA$6,0))-INDEX(Модель!$J$91:$JA$91,MATCH("IC|"&"BASE"&"|3",Модель!$J$6:$JA$6,0)) -> 6750 | Q41: =SUM(N41:P41) -> 24887.5 | R41: =IF($Q$3<>0,Q41/$Q$3,0) -> 0.00025042633 | S41: =IF($E41="Внешний","",IF($F41="Ценовой",RANK(Y41,$Y$5:$Y$45),RANK(X41,$X$5:$X$45))) -> 24 | X41: =IF(OR($E41="Внешний",$F41="Ценовой"),-1000000000000000,Q41)+ROW()/1000000000 -> 24887.5 | Y41: =IF($F41<>"Ценовой",-1000000000000000,Q41)+ROW()/1000000000 -> -1e+15
A42: RM_LOAD | B42: Клиентов на одного персонального менеджера / сотрудника покрытия (0 — модели нет) | C42: чел. | D42: 1 | E42: Управляемый | F42: Затратный | G42: =INDEX(Вводные!$D$13:$D$64,MATCH($A42,Вводные!$A$13:$A$64,0)) -> 0 | H42: =INDEX(Вводные!$E$13:$E$64,MATCH($A42,Вводные!$A$13:$A$64,0)) -> 150 | I42: =INDEX(Вводные!$F$13:$F$64,MATCH($A42,Вводные!$A$13:$A$64,0)) -> 15 | J42: =INDEX(Модель!$J$91:$JA$91,MATCH("MR|"&$A42&"|1",Модель!$J$6:$JA$6,0))-INDEX(Модель!$J$91:$JA$91,MATCH("MR|"&"BASE"&"|1",Модель!$J$6:$JA$6,0)) -> 0 | K42: =INDEX(Модель!$J$91:$JA$91,MATCH("AF|"&$A42&"|1",Модель!$J$6:$JA$6,0))-INDEX(Модель!$J$91:$JA$91,MATCH("AF|"&"BASE"&"|1",Модель!$J$6:$JA$6,0)) -> 59841.584 | L42: =INDEX(Модель!$J$91:$JA$91,MATCH("IC|"&$A42&"|1",Модель!$J$6:$JA$6,0))-INDEX(Модель!$J$91:$JA$91,MATCH("IC|"&"BASE"&"|1",Модель!$J$6:$JA$6,0)) -> 39801.98 | M42: =SUM(J42:L42) -> 99643.564 | N42: =INDEX(Модель!$J$91:$JA$91,MATCH("MR|"&$A42&"|3",Модель!$J$6:$JA$6,0))-INDEX(Модель!$J$91:$JA$91,MATCH("MR|"&"BASE"&"|3",Модель!$J$6:$JA$6,0)) -> 0 | O42: =INDEX(Модель!$J$91:$JA$91,MATCH("AF|"&$A42&"|3",Модель!$J$6:$JA$6,0))-INDEX(Модель!$J$91:$JA$91,MATCH("AF|"&"BASE"&"|3",Модель!$J$6:$JA$6,0)) -> 73927.393 | P42: =INDEX(Модель!$J$91:$JA$91,MATCH("IC|"&$A42&"|3",Модель!$J$6:$JA$6,0))-INDEX(Модель!$J$91:$JA$91,MATCH("IC|"&"BASE"&"|3",Модель!$J$6:$JA$6,0)) -> 44554.455 | Q42: =SUM(N42:P42) -> 118481.85 | R42: =IF($Q$3<>0,Q42/$Q$3,0) -> 0.0011922039 | S42: =IF($E42="Внешний","",IF($F42="Ценовой",RANK(Y42,$Y$5:$Y$45),RANK(X42,$X$5:$X$45))) -> 15 | W42: Эффект обратно пропорционален нагрузке — линейность приблизительная. | X42: =IF(OR($E42="Внешний",$F42="Ценовой"),-1000000000000000,Q42)+ROW()/1000000000 -> 118481.85 | Y42: =IF($F42<>"Ценовой",-1000000000000000,Q42)+ROW()/1000000000 -> -1e+15
A43: RM_COST | B43: Полная годовая стоимость менеджера (ФОТ, налоги, бонусы, рабочее место) | C43: у.е. | D43: -1 | E43: Частично | F43: Затратный | G43: =INDEX(Вводные!$D$13:$D$64,MATCH($A43,Вводные!$A$13:$A$64,0)) -> 0 | H43: =INDEX(Вводные!$E$13:$E$64,MATCH($A43,Вводные!$A$13:$A$64,0)) -> 60000 | I43: =INDEX(Вводные!$F$13:$F$64,MATCH($A43,Вводные!$A$13:$A$64,0)) -> 150000 | J43: =INDEX(Модель!$J$91:$JA$91,MATCH("MR|"&$A43&"|1",Модель!$J$6:$JA$6,0))-INDEX(Модель!$J$91:$JA$91,MATCH("MR|"&"BASE"&"|1",Модель!$J$6:$JA$6,0)) -> 0 | K43: =INDEX(Модель!$J$91:$JA$91,MATCH("AF|"&$A43&"|1",Модель!$J$6:$JA$6,0))-INDEX(Модель!$J$91:$JA$91,MATCH("AF|"&"BASE"&"|1",Модель!$J$6:$JA$6,0)) -> 60440 | L43: =INDEX(Модель!$J$91:$JA$91,MATCH("IC|"&$A43&"|1",Модель!$J$6:$JA$6,0))-INDEX(Модель!$J$91:$JA$91,MATCH("IC|"&"BASE"&"|1",Модель!$J$6:$JA$6,0)) -> 40200 | M43: =SUM(J43:L43) -> 100640 | N43: =INDEX(Модель!$J$91:$JA$91,MATCH("MR|"&$A43&"|3",Модель!$J$6:$JA$6,0))-INDEX(Модель!$J$91:$JA$91,MATCH("MR|"&"BASE"&"|3",Модель!$J$6:$JA$6,0)) -> 0 | O43: =INDEX(Модель!$J$91:$JA$91,MATCH("AF|"&$A43&"|3",Модель!$J$6:$JA$6,0))-INDEX(Модель!$J$91:$JA$91,MATCH("AF|"&"BASE"&"|3",Модель!$J$6:$JA$6,0)) -> 74666.667 | P43: =INDEX(Модель!$J$91:$JA$91,MATCH("IC|"&$A43&"|3",Модель!$J$6:$JA$6,0))-INDEX(Модель!$J$91:$JA$91,MATCH("IC|"&"BASE"&"|3",Модель!$J$6:$JA$6,0)) -> 45000 | Q43: =SUM(N43:P43) -> 119666.67 | R43: =IF($Q$3<>0,Q43/$Q$3,0) -> 0.0012041259 | S43: =IF($E43="Внешний","",IF($F43="Ценовой",RANK(Y43,$Y$5:$Y$45),RANK(X43,$X$5:$X$45))) -> 14 | X43: =IF(OR($E43="Внешний",$F43="Ценовой"),-1000000000000000,Q43)+ROW()/1000000000 -> 119666.67 | Y43: =IF($F43<>"Ценовой",-1000000000000000,Q43)+ROW()/1000000000 -> -1e+15
A44: CAC | B44: Затраты на привлечение одного фондированного клиента (маркетинг, агентские, бонусы) | C44: у.е. | D44: -1 | E44: Управляемый | F44: Затратный | G44: =INDEX(Вводные!$D$13:$D$64,MATCH($A44,Вводные!$A$13:$A$64,0)) -> 80 | H44: =INDEX(Вводные!$E$13:$E$64,MATCH($A44,Вводные!$A$13:$A$64,0)) -> 1500 | I44: =INDEX(Вводные!$F$13:$F$64,MATCH($A44,Вводные!$A$13:$A$64,0)) -> 15000 | J44: =INDEX(Модель!$J$91:$JA$91,MATCH("MR|"&$A44&"|1",Модель!$J$6:$JA$6,0))-INDEX(Модель!$J$91:$JA$91,MATCH("MR|"&"BASE"&"|1",Модель!$J$6:$JA$6,0)) -> 59400 | K44: =INDEX(Модель!$J$91:$JA$91,MATCH("AF|"&$A44&"|1",Модель!$J$6:$JA$6,0))-INDEX(Модель!$J$91:$JA$91,MATCH("AF|"&"BASE"&"|1",Модель!$J$6:$JA$6,0)) -> 16800 | L44: =INDEX(Модель!$J$91:$JA$91,MATCH("IC|"&$A44&"|1",Модель!$J$6:$JA$6,0))-INDEX(Модель!$J$91:$JA$91,MATCH("IC|"&"BASE"&"|1",Модель!$J$6:$JA$6,0)) -> 5400 | M44: =SUM(J44:L44) -> 81600 | N44: =INDEX(Модель!$J$91:$JA$91,MATCH("MR|"&$A44&"|3",Модель!$J$6:$JA$6,0))-INDEX(Модель!$J$91:$JA$91,MATCH("MR|"&"BASE"&"|3",Модель!$J$6:$JA$6,0)) -> 59400 | O44: =INDEX(Модель!$J$91:$JA$91,MATCH("AF|"&$A44&"|3",Модель!$J$6:$JA$6,0))-INDEX(Модель!$J$91:$JA$91,MATCH("AF|"&"BASE"&"|3",Модель!$J$6:$JA$6,0)) -> 16800 | P44: =INDEX(Модель!$J$91:$JA$91,MATCH("IC|"&$A44&"|3",Модель!$J$6:$JA$6,0))-INDEX(Модель!$J$91:$JA$91,MATCH("IC|"&"BASE"&"|3",Модель!$J$6:$JA$6,0)) -> 5400 | Q44: =SUM(N44:P44) -> 81600 | R44: =IF($Q$3<>0,Q44/$Q$3,0) -> 0.00082108643 | S44: =IF($E44="Внешний","",IF($F44="Ценовой",RANK(Y44,$Y$5:$Y$45),RANK(X44,$X$5:$X$45))) -> 20 | X44: =IF(OR($E44="Внешний",$F44="Ценовой"),-1000000000000000,Q44)+ROW()/1000000000 -> 81600 | Y44: =IF($F44<>"Ценовой",-1000000000000000,Q44)+ROW()/1000000000 -> -1e+15
A45: OPLOSS | B45: Операционные потери за период: ошибки, компенсации клиентам, штрафы | C45: у.е. | D45: -1 | E45: Управляемый | F45: Затратный | G45: =INDEX(Вводные!$D$13:$D$64,MATCH($A45,Вводные!$A$13:$A$64,0)) -> 300000 | H45: =INDEX(Вводные!$E$13:$E$64,MATCH($A45,Вводные!$A$13:$A$64,0)) -> 100000 | I45: =INDEX(Вводные!$F$13:$F$64,MATCH($A45,Вводные!$A$13:$A$64,0)) -> 200000 | J45: =INDEX(Модель!$J$91:$JA$91,MATCH("MR|"&$A45&"|1",Модель!$J$6:$JA$6,0))-INDEX(Модель!$J$91:$JA$91,MATCH("MR|"&"BASE"&"|1",Модель!$J$6:$JA$6,0)) -> 3000 | K45: =INDEX(Модель!$J$91:$JA$91,MATCH("AF|"&$A45&"|1",Модель!$J$6:$JA$6,0))-INDEX(Модель!$J$91:$JA$91,MATCH("AF|"&"BASE"&"|1",Модель!$J$6:$JA$6,0)) -> 1000 | L45: =INDEX(Модель!$J$91:$JA$91,MATCH("IC|"&$A45&"|1",Модель!$J$6:$JA$6,0))-INDEX(Модель!$J$91:$JA$91,MATCH("IC|"&"BASE"&"|1",Модель!$J$6:$JA$6,0)) -> 2000 | M45: =SUM(J45:L45) -> 6000 | N45: =INDEX(Модель!$J$91:$JA$91,MATCH("MR|"&$A45&"|3",Модель!$J$6:$JA$6,0))-INDEX(Модель!$J$91:$JA$91,MATCH("MR|"&"BASE"&"|3",Модель!$J$6:$JA$6,0)) -> 3000 | O45: =INDEX(Модель!$J$91:$JA$91,MATCH("AF|"&$A45&"|3",Модель!$J$6:$JA$6,0))-INDEX(Модель!$J$91:$JA$91,MATCH("AF|"&"BASE"&"|3",Модель!$J$6:$JA$6,0)) -> 1000 | P45: =INDEX(Модель!$J$91:$JA$91,MATCH("IC|"&$A45&"|3",Модель!$J$6:$JA$6,0))-INDEX(Модель!$J$91:$JA$91,MATCH("IC|"&"BASE"&"|3",Модель!$J$6:$JA$6,0)) -> 2000 | Q45: =SUM(N45:P45) -> 6000 | R45: =IF($Q$3<>0,Q45/$Q$3,0) -> 6.0374002e-05 | S45: =IF($E45="Внешний","",IF($F45="Ценовой",RANK(Y45,$Y$5:$Y$45),RANK(X45,$X$5:$X$45))) -> 30 | X45: =IF(OR($E45="Внешний",$F45="Ценовой"),-1000000000000000,Q45)+ROW()/1000000000 -> 6000 | Y45: =IF($F45<>"Ценовой",-1000000000000000,Q45)+ROW()/1000000000 -> -1e+15

Sheet Модель
A1: Расчётная модель маржинального дохода
A2: Колонки E–H — расчёт в режиме HORIZON с листа «Вводные». Справа (сгруппированы, раскрываются кнопкой «+») — технические сценарии чувствительности: база и по одному улучшенному драйверу на сегмент, в горизонтах «год 1» и «долгосрочно».
A3: Сегмент | E3: MR | F3: AF | G3: IC | J3: MR | K3: MR | L3: MR | M3: MR | N3: MR | O3: MR | P3: MR | Q3: MR | R3: MR | S3: MR | T3: MR | U3: MR | V3: MR | W3: MR | X3: MR | Y3: MR | Z3: MR | AA3: MR | AB3: MR | AC3: MR | AD3: MR | AE3: MR | AF3: MR | AG3: MR | AH3: MR | AI3: MR | AJ3: MR | AK3: MR | AL3: MR | AM3: MR | AN3: MR | AO3: MR | AP3: MR | AQ3: MR | AR3: MR | AS3: MR | AT3: MR | AU3: MR | AV3: MR | AW3: MR | AX3: MR | AY3: MR | AZ3: AF | BA3: AF | BB3: AF | BC3: AF | BD3: AF | BE3: AF | BF3: AF | BG3: AF | BH3: AF | BI3: AF | BJ3: AF | BK3: AF | BL3: AF | BM3: AF | BN3: AF | BO3: AF | BP3: AF | BQ3: AF | BR3: AF | BS3: AF | BT3: AF | BU3: AF | BV3: AF | BW3: AF | BX3: AF | BY3: AF | BZ3: AF | CA3: AF | CB3: AF | CC3: AF | CD3: AF | CE3: AF | CF3: AF | CG3: AF | CH3: AF | CI3: AF | CJ3: AF | CK3: AF | CL3: AF | CM3: AF | CN3: AF | CO3: AF | CP3: IC | CQ3: IC | CR3: IC | CS3: IC | CT3: IC | CU3: IC | CV3: IC | CW3: IC | CX3: IC | CY3: IC | CZ3: IC | DA3: IC | DB3: IC | DC3: IC | DD3: IC | DE3: IC | DF3: IC | DG3: IC | DH3: IC | DI3: IC | DJ3: IC | DK3: IC | DL3: IC | DM3: IC | DN3: IC | DO3: IC | DP3: IC | DQ3: IC | DR3: IC | DS3: IC | DT3: IC | DU3: IC | DV3: IC | DW3: IC | DX3: IC | DY3: IC | DZ3: IC | EA3: IC | EB3: IC | EC3: IC | ED3: IC | EE3: IC | EF3: MR | EG3: MR | EH3: MR | EI3: MR | EJ3: MR | EK3: MR | EL3: MR | EM3: MR | EN3: MR | EO3: MR | EP3: MR | EQ3: MR | ER3: MR | ES3: MR | ET3: MR | EU3: MR | EV3: MR | EW3: MR | EX3: MR | EY3: MR | EZ3: MR | FA3: MR | FB3: MR | FC3: MR | FD3: MR | FE3: MR | FF3: MR | FG3: MR | FH3: MR | FI3: MR | FJ3: MR | FK3: MR | FL3: MR | FM3: MR | FN3: MR | FO3: MR | FP3: MR | FQ3: MR | FR3: MR | FS3: MR | FT3: MR | FU3: MR | FV3: AF | FW3: AF | FX3: AF | FY3: AF | FZ3: AF | GA3: AF | GB3: AF | GC3: AF | GD3: AF | GE3: AF | GF3: AF | GG3: AF | GH3: AF | GI3: AF | GJ3: AF | GK3: AF | GL3: AF | GM3: AF | GN3: AF | GO3: AF | GP3: AF | GQ3: AF | GR3: AF | GS3: AF | GT3: AF | GU3: AF | GV3: AF | GW3: AF | GX3: AF | GY3: AF | GZ3: AF | HA3: AF | HB3: AF | HC3: AF | HD3: AF | HE3: AF | HF3: AF | HG3: AF | HH3: AF | HI3: AF | HJ3: AF | HK3: AF | HL3: IC | HM3: IC | HN3: IC | HO3: IC | HP3: IC | HQ3: IC | HR3: IC | HS3: IC | HT3: IC | HU3: IC | HV3: IC | HW3: IC | HX3: IC | HY3: IC | HZ3: IC | IA3: IC | IB3: IC | IC3: IC | ID3: IC | IE3: IC | IF3: IC | IG3: IC | IH3: IC | II3: IC | IJ3: IC | IK3: IC | IL3: IC | IM3: IC | IN3: IC | IO3: IC | IP3: IC | IQ3: IC | IR3: IC | IS3: IC | IT3: IC | IU3: IC | IV3: IC | IW3: IC | IX3: IC | IY3: IC | IZ3: IC | JA3: IC
A4: Шок драйвера | E4: BASE | F4: BASE | G4: BASE | J4: BASE | K4: LEADS | L4: CR_OPEN | M4: CR_FUND | N4: CHURN | O4: ACT | P4: TPA | Q4: TICKET | R4: TAKE | S4: EXEC | T4: AUC_PC | U4: CASH | V4: FLOAT_Y | W4: FLOAT_P | X4: MRG_PEN | Y4: MRG_DEBT | Z4: MRG_RATE | AA4: FUND_RATE | AB4: CL | AC4: FX_PEN | AD4: FX_VOL | AE4: FX_SPREAD | AF4: PRD_PEN | AG4: PRD_VOL | AH4: PRD_FEE | AI4: AM_SHARE | AJ4: AM_FEE | AK4: SUB_PEN | AL4: SUB_PRICE | AM4: CUST_FEE | AN4: SUP_RATE | AO4: SUP_COST | AP4: KYC_UNIT | AQ4: KYC_MAN | AR4: KYC_MAN_COST | AS4: OPS_PC | AT4: OPS_MAN | AU4: OPS_COST | AV4: RM_LOAD | AW4: RM_COST | AX4: CAC | AY4: OPLOSS | AZ4: BASE | BA4: LEADS | BB4: CR_OPEN | BC4: CR_FUND | BD4: CHURN | BE4: ACT | BF4: TPA | BG4: TICKET | BH4: TAKE | BI4: EXEC | BJ4: AUC_PC | BK4: CASH | BL4: FLOAT_Y | BM4: FLOAT_P | BN4: MRG_PEN | BO4: MRG_DEBT | BP4: MRG_RATE | BQ4: FUND_RATE | BR4: CL | BS4: FX_PEN | BT4: FX_VOL | BU4: FX_SPREAD | BV4: PRD_PEN | BW4: PRD_VOL | BX4: PRD_FEE | BY4: AM_SHARE | BZ4: AM_FEE | CA4: SUB_PEN | CB4: SUB_PRICE | CC4: CUST_FEE | CD4: SUP_RATE | CE4: SUP_COST | CF4: KYC_UNIT | CG4: KYC_MAN | CH4: KYC_MAN_COST | CI4: OPS_PC | CJ4: OPS_MAN | CK4: OPS_COST | CL4: RM_LOAD | CM4: RM_COST | CN4: CAC | CO4: OPLOSS | CP4: BASE | CQ4: LEADS | CR4: CR_OPEN | CS4: CR_FUND | CT4: CHURN | CU4: ACT | CV4: TPA | CW4: TICKET | CX4: TAKE | CY4: EXEC | CZ4: AUC_PC | DA4: CASH | DB4: FLOAT_Y | DC4: FLOAT_P | DD4: MRG_PEN | DE4: MRG_DEBT | DF4: MRG_RATE | DG4: FUND_RATE | DH4: CL | DI4: FX_PEN | DJ4: FX_VOL | DK4: FX_SPREAD | DL4: PRD_PEN | DM4: PRD_VOL | DN4: PRD_FEE | DO4: AM_SHARE | DP4: AM_FEE | DQ4: SUB_PEN | DR4: SUB_PRICE | DS4: CUST_FEE | DT4: SUP_RATE | DU4: SUP_COST | DV4: KYC_UNIT | DW4: KYC_MAN | DX4: KYC_MAN_COST | DY4: OPS_PC | DZ4: OPS_MAN | EA4: OPS_COST | EB4: RM_LOAD | EC4: RM_COST | ED4: CAC | EE4: OPLOSS | EF4: BASE | EG4: LEADS | EH4: CR_OPEN | EI4: CR_FUND | EJ4: CHURN | EK4: ACT | EL4: TPA | EM4: TICKET | EN4: TAKE | EO4: EXEC | EP4: AUC_PC | EQ4: CASH | ER4: FLOAT_Y | ES4: FLOAT_P | ET4: MRG_PEN | EU4: MRG_DEBT | EV4: MRG_RATE | EW4: FUND_RATE | EX4: CL | EY4: FX_PEN | EZ4: FX_VOL | FA4: FX_SPREAD | FB4: PRD_PEN | FC4: PRD_VOL | FD4: PRD_FEE | FE4: AM_SHARE | FF4: AM_FEE | FG4: SUB_PEN | FH4: SUB_PRICE | FI4: CUST_FEE | FJ4: SUP_RATE | FK4: SUP_COST | FL4: KYC_UNIT | FM4: KYC_MAN | FN4: KYC_MAN_COST | FO4: OPS_PC | FP4: OPS_MAN | FQ4: OPS_COST | FR4: RM_LOAD | FS4: RM_COST | FT4: CAC | FU4: OPLOSS | FV4: BASE | FW4: LEADS | FX4: CR_OPEN | FY4: CR_FUND | FZ4: CHURN | GA4: ACT | GB4: TPA | GC4: TICKET | GD4: TAKE | GE4: EXEC | GF4: AUC_PC | GG4: CASH | GH4: FLOAT_Y | GI4: FLOAT_P | GJ4: MRG_PEN | GK4: MRG_DEBT | GL4: MRG_RATE | GM4: FUND_RATE | GN4: CL | GO4: FX_PEN | GP4: FX_VOL | GQ4: FX_SPREAD | GR4: PRD_PEN | GS4: PRD_VOL | GT4: PRD_FEE | GU4: AM_SHARE | GV4: AM_FEE | GW4: SUB_PEN | GX4: SUB_PRICE | GY4: CUST_FEE | GZ4: SUP_RATE | HA4: SUP_COST | HB4: KYC_UNIT | HC4: KYC_MAN | HD4: KYC_MAN_COST | HE4: OPS_PC | HF4: OPS_MAN | HG4: OPS_COST | HH4: RM_LOAD | HI4: RM_COST | HJ4: CAC | HK4: OPLOSS | HL4: BASE | HM4: LEADS | HN4: CR_OPEN | HO4: CR_FUND | HP4: CHURN | HQ4: ACT | HR4: TPA | HS4: TICKET | HT4: TAKE | HU4: EXEC | HV4: AUC_PC | HW4: CASH | HX4: FLOAT_Y | HY4: FLOAT_P | HZ4: MRG_PEN | IA4: MRG_DEBT | IB4: MRG_RATE | IC4: FUND_RATE | ID4: CL | IE4: FX_PEN | IF4: FX_VOL | IG4: FX_SPREAD | IH4: PRD_PEN | II4: PRD_VOL | IJ4: PRD_FEE | IK4: AM_SHARE | IL4: AM_FEE | IM4: SUB_PEN | IN4: SUB_PRICE | IO4: CUST_FEE | IP4: SUP_RATE | IQ4: SUP_COST | IR4: KYC_UNIT | IS4: KYC_MAN | IT4: KYC_MAN_COST | IU4: OPS_PC | IV4: OPS_MAN | IW4: OPS_COST | IX4: RM_LOAD | IY4: RM_COST | IZ4: CAC | JA4: OPLOSS
A5: Горизонт | E5: =Вводные!$D$6 -> 1 | F5: =Вводные!$D$6 -> 1 | G5: =Вводные!$D$6 -> 1 | J5: 1 | K5: 1 | L5: 1 | M5: 1 | N5: 1 | O5: 1 | P5: 1 | Q5: 1 | R5: 1 | S5: 1 | T5: 1 | U5: 1 | V5: 1 | W5: 1 | X5: 1 | Y5: 1 | Z5: 1 | AA5: 1 | AB5: 1 | AC5: 1 | AD5: 1 | AE5: 1 | AF5: 1 | AG5: 1 | AH5: 1 | AI5: 1 | AJ5: 1 | AK5: 1 | AL5: 1 | AM5: 1 | AN5: 1 | AO5: 1 | AP5: 1 | AQ5: 1 | AR5: 1 | AS5: 1 | AT5: 1 | AU5: 1 | AV5: 1 | AW5: 1 | AX5: 1 | AY5: 1 | AZ5: 1 | BA5: 1 | BB5: 1 | BC5: 1 | BD5: 1 | BE5: 1 | BF5: 1 | BG5: 1 | BH5: 1 | BI5: 1 | BJ5: 1 | BK5: 1 | BL5: 1 | BM5: 1 | BN5: 1 | BO5: 1 | BP5: 1 | BQ5: 1 | BR5: 1 | BS5: 1 | BT5: 1 | BU5: 1 | BV5: 1 | BW5: 1 | BX5: 1 | BY5: 1 | BZ5: 1 | CA5: 1 | CB5: 1 | CC5: 1 | CD5: 1 | CE5: 1 | CF5: 1 | CG5: 1 | CH5: 1 | CI5: 1 | CJ5: 1 | CK5: 1 | CL5: 1 | CM5: 1 | CN5: 1 | CO5: 1 | CP5: 1 | CQ5: 1 | CR5: 1 | CS5: 1 | CT5: 1 | CU5: 1 | CV5: 1 | CW5: 1 | CX5: 1 | CY5: 1 | CZ5: 1 | DA5: 1 | DB5: 1 | DC5: 1 | DD5: 1 | DE5: 1 | DF5: 1 | DG5: 1 | DH5: 1 | DI5: 1 | DJ5: 1 | DK5: 1 | DL5: 1 | DM5: 1 | DN5: 1 | DO5: 1 | DP5: 1 | DQ5: 1 | DR5: 1 | DS5: 1 | DT5: 1 | DU5: 1 | DV5: 1 | DW5: 1 | DX5: 1 | DY5: 1 | DZ5: 1 | EA5: 1 | EB5: 1 | EC5: 1 | ED5: 1 | EE5: 1 | EF5: 3 | EG5: 3 | EH5: 3 | EI5: 3 | EJ5: 3 | EK5: 3 | EL5: 3 | EM5: 3 | EN5: 3 | EO5: 3 | EP5: 3 | EQ5: 3 | ER5: 3 | ES5: 3 | ET5: 3 | EU5: 3 | EV5: 3 | EW5: 3 | EX5: 3 | EY5: 3 | EZ5: 3 | FA5: 3 | FB5: 3 | FC5: 3 | FD5: 3 | FE5: 3 | FF5: 3 | FG5: 3 | FH5: 3 | FI5: 3 | FJ5: 3 | FK5: 3 | FL5: 3 | FM5: 3 | FN5: 3 | FO5: 3 | FP5: 3 | FQ5: 3 | FR5: 3 | FS5: 3 | FT5: 3 | FU5: 3 | FV5: 3 | FW5: 3 | FX5: 3 | FY5: 3 | FZ5: 3 | GA5: 3 | GB5: 3 | GC5: 3 | GD5: 3 | GE5: 3 | GF5: 3 | GG5: 3 | GH5: 3 | GI5: 3 | GJ5: 3 | GK5: 3 | GL5: 3 | GM5: 3 | GN5: 3 | GO5: 3 | GP5: 3 | GQ5: 3 | GR5: 3 | GS5: 3 | GT5: 3 | GU5: 3 | GV5: 3 | GW5: 3 | GX5: 3 | GY5: 3 | GZ5: 3 | HA5: 3 | HB5: 3 | HC5: 3 | HD5: 3 | HE5: 3 | HF5: 3 | HG5: 3 | HH5: 3 | HI5: 3 | HJ5: 3 | HK5: 3 | HL5: 3 | HM5: 3 | HN5: 3 | HO5: 3 | HP5: 3 | HQ5: 3 | HR5: 3 | HS5: 3 | HT5: 3 | HU5: 3 | HV5: 3 | HW5: 3 | HX5: 3 | HY5: 3 | HZ5: 3 | IA5: 3 | IB5: 3 | IC5: 3 | ID5: 3 | IE5: 3 | IF5: 3 | IG5: 3 | IH5: 3 | II5: 3 | IJ5: 3 | IK5: 3 | IL5: 3 | IM5: 3 | IN5: 3 | IO5: 3 | IP5: 3 | IQ5: 3 | IR5: 3 | IS5: 3 | IT5: 3 | IU5: 3 | IV5: 3 | IW5: 3 | IX5: 3 | IY5: 3 | IZ5: 3 | JA5: 3
A6: Ключ сценария | E6: MR|ПОКАЗ | F6: AF|ПОКАЗ | G6: IC|ПОКАЗ | J6: =J3&"|"&J4&"|"&J5 -> MR|BASE|1 | K6: =K3&"|"&K4&"|"&K5 -> MR|LEADS|1 | L6: =L3&"|"&L4&"|"&L5 -> MR|CR_OPEN|1 | M6: =M3&"|"&M4&"|"&M5 -> MR|CR_FUND|1 | N6: =N3&"|"&N4&"|"&N5 -> MR|CHURN|1 | O6: =O3&"|"&O4&"|"&O5 -> MR|ACT|1 | P6: =P3&"|"&P4&"|"&P5 -> MR|TPA|1 | Q6: =Q3&"|"&Q4&"|"&Q5 -> MR|TICKET|1 | ... JA6: =JA3&"|"&JA4&"|"&JA5 -> IC|OPLOSS|3
A7: Код | B7: Метрика | C7: Ед. | D7: Формула | E7: Масс-розница | F7: Состоятельные | G7: Институционалы и корп. | H7: Итого | J7: МР, год 1: база | K7: МР, год 1: LEADS | L7: МР, год 1: CR_OPEN | M7: МР, год 1: CR_FUND | N7: МР, год 1: CHURN | O7: МР, год 1: ACT | P7: МР, год 1: TPA | Q7: МР, год 1: TICKET | R7: МР, год 1: TAKE | S7: МР, год 1: EXEC | T7: МР, год 1: AUC_PC | U7: МР, год 1: CASH | V7: МР, год 1: FLOAT_Y | W7: МР, год 1: FLOAT_P | X7: МР, год 1: MRG_PEN | Y7: МР, год 1: MRG_DEBT | Z7: МР, год 1: MRG_RATE | AA7: МР, год 1: FUND_RATE | AB7: МР, год 1: CL | AC7: МР, год 1: FX_PEN | AD7: МР, год 1: FX_VOL | AE7: МР, год 1: FX_SPREAD | AF7: МР, год 1: PRD_PEN | AG7: МР, год 1: PRD_VOL | AH7: МР, год 1: PRD_FEE | AI7: МР, год 1: AM_SHARE | AJ7: МР, год 1: AM_FEE | AK7: МР, год 1: SUB_PEN | AL7: МР, год 1: SUB_PRICE | AM7: МР, год 1: CUST_FEE | AN7: МР, год 1: SUP_RATE | AO7: МР, год 1: SUP_COST | AP7: МР, год 1: KYC_UNIT | AQ7: МР, год 1: KYC_MAN | AR7: МР, год 1: KYC_MAN_COST | AS7: МР, год 1: OPS_PC | AT7: МР, год 1: OPS_MAN | AU7: МР, год 1: OPS_COST | AV7: МР, год 1: RM_LOAD | AW7: МР, год 1: RM_COST | AX7: МР, год 1: CAC | AY7: МР, год 1: OPLOSS | AZ7: СК, год 1: база | BA7: СК, год 1: LEADS | BB7: СК, год 1: CR_OPEN | BC7: СК, год 1: CR_FUND | BD7: СК, год 1: CHURN | BE7: СК, год 1: ACT | BF7: СК, год 1: TPA | BG7: СК, год 1: TICKET | BH7: СК, год 1: TAKE | BI7: СК, год 1: EXEC | BJ7: СК, год 1: AUC_PC | BK7: СК, год 1: CASH | BL7: СК, год 1: FLOAT_Y | BM7: СК, год 1: FLOAT_P | BN7: СК, год 1: MRG_PEN | BO7: СК, год 1: MRG_DEBT | BP7: СК, год 1: MRG_RATE | BQ7: СК, год 1: FUND_RATE | BR7: СК, год 1: CL | BS7: СК, год 1: FX_PEN | BT7: СК, год 1: FX_VOL | BU7: СК, год 1: FX_SPREAD | BV7: СК, год 1: PRD_PEN | BW7: СК, год 1: PRD_VOL | BX7: СК, год 1: PRD_FEE | BY7: СК, год 1: AM_SHARE | BZ7: СК, год 1: AM_FEE | CA7: СК, год 1: SUB_PEN | CB7: СК, год 1: SUB_PRICE | CC7: СК, год 1: CUST_FEE | CD7: СК, год 1: SUP_RATE | CE7: СК, год 1: SUP_COST | CF7: СК, год 1: KYC_UNIT | CG7: СК, год 1: KYC_MAN | CH7: СК, год 1: KYC_MAN_COST | CI7: СК, год 1: OPS_PC | CJ7: СК, год 1: OPS_MAN | CK7: СК, год 1: OPS_COST | CL7: СК, год 1: RM_LOAD | CM7: СК, год 1: RM_COST | CN7: СК, год 1: CAC | CO7: СК, год 1: OPLOSS | CP7: ИК, год 1: база | CQ7: ИК, год 1: LEADS | CR7: ИК, год 1: CR_OPEN | CS7: ИК, год 1: CR_FUND | CT7: ИК, год 1: CHURN | CU7: ИК, год 1: ACT | CV7: ИК, год 1: TPA | CW7: ИК, год 1: TICKET | CX7: ИК, год 1: TAKE | CY7: ИК, год 1: EXEC | CZ7: ИК, год 1: AUC_PC | DA7: ИК, год 1: CASH | DB7: ИК, год 1: FLOAT_Y | DC7: ИК, год 1: FLOAT_P | DD7: ИК, год 1: MRG_PEN | DE7: ИК, год 1: MRG_DEBT | DF7: ИК, год 1: MRG_RATE | DG7: ИК, год 1: FUND_RATE | DH7: ИК, год 1: CL | DI7: ИК, год 1: FX_PEN | DJ7: ИК, год 1: FX_VOL | DK7: ИК, год 1: FX_SPREAD | DL7: ИК, год 1: PRD_PEN | DM7: ИК, год 1: PRD_VOL | DN7: ИК, год 1: PRD_FEE | DO7: ИК, год 1: AM_SHARE | DP7: ИК, год 1: AM_FEE | DQ7: ИК, год 1: SUB_PEN | DR7: ИК, год 1: SUB_PRICE | DS7: ИК, год 1: CUST_FEE | DT7: ИК, год 1: SUP_RATE | DU7: ИК, год 1: SUP_COST | DV7: ИК, год 1: KYC_UNIT | DW7: ИК, год 1: KYC_MAN | DX7: ИК, год 1: KYC_MAN_COST | DY7: ИК, год 1: OPS_PC | DZ7: ИК, год 1: OPS_MAN | EA7: ИК, год 1: OPS_COST | EB7: ИК, год 1: RM_LOAD | EC7: ИК, год 1: RM_COST | ED7: ИК, год 1: CAC | EE7: ИК, год 1: OPLOSS | EF7: МР, долгосрочно: база | EG7: МР, долгосрочно: LEADS | EH7: МР, долгосрочно: CR_OPEN | EI7: МР, долгосрочно: CR_FUND | EJ7: МР, долгосрочно: CHURN | EK7: МР, долгосрочно: ACT | EL7: МР, долгосрочно: TPA | EM7: МР, долгосрочно: TICKET | EN7: МР, долгосрочно: TAKE | EO7: МР, долгосрочно: EXEC | EP7: МР, долгосрочно: AUC_PC | EQ7: МР, долгосрочно: CASH | ER7: МР, долгосрочно: FLOAT_Y | ES7: МР, долгосрочно: FLOAT_P | ET7: МР, долгосрочно: MRG_PEN | EU7: МР, долгосрочно: MRG_DEBT | EV7: МР, долгосрочно: MRG_RATE | EW7: МР, долгосрочно: FUND_RATE | EX7: МР, долгосрочно: CL | EY7: МР, долгосрочно: FX_PEN | EZ7: МР, долгосрочно: FX_VOL | FA7: МР, долгосрочно: FX_SPREAD | FB7: МР, долгосрочно: PRD_PEN | FC7: МР, долгосрочно: PRD_VOL | FD7: МР, долгосрочно: PRD_FEE | FE7: МР, долгосрочно: AM_SHARE | FF7: МР, долгосрочно: AM_FEE | FG7: МР, долгосрочно: SUB_PEN | FH7: МР, долгосрочно: SUB_PRICE | FI7: МР, долгосрочно: CUST_FEE | FJ7: МР, долгосрочно: SUP_RATE | FK7: МР, долгосрочно: SUP_COST | FL7: МР, долгосрочно: KYC_UNIT | FM7: МР, долгосрочно: KYC_MAN | FN7: МР, долгосрочно: KYC_MAN_COST | FO7: МР, долгосрочно: OPS_PC | FP7: МР, долгосрочно: OPS_MAN | FQ7: МР, долгосрочно: OPS_COST | FR7: МР, долгосрочно: RM_LOAD | FS7: МР, долгосрочно: RM_COST | FT7: МР, долгосрочно: CAC | FU7: МР, долгосрочно: OPLOSS | FV7: СК, долгосрочно: база | FW7: СК, долгосрочно: LEADS | FX7: СК, долгосрочно: CR_OPEN | FY7: СК, долгосрочно: CR_FUND | FZ7: СК, долгосрочно: CHURN | GA7: СК, долгосрочно: ACT | GB7: СК, долгосрочно: TPA | GC7: СК, долгосрочно: TICKET | GD7: СК, долгосрочно: TAKE | GE7: СК, долгосрочно: EXEC | GF7: СК, долгосрочно: AUC_PC | GG7: СК, долгосрочно: CASH | GH7: СК, долгосрочно: FLOAT_Y | GI7: СК, долгосрочно: FLOAT_P | GJ7: СК, долгосрочно: MRG_PEN | GK7: СК, долгосрочно: MRG_DEBT | GL7: СК, долгосрочно: MRG_RATE | GM7: СК, долгосрочно: FUND_RATE | GN7: СК, долгосрочно: CL | GO7: СК, долгосрочно: FX_PEN | GP7: СК, долгосрочно: FX_VOL | GQ7: СК, долгосрочно: FX_SPREAD | GR7: СК, долгосрочно: PRD_PEN | GS7: СК, долгосрочно: PRD_VOL | GT7: СК, долгосрочно: PRD_FEE | GU7: СК, долгосрочно: AM_SHARE | GV7: СК, долгосрочно: AM_FEE | GW7: СК, долгосрочно: SUB_PEN | GX7: СК, долгосрочно: SUB_PRICE | GY7: СК, долгосрочно: CUST_FEE | GZ7: СК, долгосрочно: SUP_RATE | HA7: СК, долгосрочно: SUP_COST | HB7: СК, долгосрочно: KYC_UNIT | HC7: СК, долгосрочно: KYC_MAN | HD7: СК, долгосрочно: KYC_MAN_COST | HE7: СК, долгосрочно: OPS_PC | HF7: СК, долгосрочно: OPS_MAN | HG7: СК, долгосрочно: OPS_COST | HH7: СК, долгосрочно: RM_LOAD | HI7: СК, долгосрочно: RM_COST | HJ7: СК, долгосрочно: CAC | HK7: СК, долгосрочно: OPLOSS | HL7: ИК, долгосрочно: база | HM7: ИК, долгосрочно: LEADS | HN7: ИК, долгосрочно: CR_OPEN | HO7: ИК, долгосрочно: CR_FUND | HP7: ИК, долгосрочно: CHURN | HQ7: ИК, долгосрочно: ACT | HR7: ИК, долгосрочно: TPA | HS7: ИК, долгосрочно: TICKET | HT7: ИК, долгосрочно: TAKE | HU7: ИК, долгосрочно: EXEC | HV7: ИК, долгосрочно: AUC_PC | HW7: ИК, долгосрочно: CASH | HX7: ИК, долгосрочно: FLOAT_Y | HY7: ИК, долгосрочно: FLOAT_P | HZ7: ИК, долгосрочно: MRG_PEN | IA7: ИК, долгосрочно: MRG_DEBT | IB7: ИК, долгосрочно: MRG_RATE | IC7: ИК, долгосрочно: FUND_RATE | ID7: ИК, долгосрочно: CL | IE7: ИК, долгосрочно: FX_PEN | IF7: ИК, долгосрочно: FX_VOL | IG7: ИК, долгосрочно: FX_SPREAD | IH7: ИК, долгосрочно: PRD_PEN | II7: ИК, долгосрочно: PRD_VOL | IJ7: ИК, долгосрочно: PRD_FEE | IK7: ИК, долгосрочно: AM_SHARE | IL7: ИК, долгосрочно: AM_FEE | IM7: ИК, долгосрочно: SUB_PEN | IN7: ИК, долгосрочно: SUB_PRICE | IO7: ИК, долгосрочно: CUST_FEE | IP7: ИК, долгосрочно: SUP_RATE | IQ7: ИК, долгосрочно: SUP_COST | IR7: ИК, долгосрочно: KYC_UNIT | IS7: ИК, долгосрочно: KYC_MAN | IT7: ИК, долгосрочно: KYC_MAN_COST | IU7: ИК, долгосрочно: OPS_PC | IV7: ИК, долгосрочно: OPS_MAN | IW7: ИК, долгосрочно: OPS_COST | IX7: ИК, долгосрочно: RM_LOAD | IY7: ИК, долгосрочно: RM_COST | IZ7: ИК, долгосрочно: CAC | JA7: ИК, долгосрочно: OPLOSS
A8: Клиентская база
A9: N0 | B9: Фондированные клиенты на начало периода | C9: чел. | D9: Вводная | E9: =INDEX(Вводные!$D$13:$F$64,MATCH($A9,Вводные!$A$13:$A$64,0),MATCH(E$3,Вводные!$D$11:$F$11,0))*(1+IF(E$4=$A9,Вводные!$D$5*INDEX(Вводные!$G$13:$G$64,MATCH($A9,Вводные!$A$13:$A$64,0)),0)) -> 500000 | F9: =INDEX(Вводные!$D$13:$F$64,MATCH($A9,Вводные!$A$13:$A$64,0),MATCH(F$3,Вводные!$D$11:$F$11,0))*(1+IF(F$4=$A9,Вводные!$D$5*INDEX(Вводные!$G$13:$G$64,MATCH($A9,Вводные!$A$13:$A$64,0)),0)) -> 15000 | G9: =INDEX(Вводные!$D$13:$F$64,MATCH($A9,Вводные!$A$13:$A$64,0),MATCH(G$3,Вводные!$D$11:$F$11,0))*(1+IF(G$4=$A9,Вводные!$D$5*INDEX(Вводные!$G$13:$G$64,MATCH($A9,Вводные!$A$13:$A$64,0)),0)) -> 400 | H9: =SUM(E9:G9) -> 515400 | J9: =INDEX(Вводные!$D$13:$F$64,MATCH($A9,Вводные!$A$13:$A$64,0),MATCH(J$3,Вводные!$D$11:$F$11,0))*(1+IF(J$4=$A9,Вводные!$D$5*INDEX(Вводные!$G$13:$G$64,MATCH($A9,Вводные!$A$13:$A$64,0)),0)) -> 500000 | K9: =INDEX(Вводные!$D$13:$F$64,MATCH($A9,Вводные!$A$13:$A$64,0),MATCH(K$3,Вводные!$D$11:$F$11,0))*(1+IF(K$4=$A9,Вводные!$D$5*INDEX(Вводные!$G$13:$G$64,MATCH($A9,Вводные!$A$13:$A$64,0)),0)) -> 500000 | L9: =INDEX(Вводные!$D$13:$F$64,MATCH($A9,Вводные!$A$13:$A$64,0),MATCH(L$3,Вводные!$D$11:$F$11,0))*(1+IF(L$4=$A9,Вводные!$D$5*INDEX(Вводные!$G$13:$G$64,MATCH($A9,Вводные!$A$13:$A$64,0)),0)) -> 500000 | M9: =INDEX(Вводные!$D$13:$F$64,MATCH($A9,Вводные!$A$13:$A$64,0),MATCH(M$3,Вводные!$D$11:$F$11,0))*(1+IF(M$4=$A9,Вводные!$D$5*INDEX(Вводные!$G$13:$G$64,MATCH($A9,Вводные!$A$13:$A$64,0)),0)) -> 500000 | N9: =INDEX(Вводные!$D$13:$F$64,MATCH($A9,Вводные!$A$13:$A$64,0),MATCH(N$3,Вводные!$D$11:$F$11,0))*(1+IF(N$4=$A9,Вводные!$D$5*INDEX(Вводные!$G$13:$G$64,MATCH($A9,Вводные!$A$13:$A$64,0)),0)) -> 500000 | O9: =INDEX(Вводные!$D$13:$F$64,MATCH($A9,Вводные!$A$13:$A$64,0),MATCH(O$3,Вводные!$D$11:$F$11,0))*(1+IF(O$4=$A9,Вводные!$D$5*INDEX(Вводные!$G$13:$G$64,MATCH($A9,Вводные!$A$13:$A$64,0)),0)) -> 500000 | P9: =INDEX(Вводные!$D$13:$F$64,MATCH($A9,Вводные!$A$13:$A$64,0),MATCH(P$3,Вводные!$D$11:$F$11,0))*(1+IF(P$4=$A9,Вводные!$D$5*INDEX(Вводные!$G$13:$G$64,MATCH($A9,Вводные!$A$13:$A$64,0)),0)) -> 500000 | Q9: =INDEX(Вводные!$D$13:$F$64,MATCH($A9,Вводные!$A$13:$A$64,0),MATCH(Q$3,Вводные!$D$11:$F$11,0))*(1+IF(Q$4=$A9,Вводные!$D$5*INDEX(Вводные!$G$13:$G$64,MATCH($A9,Вводные!$A$13:$A$64,0)),0)) -> 500000 | ... JA9: =INDEX(Вводные!$D$13:$F$64,MATCH($A9,Вводные!$A$13:$A$64,0),MATCH(JA$3,Вводные!$D$11:$F$11,0))*(1+IF(JA$4=$A9,Вводные!$D$5*INDEX(Вводные!$G$13:$G$64,MATCH($A9,Вводные!$A$13:$A$64,0)),0)) -> 400
A10: LEADS | B10: Заявки на открытие счёта за период (ИК — потенциальные клиенты в воронке продаж) | C10: шт. | D10: Вводная | E10: =INDEX(Вводные!$D$13:$F$64,MATCH($A10,Вводные!$A$13:$A$64,0),MATCH(E$3,Вводные!$D$11:$F$11,0))*(1+IF(E$4=$A10,Вводные!$D$5*INDEX(Вводные!$G$13:$G$64,MATCH($A10,Вводные!$A$13:$A$64,0)),0)) -> 300000 | F10: =INDEX(Вводные!$D$13:$F$64,MATCH($A10,Вводные!$A$13:$A$64,0),MATCH(F$3,Вводные!$D$11:$F$11,0))*(1+IF(F$4=$A10,Вводные!$D$5*INDEX(Вводные!$G$13:$G$64,MATCH($A10,Вводные!$A$13:$A$64,0)),0)) -> 2000 | G10: =INDEX(Вводные!$D$13:$F$64,MATCH($A10,Вводные!$A$13:$A$64,0),MATCH(G$3,Вводные!$D$11:$F$11,0))*(1+IF(G$4=$A10,Вводные!$D$5*INDEX(Вводные!$G$13:$G$64,MATCH($A10,Вводные!$A$13:$A$64,0)),0)) -> 120 | H10: =SUM(E10:G10) -> 302120 | J10: =INDEX(Вводные!$D$13:$F$64,MATCH($A10,Вводные!$A$13:$A$64,0),MATCH(J$3,Вводные!$D$11:$F$11,0))*(1+IF(J$4=$A10,Вводные!$D$5*INDEX(Вводные!$G$13:$G$64,MATCH($A10,Вводные!$A$13:$A$64,0)),0)) -> 300000 | K10: =INDEX(Вводные!$D$13:$F$64,MATCH($A10,Вводные!$A$13:$A$64,0),MATCH(K$3,Вводные!$D$11:$F$11,0))*(1+IF(K$4=$A10,Вводные!$D$5*INDEX(Вводные!$G$13:$G$64,MATCH($A10,Вводные!$A$13:$A$64,0)),0)) -> 303000 | L10: =INDEX(Вводные!$D$13:$F$64,MATCH($A10,Вводные!$A$13:$A$64,0),MATCH(L$3,Вводные!$D$11:$F$11,0))*(1+IF(L$4=$A10,Вводные!$D$5*INDEX(Вводные!$G$13:$G$64,MATCH($A10,Вводные!$A$13:$A$64,0)),0)) -> 300000 | M10: =INDEX(Вводные!$D$13:$F$64,MATCH($A10,Вводные!$A$13:$A$64,0),MATCH(M$3,Вводные!$D$11:$F$11,0))*(1+IF(M$4=$A10,Вводные!$D$5*INDEX(Вводные!$G$13:$G$64,MATCH($A10,Вводные!$A$13:$A$64,0)),0)) -> 300000 | N10: =INDEX(Вводные!$D$13:$F$64,MATCH($A10,Вводные!$A$13:$A$64,0),MATCH(N$3,Вводные!$D$11:$F$11,0))*(1+IF(N$4=$A10,Вводные!$D$5*INDEX(Вводные!$G$13:$G$64,MATCH($A10,Вводные!$A$13:$A$64,0)),0)) -> 300000 | O10: =INDEX(Вводные!$D$13:$F$64,MATCH($A10,Вводные!$A$13:$A$64,0),MATCH(O$3,Вводные!$D$11:$F$11,0))*(1+IF(O$4=$A10,Вводные!$D$5*INDEX(Вводные!$G$13:$G$64,MATCH($A10,Вводные!$A$13:$A$64,0)),0)) -> 300000 | P10: =INDEX(Вводные!$D$13:$F$64,MATCH($A10,Вводные!$A$13:$A$64,0),MATCH(P$3,Вводные!$D$11:$F$11,0))*(1+IF(P$4=$A10,Вводные!$D$5*INDEX(Вводные!$G$13:$G$64,MATCH($A10,Вводные!$A$13:$A$64,0)),0)) -> 300000 | Q10: =INDEX(Вводные!$D$13:$F$64,MATCH($A10,Вводные!$A$13:$A$64,0),MATCH(Q$3,Вводные!$D$11:$F$11,0))*(1+IF(Q$4=$A10,Вводные!$D$5*INDEX(Вводные!$G$13:$G$64,MATCH($A10,Вводные!$A$13:$A$64,0)),0)) -> 300000 | ... JA10: =INDEX(Вводные!$D$13:$F$64,MATCH($A10,Вводные!$A$13:$A$64,0),MATCH(JA$3,Вводные!$D$11:$F$11,0))*(1+IF(JA$4=$A10,Вводные!$D$5*INDEX(Вводные!$G$13:$G$64,MATCH($A10,Вводные!$A$13:$A$64,0)),0)) -> 120
A11: CR_OPEN | B11: Конверсия: заявка → открытый счёт (KYC пройден; ИК — договор подписан) | C11: % | D11: Вводная | E11: =INDEX(Вводные!$D$13:$F$64,MATCH($A11,Вводные!$A$13:$A$64,0),MATCH(E$3,Вводные!$D$11:$F$11,0))*(1+IF(E$4=$A11,Вводные!$D$5*INDEX(Вводные!$G$13:$G$64,MATCH($A11,Вводные!$A$13:$A$64,0)),0)) -> 0.45 | F11: =INDEX(Вводные!$D$13:$F$64,MATCH($A11,Вводные!$A$13:$A$64,0),MATCH(F$3,Вводные!$D$11:$F$11,0))*(1+IF(F$4=$A11,Вводные!$D$5*INDEX(Вводные!$G$13:$G$64,MATCH($A11,Вводные!$A$13:$A$64,0)),0)) -> 0.7 | G11: =INDEX(Вводные!$D$13:$F$64,MATCH($A11,Вводные!$A$13:$A$64,0),MATCH(G$3,Вводные!$D$11:$F$11,0))*(1+IF(G$4=$A11,Вводные!$D$5*INDEX(Вводные!$G$13:$G$64,MATCH($A11,Вводные!$A$13:$A$64,0)),0)) -> 0.4 | J11: =INDEX(Вводные!$D$13:$F$64,MATCH($A11,Вводные!$A$13:$A$64,0),MATCH(J$3,Вводные!$D$11:$F$11,0))*(1+IF(J$4=$A11,Вводные!$D$5*INDEX(Вводные!$G$13:$G$64,MATCH($A11,Вводные!$A$13:$A$64,0)),0)) -> 0.45 | K11: =INDEX(Вводные!$D$13:$F$64,MATCH($A11,Вводные!$A$13:$A$64,0),MATCH(K$3,Вводные!$D$11:$F$11,0))*(1+IF(K$4=$A11,Вводные!$D$5*INDEX(Вводные!$G$13:$G$64,MATCH($A11,Вводные!$A$13:$A$64,0)),0)) -> 0.45 | L11: =INDEX(Вводные!$D$13:$F$64,MATCH($A11,Вводные!$A$13:$A$64,0),MATCH(L$3,Вводные!$D$11:$F$11,0))*(1+IF(L$4=$A11,Вводные!$D$5*INDEX(Вводные!$G$13:$G$64,MATCH($A11,Вводные!$A$13:$A$64,0)),0)) -> 0.4545 | M11: =INDEX(Вводные!$D$13:$F$64,MATCH($A11,Вводные!$A$13:$A$64,0),MATCH(M$3,Вводные!$D$11:$F$11,0))*(1+IF(M$4=$A11,Вводные!$D$5*INDEX(Вводные!$G$13:$G$64,MATCH($A11,Вводные!$A$13:$A$64,0)),0)) -> 0.45 | N11: =INDEX(Вводные!$D$13:$F$64,MATCH($A11,Вводные!$A$13:$A$64,0),MATCH(N$3,Вводные!$D$11:$F$11,0))*(1+IF(N$4=$A11,Вводные!$D$5*INDEX(Вводные!$G$13:$G$64,MATCH($A11,Вводные!$A$13:$A$64,0)),0)) -> 0.45 | O11: =INDEX(Вводные!$D$13:$F$64,MATCH($A11,Вводные!$A$13:$A$64,0),MATCH(O$3,Вводные!$D$11:$F$11,0))*(1+IF(O$4=$A11,Вводные!$D$5*INDEX(Вводные!$G$13:$G$64,MATCH($A11,Вводные!$A$13:$A$64,0)),0)) -> 0.45 | P11: =INDEX(Вводные!$D$13:$F$64,MATCH($A11,Вводные!$A$13:$A$64,0),MATCH(P$3,Вводные!$D$11:$F$11,0))*(1+IF(P$4=$A11,Вводные!$D$5*INDEX(Вводные!$G$13:$G$64,MATCH($A11,Вводные!$A$13:$A$64,0)),0)) -> 0.45 | Q11: =INDEX(Вводные!$D$13:$F$64,MATCH($A11,Вводные!$A$13:$A$64,0),MATCH(Q$3,Вводные!$D$11:$F$11,0))*(1+IF(Q$4=$A11,Вводные!$D$5*INDEX(Вводные!$G$13:$G$64,MATCH($A11,Вводные!$A$13:$A$64,0)),0)) -> 0.45 | ... JA11: =INDEX(Вводные!$D$13:$F$64,MATCH($A11,Вводные!$A$13:$A$64,0),MATCH(JA$3,Вводные!$D$11:$F$11,0))*(1+IF(JA$4=$A11,Вводные!$D$5*INDEX(Вводные!$G$13:$G$64,MATCH($A11,Вводные!$A$13:$A$64,0)),0)) -> 0.4
A12: CR_FUND | B12: Конверсия: открытый счёт → фондированный (первое пополнение) | C12: % | D12: Вводная | E12: =INDEX(Вводные!$D$13:$F$64,MATCH($A12,Вводные!$A$13:$A$64,0),MATCH(E$3,Вводные!$D$11:$F$11,0))*(1+IF(E$4=$A12,Вводные!$D$5*INDEX(Вводные!$G$13:$G$64,MATCH($A12,Вводные!$A$13:$A$64,0)),0)) -> 0.55 | F12: =INDEX(Вводные!$D$13:$F$64,MATCH($A12,Вводные!$A$13:$A$64,0),MATCH(F$3,Вводные!$D$11:$F$11,0))*(1+IF(F$4=$A12,Вводные!$D$5*INDEX(Вводные!$G$13:$G$64,MATCH($A12,Вводные!$A$13:$A$64,0)),0)) -> 0.8 | G12: =INDEX(Вводные!$D$13:$F$64,MATCH($A12,Вводные!$A$13:$A$64,0),MATCH(G$3,Вводные!$D$11:$F$11,0))*(1+IF(G$4=$A12,Вводные!$D$5*INDEX(Вводные!$G$13:$G$64,MATCH($A12,Вводные!$A$13:$A$64,0)),0)) -> 0.75 | J12: =INDEX(Вводные!$D$13:$F$64,MATCH($A12,Вводные!$A$13:$A$64,0),MATCH(J$3,Вводные!$D$11:$F$11,0))*(1+IF(J$4=$A12,Вводные!$D$5*INDEX(Вводные!$G$13:$G$64,MATCH($A12,Вводные!$A$13:$A$64,0)),0)) -> 0.55 | K12: =INDEX(Вводные!$D$13:$F$64,MATCH($A12,Вводные!$A$13:$A$64,0),MATCH(K$3,Вводные!$D$11:$F$11,0))*(1+IF(K$4=$A12,Вводные!$D$5*INDEX(Вводные!$G$13:$G$64,MATCH($A12,Вводные!$A$13:$A$64,0)),0)) -> 0.55 | L12: =INDEX(Вводные!$D$13:$F$64,MATCH($A12,Вводные!$A$13:$A$64,0),MATCH(L$3,Вводные!$D$11:$F$11,0))*(1+IF(L$4=$A12,Вводные!$D$5*INDEX(Вводные!$G$13:$G$64,MATCH($A12,Вводные!$A$13:$A$64,0)),0)) -> 0.55 | M12: =INDEX(Вводные!$D$13:$F$64,MATCH($A12,Вводные!$A$13:$A$64,0),MATCH(M$3,Вводные!$D$11:$F$11,0))*(1+IF(M$4=$A12,Вводные!$D$5*INDEX(Вводные!$G$13:$G$64,MATCH($A12,Вводные!$A$13:$A$64,0)),0)) -> 0.5555 | N12: =INDEX(Вводные!$D$13:$F$64,MATCH($A12,Вводные!$A$13:$A$64,0),MATCH(N$3,Вводные!$D$11:$F$11,0))*(1+IF(N$4=$A12,Вводные!$D$5*INDEX(Вводные!$G$13:$G$64,MATCH($A12,Вводные!$A$13:$A$64,0)),0)) -> 0.55 | O12: =INDEX(Вводные!$D$13:$F$64,MATCH($A12,Вводные!$A$13:$A$64,0),MATCH(O$3,Вводные!$D$11:$F$11,0))*(1+IF(O$4=$A12,Вводные!$D$5*INDEX(Вводные!$G$13:$G$64,MATCH($A12,Вводные!$A$13:$A$64,0)),0)) -> 0.55 | P12: =INDEX(Вводные!$D$13:$F$64,MATCH($A12,Вводные!$A$13:$A$64,0),MATCH(P$3,Вводные!$D$11:$F$11,0))*(1+IF(P$4=$A12,Вводные!$D$5*INDEX(Вводные!$G$13:$G$64,MATCH($A12,Вводные!$A$13:$A$64,0)),0)) -> 0.55 | Q12: =INDEX(Вводные!$D$13:$F$64,MATCH($A12,Вводные!$A$13:$A$64,0),MATCH(Q$3,Вводные!$D$11:$F$11,0))*(1+IF(Q$4=$A12,Вводные!$D$5*INDEX(Вводные!$G$13:$G$64,MATCH($A12,Вводные!$A$13:$A$64,0)),0)) -> 0.55 | ... JA12: =INDEX(Вводные!$D$13:$F$64,MATCH($A12,Вводные!$A$13:$A$64,0),MATCH(JA$3,Вводные!$D$11:$F$11,0))*(1+IF(JA$4=$A12,Вводные!$D$5*INDEX(Вводные!$G$13:$G$64,MATCH($A12,Вводные!$A$13:$A$64,0)),0)) -> 0.75
A13: NEW | B13: Новые фондированные клиенты | C13: чел. | D13: LEADS × CR_OPEN × CR_FUND | E13: =E10*E11*E12 -> 74250 | F13: =F10*F11*F12 -> 1120 | G13: =G10*G11*G12 -> 36 | H13: =SUM(E13:G13) -> 75406 | J13: =J10*J11*J12 -> 74250 | K13: =K10*K11*K12 -> 74992.5 | L13: =L10*L11*L12 -> 74992.5 | M13: =M10*M11*M12 -> 74992.5 | N13: =N10*N11*N12 -> 74250 | O13: =O10*O11*O12 -> 74250 | P13: =P10*P11*P12 -> 74250 | Q13: =Q10*Q11*Q12 -> 74250 | ... JA13: =JA10*JA11*JA12 -> 36
A14: CHURN | B14: Годовой отток фондированных клиентов (вывели активы ниже порога или закрыли счёт) | C14: % | D14: Вводная | E14: =INDEX(Вводные!$D$13:$F$64,MATCH($A14,Вводные!$A$13:$A$64,0),MATCH(E$3,Вводные!$D$11:$F$11,0))*(1+IF(E$4=$A14,Вводные!$D$5*INDEX(Вводные!$G$13:$G$64,MATCH($A14,Вводные!$A$13:$A$64,0)),0)) -> 0.12 | F14: =INDEX(Вводные!$D$13:$F$64,MATCH($A14,Вводные!$A$13:$A$64,0),MATCH(F$3,Вводные!$D$11:$F$11,0))*(1+IF(F$4=$A14,Вводные!$D$5*INDEX(Вводные!$G$13:$G$64,MATCH($A14,Вводные!$A$13:$A$64,0)),0)) -> 0.06 | G14: =INDEX(Вводные!$D$13:$F$64,MATCH($A14,Вводные!$A$13:$A$64,0),MATCH(G$3,Вводные!$D$11:$F$11,0))*(1+IF(G$4=$A14,Вводные!$D$5*INDEX(Вводные!$G$13:$G$64,MATCH($A14,Вводные!$A$13:$A$64,0)),0)) -> 0.08 | J14: =INDEX(Вводные!$D$13:$F$64,MATCH($A14,Вводные!$A$13:$A$64,0),MATCH(J$3,Вводные!$D$11:$F$11,0))*(1+IF(J$4=$A14,Вводные!$D$5*INDEX(Вводные!$G$13:$G$64,MATCH($A14,Вводные!$A$13:$A$64,0)),0)) -> 0.12 | K14: =INDEX(Вводные!$D$13:$F$64,MATCH($A14,Вводные!$A$13:$A$64,0),MATCH(K$3,Вводные!$D$11:$F$11,0))*(1+IF(K$4=$A14,Вводные!$D$5*INDEX(Вводные!$G$13:$G$64,MATCH($A14,Вводные!$A$13:$A$64,0)),0)) -> 0.12 | L14: =INDEX(Вводные!$D$13:$F$64,MATCH($A14,Вводные!$A$13:$A$64,0),MATCH(L$3,Вводные!$D$11:$F$11,0))*(1+IF(L$4=$A14,Вводные!$D$5*INDEX(Вводные!$G$13:$G$64,MATCH($A14,Вводные!$A$13:$A$64,0)),0)) -> 0.12 | M14: =INDEX(Вводные!$D$13:$F$64,MATCH($A14,Вводные!$A$13:$A$64,0),MATCH(M$3,Вводные!$D$11:$F$11,0))*(1+IF(M$4=$A14,Вводные!$D$5*INDEX(Вводные!$G$13:$G$64,MATCH($A14,Вводные!$A$13:$A$64,0)),0)) -> 0.12 | N14: =INDEX(Вводные!$D$13:$F$64,MATCH($A14,Вводные!$A$13:$A$64,0),MATCH(N$3,Вводные!$D$11:$F$11,0))*(1+IF(N$4=$A14,Вводные!$D$5*INDEX(Вводные!$G$13:$G$64,MATCH($A14,Вводные!$A$13:$A$64,0)),0)) -> 0.1188 | O14: =INDEX(Вводные!$D$13:$F$64,MATCH($A14,Вводные!$A$13:$A$64,0),MATCH(O$3,Вводные!$D$11:$F$11,0))*(1+IF(O$4=$A14,Вводные!$D$5*INDEX(Вводные!$G$13:$G$64,MATCH($A14,Вводные!$A$13:$A$64,0)),0)) -> 0.12 | P14: =INDEX(Вводные!$D$13:$F$64,MATCH($A14,Вводные!$A$13:$A$64,0),MATCH(P$3,Вводные!$D$11:$F$11,0))*(1+IF(P$4=$A14,Вводные!$D$5*INDEX(Вводные!$G$13:$G$64,MATCH($A14,Вводные!$A$13:$A$64,0)),0)) -> 0.12 | Q14: =INDEX(Вводные!$D$13:$F$64,MATCH($A14,Вводные!$A$13:$A$64,0),MATCH(Q$3,Вводные!$D$11:$F$11,0))*(1+IF(Q$4=$A14,Вводные!$D$5*INDEX(Вводные!$G$13:$G$64,MATCH($A14,Вводные!$A$13:$A$64,0)),0)) -> 0.12 | ... JA14: =INDEX(Вводные!$D$13:$F$64,MATCH($A14,Вводные!$A$13:$A$64,0),MATCH(JA$3,Вводные!$D$11:$F$11,0))*(1+IF(JA$4=$A14,Вводные!$D$5*INDEX(Вводные!$G$13:$G$64,MATCH($A14,Вводные!$A$13:$A$64,0)),0)) -> 0.08
A15: CHURNED | B15: Ушедшие фондированные клиенты | C15: чел. | D15: N0 × CHURN | E15: =E9*E14 -> 60000 | F15: =F9*F14 -> 900 | G15: =G9*G14 -> 32 | H15: =SUM(E15:G15) -> 60932 | J15: =J9*J14 -> 60000 | K15: =K9*K14 -> 60000 | L15: =L9*L14 -> 60000 | M15: =M9*M14 -> 60000 | N15: =N9*N14 -> 59400 | O15: =O9*O14 -> 60000 | P15: =P9*P14 -> 60000 | Q15: =Q9*Q14 -> 60000 | ... JA15: =JA9*JA14 -> 32
A16: N_AVG | B16: Фондированные клиенты, среднее за период | C16: чел. | D16: Горизонт 1: N0 + ½(NEW − CHURNED); 2: N0 + NEW − CHURNED; 3: NEW ÷ CHURN | E16: =IF(E$5=3,IF(E14>0,E13/E14,E9),E9+IF(E$5=1,0.5,1)*(E13-E15)) -> 507125 | F16: =IF(F$5=3,IF(F14>0,F13/F14,F9),F9+IF(F$5=1,0.5,1)*(F13-F15)) -> 15110 | G16: =IF(G$5=3,IF(G14>0,G13/G14,G9),G9+IF(G$5=1,0.5,1)*(G13-G15)) -> 402 | H16: =SUM(E16:G16) -> 522637 | J16: =IF(J$5=3,IF(J14>0,J13/J14,J9),J9+IF(J$5=1,0.5,1)*(J13-J15)) -> 507125 | K16: =IF(K$5=3,IF(K14>0,K13/K14,K9),K9+IF(K$5=1,0.5,1)*(K13-K15)) -> 507496.25 | L16: =IF(L$5=3,IF(L14>0,L13/L14,L9),L9+IF(L$5=1,0.5,1)*(L13-L15)) -> 507496.25 | M16: =IF(M$5=3,IF(M14>0,M13/M14,M9),M9+IF(M$5=1,0.5,1)*(M13-M15)) -> 507496.25 | N16: =IF(N$5=3,IF(N14>0,N13/N14,N9),N9+IF(N$5=1,0.5,1)*(N13-N15)) -> 507425 | O16: =IF(O$5=3,IF(O14>0,O13/O14,O9),O9+IF(O$5=1,0.5,1)*(O13-O15)) -> 507125 | P16: =IF(P$5=3,IF(P14>0,P13/P14,P9),P9+IF(P$5=1,0.5,1)*(P13-P15)) -> 507125 | Q16: =IF(Q$5=3,IF(Q14>0,Q13/Q14,Q9),Q9+IF(Q$5=1,0.5,1)*(Q13-Q15)) -> 507125 | ... JA16: =IF(JA$5=3,IF(JA14>0,JA13/JA14,JA9),JA9+IF(JA$5=1,0.5,1)*(JA13-JA15)) -> 450
A17: ACT | B17: Доля активных: среднемесячная доля фондированных клиентов с ≥1 операцией (сделка, пополнение, покупка продукта или подписки) | C17: % | D17: Вводная | E17: =INDEX(Вводные!$D$13:$F$64,MATCH($A17,Вводные!$A$13:$A$64,0),MATCH(E$3,Вводные!$D$11:$F$11,0))*(1+IF(E$4=$A17,Вводные!$D$5*INDEX(Вводные!$G$13:$G$64,MATCH($A17,Вводные!$A$13:$A$64,0)),0)) -> 0.35 | F17: =INDEX(Вводные!$D$13:$F$64,MATCH($A17,Вводные!$A$13:$A$64,0),MATCH(F$3,Вводные!$D$11:$F$11,0))*(1+IF(F$4=$A17,Вводные!$D$5*INDEX(Вводные!$G$13:$G$64,MATCH($A17,Вводные!$A$13:$A$64,0)),0)) -> 0.55 | G17: =INDEX(Вводные!$D$13:$F$64,MATCH($A17,Вводные!$A$13:$A$64,0),MATCH(G$3,Вводные!$D$11:$F$11,0))*(1+IF(G$4=$A17,Вводные!$D$5*INDEX(Вводные!$G$13:$G$64,MATCH($A17,Вводные!$A$13:$A$64,0)),0)) -> 0.8 | J17: =INDEX(Вводные!$D$13:$F$64,MATCH($A17,Вводные!$A$13:$A$64,0),MATCH(J$3,Вводные!$D$11:$F$11,0))*(1+IF(J$4=$A17,Вводные!$D$5*INDEX(Вводные!$G$13:$G$64,MATCH($A17,Вводные!$A$13:$A$64,0)),0)) -> 0.35 | K17: =INDEX(Вводные!$D$13:$F$64,MATCH($A17,Вводные!$A$13:$A$64,0),MATCH(K$3,Вводные!$D$11:$F$11,0))*(1+IF(K$4=$A17,Вводные!$D$5*INDEX(Вводные!$G$13:$G$64,MATCH($A17,Вводные!$A$13:$A$64,0)),0)) -> 0.35 | L17: =INDEX(Вводные!$D$13:$F$64,MATCH($A17,Вводные!$A$13:$A$64,0),MATCH(L$3,Вводные!$D$11:$F$11,0))*(1+IF(L$4=$A17,Вводные!$D$5*INDEX(Вводные!$G$13:$G$64,MATCH($A17,Вводные!$A$13:$A$64,0)),0)) -> 0.35 | M17: =INDEX(Вводные!$D$13:$F$64,MATCH($A17,Вводные!$A$13:$A$64,0),MATCH(M$3,Вводные!$D$11:$F$11,0))*(1+IF(M$4=$A17,Вводные!$D$5*INDEX(Вводные!$G$13:$G$64,MATCH($A17,Вводные!$A$13:$A$64,0)),0)) -> 0.35 | N17: =INDEX(Вводные!$D$13:$F$64,MATCH($A17,Вводные!$A$13:$A$64,0),MATCH(N$3,Вводные!$D$11:$F$11,0))*(1+IF(N$4=$A17,Вводные!$D$5*INDEX(Вводные!$G$13:$G$64,MATCH($A17,Вводные!$A$13:$A$64,0)),0)) -> 0.35 | O17: =INDEX(Вводные!$D$13:$F$64,MATCH($A17,Вводные!$A$13:$A$64,0),MATCH(O$3,Вводные!$D$11:$F$11,0))*(1+IF(O$4=$A17,Вводные!$D$5*INDEX(Вводные!$G$13:$G$64,MATCH($A17,Вводные!$A$13:$A$64,0)),0)) -> 0.3535 | P17: =INDEX(Вводные!$D$13:$F$64,MATCH($A17,Вводные!$A$13:$A$64,0),MATCH(P$3,Вводные!$D$11:$F$11,0))*(1+IF(P$4=$A17,Вводные!$D$5*INDEX(Вводные!$G$13:$G$64,MATCH($A17,Вводные!$A$13:$A$64,0)),0)) -> 0.35 | Q17: =INDEX(Вводные!$D$13:$F$64,MATCH($A17,Вводные!$A$13:$A$64,0),MATCH(Q$3,Вводные!$D$11:$F$11,0))*(1+IF(Q$4=$A17,Вводные!$D$5*INDEX(Вводные!$G$13:$G$64,MATCH($A17,Вводные!$A$13:$A$64,0)),0)) -> 0.35 | ... JA17: =INDEX(Вводные!$D$13:$F$64,MATCH($A17,Вводные!$A$13:$A$64,0),MATCH(JA$3,Вводные!$D$11:$F$11,0))*(1+IF(JA$4=$A17,Вводные!$D$5*INDEX(Вводные!$G$13:$G$64,MATCH($A17,Вводные!$A$13:$A$64,0)),0)) -> 0.8
A18: ACTIVE | B18: Активные клиенты (среднемесячно) | C18: чел. | D18: N_AVG × ACT | E18: =E16*E17 -> 177493.75 | F18: =F16*F17 -> 8310.5 | G18: =G16*G17 -> 321.6 | H18: =SUM(E18:G18) -> 186125.85 | J18: =J16*J17 -> 177493.75 | K18: =K16*K17 -> 177623.69 | L18: =L16*L17 -> 177623.69 | M18: =M16*M17 -> 177623.69 | N18: =N16*N17 -> 177598.75 | O18: =O16*O17 -> 179268.69 | P18: =P16*P17 -> 177493.75 | Q18: =Q16*Q17 -> 177493.75 | ... JA18: =JA16*JA17 -> 360
A19: AUC | B19: Активы клиентов, среднее за период | C19: у.е. | D19: N_AVG × AUC_PC | E19: =E16*E35 -> 4057000000 | F19: =F16*F35 -> 3022000000 | G19: =G16*G35 -> 10050000000 | H19: =SUM(E19:G19) -> 17129000000 | J19: =J16*J35 -> 4057000000 | K19: =K16*K35 -> 4059970000 | L19: =L16*L35 -> 4059970000 | M19: =M16*M35 -> 4059970000 | N19: =N16*N35 -> 4059400000 | O19: =O16*O35 -> 4057000000 | P19: =P16*P35 -> 4057000000 | Q19: =Q16*Q35 -> 4057000000 | ... JA19: =JA16*JA35 -> 11250000000
A20: R1. Торговые комиссии
A21: TPA | B21: Сделок в месяц на активного клиента | C21: шт./клиент | D21: Вводная | E21: =INDEX(Вводные!$D$13:$F$64,MATCH($A21,Вводные!$A$13:$A$64,0),MATCH(E$3,Вводные!$D$11:$F$11,0))*(1+IF(E$4=$A21,Вводные!$D$5*INDEX(Вводные!$G$13:$G$64,MATCH($A21,Вводные!$A$13:$A$64,0)),0)) -> 6 | F21: =INDEX(Вводные!$D$13:$F$64,MATCH($A21,Вводные!$A$13:$A$64,0),MATCH(F$3,Вводные!$D$11:$F$11,0))*(1+IF(F$4=$A21,Вводные!$D$5*INDEX(Вводные!$G$13:$G$64,MATCH($A21,Вводные!$A$13:$A$64,0)),0)) -> 3.5 | G21: =INDEX(Вводные!$D$13:$F$64,MATCH($A21,Вводные!$A$13:$A$64,0),MATCH(G$3,Вводные!$D$11:$F$11,0))*(1+IF(G$4=$A21,Вводные!$D$5*INDEX(Вводные!$G$13:$G$64,MATCH($A21,Вводные!$A$13:$A$64,0)),0)) -> 130 | J21: =INDEX(Вводные!$D$13:$F$64,MATCH($A21,Вводные!$A$13:$A$64,0),MATCH(J$3,Вводные!$D$11:$F$11,0))*(1+IF(J$4=$A21,Вводные!$D$5*INDEX(Вводные!$G$13:$G$64,MATCH($A21,Вводные!$A$13:$A$64,0)),0)) -> 6 | K21: =INDEX(Вводные!$D$13:$F$64,MATCH($A21,Вводные!$A$13:$A$64,0),MATCH(K$3,Вводные!$D$11:$F$11,0))*(1+IF(K$4=$A21,Вводные!$D$5*INDEX(Вводные!$G$13:$G$64,MATCH($A21,Вводные!$A$13:$A$64,0)),0)) -> 6 | L21: =INDEX(Вводные!$D$13:$F$64,MATCH($A21,Вводные!$A$13:$A$64,0),MATCH(L$3,Вводные!$D$11:$F$11,0))*(1+IF(L$4=$A21,Вводные!$D$5*INDEX(Вводные!$G$13:$G$64,MATCH($A21,Вводные!$A$13:$A$64,0)),0)) -> 6 | M21: =INDEX(Вводные!$D$13:$F$64,MATCH($A21,Вводные!$A$13:$A$64,0),MATCH(M$3,Вводные!$D$11:$F$11,0))*(1+IF(M$4=$A21,Вводные!$D$5*INDEX(Вводные!$G$13:$G$64,MATCH($A21,Вводные!$A$13:$A$64,0)),0)) -> 6 | N21: =INDEX(Вводные!$D$13:$F$64,MATCH($A21,Вводные!$A$13:$A$64,0),MATCH(N$3,Вводные!$D$11:$F$11,0))*(1+IF(N$4=$A21,Вводные!$D$5*INDEX(Вводные!$G$13:$G$64,MATCH($A21,Вводные!$A$13:$A$64,0)),0)) -> 6 | O21: =INDEX(Вводные!$D$13:$F$64,MATCH($A21,Вводные!$A$13:$A$64,0),MATCH(O$3,Вводные!$D$11:$F$11,0))*(1+IF(O$4=$A21,Вводные!$D$5*INDEX(Вводные!$G$13:$G$64,MATCH($A21,Вводные!$A$13:$A$64,0)),0)) -> 6 | P21: =INDEX(Вводные!$D$13:$F$64,MATCH($A21,Вводные!$A$13:$A$64,0),MATCH(P$3,Вводные!$D$11:$F$11,0))*(1+IF(P$4=$A21,Вводные!$D$5*INDEX(Вводные!$G$13:$G$64,MATCH($A21,Вводные!$A$13:$A$64,0)),0)) -> 6.06 | Q21: =INDEX(Вводные!$D$13:$F$64,MATCH($A21,Вводные!$A$13:$A$64,0),MATCH(Q$3,Вводные!$D$11:$F$11,0))*(1+IF(Q$4=$A21,Вводные!$D$5*INDEX(Вводные!$G$13:$G$64,MATCH($A21,Вводные!$A$13:$A$64,0)),0)) -> 6 | ... JA21: =INDEX(Вводные!$D$13:$F$64,MATCH($A21,Вводные!$A$13:$A$64,0),MATCH(JA$3,Вводные!$D$11:$F$11,0))*(1+IF(JA$4=$A21,Вводные!$D$5*INDEX(Вводные!$G$13:$G$64,MATCH($A21,Вводные!$A$13:$A$64,0)),0)) -> 130
A22: TICKET | B22: Средний объём сделки | C22: у.е. | D22: Вводная | E22: =INDEX(Вводные!$D$13:$F$64,MATCH($A22,Вводные!$A$13:$A$64,0),MATCH(E$3,Вводные!$D$11:$F$11,0))*(1+IF(E$4=$A22,Вводные!$D$5*INDEX(Вводные!$G$13:$G$64,MATCH($A22,Вводные!$A$13:$A$64,0)),0)) -> 800 | F22: =INDEX(Вводные!$D$13:$F$64,MATCH($A22,Вводные!$A$13:$A$64,0),MATCH(F$3,Вводные!$D$11:$F$11,0))*(1+IF(F$4=$A22,Вводные!$D$5*INDEX(Вводные!$G$13:$G$64,MATCH($A22,Вводные!$A$13:$A$64,0)),0)) -> 15000 | G22: =INDEX(Вводные!$D$13:$F$64,MATCH($A22,Вводные!$A$13:$A$64,0),MATCH(G$3,Вводные!$D$11:$F$11,0))*(1+IF(G$4=$A22,Вводные!$D$5*INDEX(Вводные!$G$13:$G$64,MATCH($A22,Вводные!$A$13:$A$64,0)),0)) -> 100000 | J22: =INDEX(Вводные!$D$13:$F$64,MATCH($A22,Вводные!$A$13:$A$64,0),MATCH(J$3,Вводные!$D$11:$F$11,0))*(1+IF(J$4=$A22,Вводные!$D$5*INDEX(Вводные!$G$13:$G$64,MATCH($A22,Вводные!$A$13:$A$64,0)),0)) -> 800 | K22: =INDEX(Вводные!$D$13:$F$64,MATCH($A22,Вводные!$A$13:$A$64,0),MATCH(K$3,Вводные!$D$11:$F$11,0))*(1+IF(K$4=$A22,Вводные!$D$5*INDEX(Вводные!$G$13:$G$64,MATCH($A22,Вводные!$A$13:$A$64,0)),0)) -> 800 | L22: =INDEX(Вводные!$D$13:$F$64,MATCH($A22,Вводные!$A$13:$A$64,0),MATCH(L$3,Вводные!$D$11:$F$11,0))*(1+IF(L$4=$A22,Вводные!$D$5*INDEX(Вводные!$G$13:$G$64,MATCH($A22,Вводные!$A$13:$A$64,0)),0)) -> 800 | M22: =INDEX(Вводные!$D$13:$F$64,MATCH($A22,Вводные!$A$13:$A$64,0),MATCH(M$3,Вводные!$D$11:$F$11,0))*(1+IF(M$4=$A22,Вводные!$D$5*INDEX(Вводные!$G$13:$G$64,MATCH($A22,Вводные!$A$13:$A$64,0)),0)) -> 800 | N22: =INDEX(Вводные!$D$13:$F$64,MATCH($A22,Вводные!$A$13:$A$64,0),MATCH(N$3,Вводные!$D$11:$F$11,0))*(1+IF(N$4=$A22,Вводные!$D$5*INDEX(Вводные!$G$13:$G$64,MATCH($A22,Вводные!$A$13:$A$64,0)),0)) -> 800 | O22: =INDEX(Вводные!$D$13:$F$64,MATCH($A22,Вводные!$A$13:$A$64,0),MATCH(O$3,Вводные!$D$11:$F$11,0))*(1+IF(O$4=$A22,Вводные!$D$5*INDEX(Вводные!$G$13:$G$64,MATCH($A22,Вводные!$A$13:$A$64,0)),0)) -> 800 | P22: =INDEX(Вводные!$D$13:$F$64,MATCH($A22,Вводные!$A$13:$A$64,0),MATCH(P$3,Вводные!$D$11:$F$11,0))*(1+IF(P$4=$A22,Вводные!$D$5*INDEX(Вводные!$G$13:$G$64,MATCH($A22,Вводные!$A$13:$A$64,0)),0)) -> 800 | Q22: =INDEX(Вводные!$D$13:$F$64,MATCH($A22,Вводные!$A$13:$A$64,0),MATCH(Q$3,Вводные!$D$11:$F$11,0))*(1+IF(Q$4=$A22,Вводные!$D$5*INDEX(Вводные!$G$13:$G$64,MATCH($A22,Вводные!$A$13:$A$64,0)),0)) -> 808 | ... JA22: =INDEX(Вводные!$D$13:$F$64,MATCH($A22,Вводные!$A$13:$A$64,0),MATCH(JA$3,Вводные!$D$11:$F$11,0))*(1+IF(JA$4=$A22,Вводные!$D$5*INDEX(Вводные!$G$13:$G$64,MATCH($A22,Вводные!$A$13:$A$64,0)),0)) -> 100000
A23: TURN | B23: Оборот клиентов за период | C23: у.е. | D23: ACTIVE × TPA × 12 × TICKET | E23: =E18*E21*12*E22 -> 10223640000 | F23: =F18*F21*12*F22 -> 5235615000 | G23: =G18*G21*12*G22 -> 50169600000 | H23: =SUM(E23:G23) -> 65628855000 | J23: =J18*J21*12*J22 -> 10223640000 | K23: =K18*K21*12*K22 -> 10231124400 | L23: =L18*L21*12*L22 -> 10231124400 | M23: =M18*M21*12*M22 -> 10231124400 | N23: =N18*N21*12*N22 -> 10229688000 | O23: =O18*O21*12*O22 -> 10325876400 | P23: =P18*P21*12*P22 -> 10325876400 | Q23: =Q18*Q21*12*Q22 -> 10325876400 | ... JA23: =JA18*JA21*12*JA22 -> 56160000000
